Submits/RTL_Design_and_Integration_Material/Ibrahim_Verilog_Codes/16_Async_FIFO_Practice/async_fifo_practice.v
module async_fifo_practice(
wr_clk_i, rd_clk_i, rst_i, 
wdata_i, wr_en_i, full_o, wr_error_o, // write 
rdata_o, rd_en_i, empty_o, rd_error_o
);

	parameter DEPTH = 1, WIDTH = 1, PTR_WIDTH = 1;

	input wr_clk_i, rd_clk_i, rst_i, wr_en_i, rd_en_i;
	input [WIDTH-1:0] wdata_i;
	output reg full_o, wr_error_o, empty_o, rd_error_o;
	output reg [WIDTH-1:0] rdata_o;

	// Internal wire declaration 

	reg [PTR_WIDTH-1:0] wr_ptr, rd_ptr;
	reg wr_toggle_f, rd_toggle_f;
	reg [PTR_WIDTH-1:0] wr_ptr_rd_clk, rd_ptr_wr_clk;
	reg wr_toggle_f_rd_clk, rd_toggle_f_wr_clk;
	reg [PTR_WIDTH-1:0] wr_ptr_gray, rd_ptr_gray;

	// mem declaration 

	reg [WIDTH-1:0] mem [DEPTH-1:0]; // mem

	// integer declaration
	integer i;

	/* Steps

	1. [Done] Declare internal pointers. wr_ptr, rd_ptr, wr_toggle_f, rd_toggle_f;
	2. [Done]logic when full and empty occurs.
	3. [Done]logic when wr_error and rd_error occurs.
	4. [Done]two different always module for wr_clk_i and rd_clk_i
	5. [Done]mem declaration 
	6. Gray Code declaration

	wr_en_i = 1, full_o = 0, crosses 15, then wr_toggle_f = 1

	*/

	// Write seq logic
	always @ (posedge wr_clk_i) begin 
		if (rst_i) begin 
			full_o = 0; // will there be non-blocking over here ?
			empty_o = 1;
			wr_error_o = 0;
			rd_error_o = 0;
			rdata_o = 0;
			wr_ptr = 0;
			rd_ptr = 0;
			wr_toggle_f = 0;
			rd_toggle_f = 0;
			wr_ptr_rd_clk = 0;
			rd_ptr_wr_clk = 0;
			wr_toggle_f_rd_clk = 0;
			rd_toggle_f_wr_clk = 0;
			wr_ptr_gray = 0;
			rd_ptr_gray = 0;
			for (i=0; i<DEPTH; i=i+1) begin 
				mem[i] = 0;
			end
		end
		else begin 
		wr_error_o = 0;
			if (wr_en_i) begin 
				if (full_o == 0) begin // Not Full
					mem [wr_ptr] = wdata_i;
					wr_ptr = wr_ptr + 1;
					wr_ptr_gray = {wr_ptr[PTR_WIDTH-1], wr_ptr[PTR_WIDTH-1:1] ^ wr_ptr[PTR_WIDTH-2:0]};
					if (wr_ptr == DEPTH) begin // toggle wr_ptr
						wr_toggle_f = ~wr_toggle_f;
					end 
				end
				else begin // Full
					wr_error_o = 1;
				end 
			end
		end 
	end

	//read seq logic
	always @ (posedge rd_clk_i) begin 
		if (rst_i != 1) begin
			rd_error_o = 0;
			if (rd_en_i) begin 
				if (empty_o == 0) begin // Not empty
					rdata_o = mem[rd_ptr];
					rd_ptr = rd_ptr + 1;
					rd_ptr_gray = {rd_ptr[PTR_WIDTH-1], rd_ptr[PTR_WIDTH-1:1] ^ rd_ptr[PTR_WIDTH-2:0]};
					if (rd_ptr == DEPTH) begin // toggle rd_ptr
						rd_toggle_f = ~rd_toggle_f;
					end 
				end 
				else begin // empty
					rd_error_o = 1;
				end 
			end 
		end
	end 

	// logic to generate full and empty

	always @ (*) begin 
		empty_o = 0;
		full_o = 0;
		// full	
		if (rd_ptr_wr_clk == wr_ptr_gray) begin 
			if (rd_toggle_f_wr_clk != wr_toggle_f) full_o = 1;
		end
		// empty		
		if (rd_ptr_gray == wr_ptr_rd_clk) begin 
			if (rd_toggle_f == wr_toggle_f_rd_clk) empty_o = 1;
		end	
		
	end 


	// Now the problem is rd_clk_i and wr_clk_i does not 
	// have same frequency. Hence we need to define synchronizers

	// full happens on wr_clk_i, hence we need to bring rd_ptr
	// and rd_toggle_f to wr_clk_i frquency
	// V.V for empty 

	always @ (posedge wr_clk_i) begin 
		rd_ptr_wr_clk <= rd_ptr_gray;
		rd_toggle_f_wr_clk <= rd_toggle_f;
	end

	always @ (posedge rd_clk_i) begin 
		wr_ptr_rd_clk <= wr_ptr_gray;
		wr_toggle_f_rd_clk <= wr_toggle_f;
	end 

endmodule

Submits/RTL_Design_and_Integration_Material/Ibrahim_Verilog_Codes/16_Async_FIFO_Practice/tb_practice.v
`include "async_fifo_practice.v"
module tb();

	parameter DEPTH=16, WIDTH=8, PTR_WIDTH=4;
	parameter WR_CK_TP=10, RD_CLK_TP=14;
	parameter MAX_WR_DLY=10, MAX_RD_DLY=10;
	parameter NUM_TXS=10;

	//wr_ptr is internal to the design 
	reg rd_clk_i, wr_clk_i, rst_i, wr_en_i, rd_en_i;
	reg [WIDTH-1:0] wdata_i;
	wire wr_error_o, rd_error_o, full_o, empty_o;
	wire [WIDTH-1:0] rdata_o;

	integer num_wr, num_rd;
	integer i, j, k, l;
	integer wr_delay, rd_delay;
	integer seed;
	reg [30*8:1] testname;

	// instantiate the design
	async_fifo_practice dut (.rd_clk_i(rd_clk_i), .wr_clk_i(wr_clk_i), .rst_i(rst_i), .wdata_i(wdata_i), .wr_en_i(wr_en_i), .wr_error_o(wr_error_o), .rdata_o(rdata_o), .full_o(full_o), .empty_o(empty_o), .rd_en_i(rd_en_i), .rd_error_o(rd_error_o));

	// generate clk
	initial begin 
		wr_clk_i = 0;
		forever #(WR_CK_TP/2.0) wr_clk_i = ~wr_clk_i;
		//don't code anything after forever in any language
	end
	
	initial begin 
		rd_clk_i = 0;
		forever #(RD_CLK_TP/2.0) rd_clk_i = ~rd_clk_i;
		//don't code anything after forever in any language
	end	

	// generate test inputs
	initial begin 
		$value$plusargs("testname=%s", testname);
		rst_i = 1; 
		seed = 415341;
		// drive design inputs to 0
		wdata_i = 0;
		wr_en_i = 0;
		rd_en_i = 0;
		// #20;
		@(posedge wr_clk_i); // holding
		rst_i = 0; // releasing
		// apply stimulus: write to the FIFO and read from the FIFO
		case (testname) 
			"test_full": begin 
				write_fifo(DEPTH);
			end
			"test_empty": begin
				write_fifo(DEPTH);
				read_fifo(DEPTH);
			end
			"test_full_error": begin 
				write_fifo(DEPTH+1);
			end
			"test_empty_error": begin 
				write_fifo(DEPTH);
				read_fifo(DEPTH+1);
			end
			"test_concurrent_wr_rd": begin 
				fork
					begin 
						for (k=0; k < NUM_TXS; k=k+1) begin //500 people going into bank in whole day
							write_fifo(1); // write one data into FIFO
							//wr_delay = $urandom_range(1, MAX_WR_DLY); //1 to 10 minutes between one person to next person
							wr_delay = 1 + $random(seed)%MAX_WR_DLY; // random number 1 to 10
							repeat (wr_delay) @(posedge wr_clk_i); // applying delay for wr_delay number of times clock edges
						end
					end 
					begin
						for (l=0; l < NUM_TXS; l=l+1) begin //500 people going out from the bank
							read_fifo(1); // read one data from FIFO
							//rd_delay = $urandom_range(1, MAX_RD_DLY); //1 to 10 minutes between one person to next person
							rd_delay = 1 + $random(seed)%MAX_RD_DLY; // random number 1 to 10
							repeat (rd_delay) @(posedge rd_clk_i); // applying delay for rd_delay number of times clock edges
							
						end
					end
				join 
			end
		endcase
		
		#50;
		$finish;
	end

	task write_fifo(input integer num_wr);
		begin
			for (i = 0; i < num_wr; i=i+1) begin 
				@(posedge wr_clk_i) 
				wr_en_i = 1;
				wdata_i = $random;
			end 	
			@(posedge wr_clk_i);
			wr_en_i = 0;
			wdata_i = 0;
		end
	endtask

	task read_fifo(input integer num_rd);
		begin
			for (j = 0; j < num_rd; j=j+1) begin 
				@(posedge rd_clk_i) rd_en_i = 1;	
			end
			@(posedge rd_clk_i);
			rd_en_i = 0;
		end
	endtask

	// dump files
	initial begin
		$dumpfile("waves.vcd");
		$dumpvars;
		
	end 

endmodule

Submits/RTL_Design_and_Integration_Material/Ibrahim_Verilog_Codes/16_Async_FIFO_Practice/waves.vcd
$date
	Sun May 21 22:40:36 2023
$end
$version
	QuestaSim Version 10.6c
$end
$timescale
	1ns
$end

$scope module tb $end
$var parameter 32 ! DEPTH $end
$var parameter 32 " WIDTH $end
$var parameter 32 # PTR_WIDTH $end
$var parameter 32 $ WR_CK_TP $end
$var parameter 32 % RD_CLK_TP $end
$var parameter 32 & MAX_WR_DLY $end
$var parameter 32 ' MAX_RD_DLY $end
$var parameter 32 ( NUM_TXS $end
$var reg 1 ) rd_clk_i $end
$var reg 1 * wr_clk_i $end
$var reg 1 + rst_i $end
$var reg 1 , wr_en_i $end
$var reg 1 - rd_en_i $end
$var reg 8 . wdata_i [7:0] $end
$var wire 1 / wr_error_o $end
$var wire 1 0 rd_error_o $end
$var wire 1 1 full_o $end
$var wire 1 2 empty_o $end
$var wire 1 3 rdata_o [7] $end
$var wire 1 4 rdata_o [6] $end
$var wire 1 5 rdata_o [5] $end
$var wire 1 6 rdata_o [4] $end
$var wire 1 7 rdata_o [3] $end
$var wire 1 8 rdata_o [2] $end
$var wire 1 9 rdata_o [1] $end
$var wire 1 : rdata_o [0] $end
$var integer 32 ; num_wr $end
$var integer 32 < num_rd $end
$var integer 32 = i $end
$var integer 32 > j $end
$var integer 32 ? k $end
$var integer 32 @ l $end
$var integer 32 A wr_delay $end
$var integer 32 B rd_delay $end
$var integer 32 C seed $end
$var reg 240 D testname [240:1] $end

$scope task write_fifo $end
$var integer 32 E num_wr $end
$upscope $end

$scope task read_fifo $end
$var integer 32 F num_rd $end
$upscope $end

$scope module dut $end
$var parameter 32 G DEPTH $end
$var parameter 32 H WIDTH $end
$var parameter 32 I PTR_WIDTH $end
$var wire 1 J wr_clk_i $end
$var wire 1 K rd_clk_i $end
$var wire 1 L rst_i $end
$var wire 1 M wr_en_i $end
$var wire 1 N rd_en_i $end
$var wire 1 O wdata_i [7] $end
$var wire 1 P wdata_i [6] $end
$var wire 1 Q wdata_i [5] $end
$var wire 1 R wdata_i [4] $end
$var wire 1 S wdata_i [3] $end
$var wire 1 T wdata_i [2] $end
$var wire 1 U wdata_i [1] $end
$var wire 1 V wdata_i [0] $end
$var reg 1 W full_o $end
$var reg 1 X wr_error_o $end
$var reg 1 Y empty_o $end
$var reg 1 Z rd_error_o $end
$var reg 8 [ rdata_o [7:0] $end
$var reg 4 \ wr_ptr [3:0] $end
$var reg 4 ] rd_ptr [3:0] $end
$var reg 1 ^ wr_toggle_f $end
$var reg 1 _ rd_toggle_f $end
$var reg 4 ` wr_ptr_rd_clk [3:0] $end
$var reg 4 a rd_ptr_wr_clk [3:0] $end
$var reg 1 b wr_toggle_f_rd_clk $end
$var reg 1 c rd_toggle_f_wr_clk $end
$var reg 4 d wr_ptr_gray [3:0] $end
$var reg 4 e rd_ptr_gray [3:0] $end
$var integer 32 f i $end
$upscope $end
$upscope $end
$enddefinitions $end
#0
$dumpvars
0)
0*
1+
0,
0-
b0 .
b11101000110010101110011011101000101111101100011011011110110111001100011011101010111001001110010011001010110111001110100010111110111011101110010010111110111001001100100 D
xW
xX
xY
xZ
bx [
bx \
bx ]
x^
x_
bx `
bx a
xb
xc
bx d
bx e
b10000 !
b1000 "
b100 #
b1010 $
b1110 %
b1010 &
b1010 '
b1010 (
b10000 G
b1000 H
b100 I
bx ;
bx <
bx =
bx >
bx ?
bx @
bx A
bx B
b1100101011001101101 C
bx f
bx E
bx F
x/
x0
x1
x2
x:
x9
x8
x7
x6
x5
x4
x3
0N
0M
0V
0U
0T
0S
0R
0Q
0P
0O
1L
0J
0K
$end
#5
1*
1J
0W
1Y
0X
0Z
b0 [
b0 \
b0 ]
0^
0_
b0 `
b0 a
0b
0c
b0 d
b0 e
b0 f
b1 f
b10 f
b11 f
b100 f
b101 f
b110 f
b111 f
b1000 f
b1001 f
b1010 f
b1011 f
b1100 f
b1101 f
b1110 f
b1111 f
b10000 f
0+
b0 ?
b1 E
b0 =
b0 @
b1 F
b0 >
01
12
0/
00
0:
09
08
07
06
05
04
03
0L
0Y
1Y
#7
1)
1K
1-
b1 >
1N
#10
0*
0J
#14
0)
0K
#15
1*
1J
1,
b100100 .
b1 =
1M
1T
1Q
#20
0*
0J
#21
1)
1K
1Z
0-
b10101101111000111011111001001010 C
b10 B
10
0N
#25
1*
1J
b1 \
b1 d
0,
b0 .
b10001110010100110010001101000011 C
b11 A
0M
0T
0Q
0Y
1Y
#28
0)
0K
#30
0*
0J
#35
1)
1*
1K
1J
0Z
00
b1 `
0Y
02
#40
0*
0J
#42
0)
0K
#45
1*
1J
#49
1)
1K
b1 @
b0 >
#50
0*
0J
#55
1*
1J
b1 ?
b0 =
#56
0)
0K
#60
0*
0J
#63
1)
1K
1-
b1 >
1N
#65
1*
1J
1,
b10101001 .
b1 =
1M
1V
1S
1Q
1O
#70
0)
0*
0K
0J
#75
1*
1J
b10 \
b11 d
0,
b0 .
b1010100101000001010001110101000 C
b0 A
b10 ?
b0 =
0M
0V
0S
0Q
0O
#77
1)
1K
b100100 [
b1 ]
b1 e
0-
b10010000100110101001010110001001 C
b1010 B
18
15
0N
1Y
12
b11 `
0Y
02
#80
0*
0J
#84
0)
0K
#85
1*
1J
1,
b1110101 .
b1 =
1M
1V
1T
1R
1Q
1P
b1 a
#90
0*
0J
#91
1)
1K
#95
1*
1J
b11 \
b10 d
0,
b0 .
b111010111010101011001110110110 C
b11111111111111111111111111111000 A
b11 ?
b0 =
0M
0V
0T
0R
0Q
0P
#98
0)
0K
#100
0*
0J
#105
1)
1*
1K
1J
1,
b10011001 .
b1 =
1M
1V
1S
1R
1O
b10 `
#110
0*
0J
#112
0)
0K
#115
1*
1J
b100 \
b110 d
0,
b0 .
b11001100110010000010011010111111 C
b110 A
0M
0V
0S
0R
0O
#119
1)
1K
b110 `
#120
0*
0J
#125
1*
1J
#126
0)
0K
#130
0*
0J
#133
1)
1K
#135
1*
1J
#140
0)
0*
0K
0J
#145
1*
1J
#147
1)
1K
#150
0*
0J
#154
0)
0K
#155
1*
1J
#160
0*
0J
#161
1)
1K
#165
1*
1J
#168
0)
0K
#170
0*
0J
#175
1)
1*
1K
1J
b100 ?
b0 =
#180
0*
0J
#182
0)
0K
#185
1*
1J
1,
b10011001 .
b1 =
1M
1V
1S
1R
1O
#189
1)
1K
#190
0*
0J
#195
1*
1J
b101 \
b111 d
0,
b0 .
b1001100111111011011100111110100 C
b11111111111111111111111111111100 A
b101 ?
b0 =
0M
0V
0S
0R
0O
#196
0)
0K
#200
0*
0J
#203
1)
1K
b111 `
#205
1*
1J
1,
b10000111 .
b1 =
1M
1V
1U
1T
1O
#210
0)
0*
0K
0J
#215
1*
1J
b110 \
b101 d
0,
b0 .
b1000011100100110100110001100101 C
b0 A
b110 ?
b0 =
0M
0V
0U
0T
0O
#217
1)
1K
b10 @
b0 >
b101 `
#220
0*
0J
#224
0)
0K
#225
1*
1J
1,
b11001000 .
b1 =
1M
1S
1P
1O
#230
0*
0J
#231
1)
1K
1-
b1 >
1N
#235
1*
1J
b111 \
b100 d
0,
b0 .
b11100100001110100100110111100010 C
b11 A
0M
0S
0P
0O
#238
0)
0K
#240
0*
0J
#245
1)
1*
1K
1J
b10101001 [
b10 ]
b11 e
0-
b110100001101101011111111011 C
b11111111111111111111111111111000 B
b11 @
b0 >
1:
08
17
13
0N
b100 `
#250
0*
0J
#252
0)
0K
#255
1*
1J
b11 a
#259
1)
1K
1-
b1 >
1N
#260
0*
0J
#265
1*
1J
b111 ?
b0 =
#266
0)
0K
#270
0*
0J
#273
1)
1K
b1110101 [
b11 ]
b10 e
0-
b11101010111011011011001100000000 C
b1000 B
18
07
16
14
03
0N
#275
1*
1J
1,
b11001010 .
b1 =
1M
1U
1S
1P
1O
b10 a
#280
0)
0*
0K
0J
#285
1*
1J
b1000 \
b1100 d
0,
b0 .
b11100101011011110101011100000001 C
b1001 A
0M
0U
0S
0P
0O
#287
1)
1K
b1100 `
#290
0*
0J
#294
0)
0K
#295
1*
1J
#300
0*
0J
#301
1)
1K
#305
1*
1J
#308
0)
0K
#310
0*
0J
#315
1)
1*
1K
1J
#320
0*
0J
#322
0)
0K
#325
1*
1J
#329
1)
1K
#330
0*
0J
#335
1*
1J
#336
0)
0K
#340
0*
0J
#343
1)
1K
#345
1*
1J
#350
0)
0*
0K
0J
#355
1*
1J
#357
1)
1K
#360
0*
0J
#364
0)
0K
#365
1*
1J
#370
0*
0J
#371
1)
1K
#375
1*
1J
b1000 ?
b0 =
#378
0)
0K
#380
0*
0J
#385
1)
1*
1K
1J
b100 @
b0 >
1,
b1110001 .
b1 =
1M
1V
1R
1Q
1P
#390
0*
0J
#392
0)
0K
#395
1*
1J
b1001 \
b1101 d
0,
b0 .
b10111000100101001011100011001110 C
b1010 A
0M
0V
0R
0Q
0P
#399
1)
1K
1-
b1 >
1N
b1101 `
#400
0*
0J
#405
1*
1J
#406
0)
0K
#410
0*
0J
#413
1)
1K
b10011001 [
b100 ]
b110 e
0-
b10101010010000111001011110111 C
b11111111111111111111111111111111 B
b101 @
b0 >
08
17
05
04
13
0N
#415
1*
1J
b110 a
#420
0)
0*
0K
0J
#425
1*
1J
#427
1)
1K
1-
b1 >
1N
#430
0*
0J
#434
0)
0K
#435
1*
1J
#440
0*
0J
#441
1)
1K
b101 ]
b111 e
0-
b101011110100011001101011001100 C
b11111111111111111111111111111110 B
b110 @
b0 >
0N
#445
1*
1J
b111 a
#448
0)
0K
#450
0*
0J
#455
1)
1*
1K
1J
1-
b1 >
1N
#460
0*
0J
#462
0)
0K
#465
1*
1J
#469
1)
1K
b10000111 [
b110 ]
b101 e
0-
b1010110100000010101000101011101 C
b111 @
b0 >
19
18
07
06
0N
#470
0*
0J
#475
1*
1J
b101 a
#476
0)
0K
#480
0*
0J
#483
1)
1K
1-
b1 >
1N
#485
1*
1J
#490
0)
0*
0K
0J
#495
1*
1J
b1001 ?
b0 =
#497
1)
1K
b11001000 [
b111 ]
b100 e
0-
b101000000011001110000001111010 C
b1 B
0:
09
08
17
14
0N
#500
0*
0J
#504
0)
0K
#505
1*
1J
1,
b110100 .
b1 =
1M
1T
1R
1Q
b100 a
#510
0*
0J
#511
1)
1K
b1000 @
b0 >
#515
1*
1J
b1010 \
b1111 d
0,
b0 .
b10011010001011111111001110110011 C
b1 A
0M
0T
0R
0Q
#518
0)
0K
#520
0*
0J
#525
1)
1*
1K
1J
1-
b1 >
b1010 ?
1N
b1111 `
#530
0*
0J
#532
0)
0K
#535
1*
1J
#539
1)
1K
b11001010 [
b1000 ]
b1100 e
0-
b11011011011110010011110101011000 C
b11 B
19
0N
#540
0*
0J
#545
1*
1J
b1100 a
#546
0)
0K
#550
0*
0J
#553
1)
1K
#555
1*
1J
#560
0)
0*
0K
0J
#565
1*
1J
#567
1)
1K
#570
0*
0J
#574
0)
0K
#575
1*
1J
#580
0*
0J
#581
1)
1K
b1001 @
b0 >
#585
1*
1J
#588
0)
0K
#590
0*
0J
#595
1)
1*
1K
1J
1-
b1 >
1N
#600
0*
0J
#602
0)
0K
#605
1*
1J
#609
1)
1K
b1110001 [
b1001 ]
b1101 e
0-
b100101100010111001011101111001 C
b11111111111111111111111111111100 B
b1010 @
1:
09
07
16
15
03
0N
#610
0*
0J
#615
1*
1J
b1101 a
