Submits/RTL_Design_and_Integration_Material/Verilog_codes/31_Asynchronous_FIFO/async_fifo.v
module async_fifo(
	// write interface
	rd_clk_i, wr_clk_i, rst_i, wdata_i, wr_en_i, wr_error_o,
	// read interface	
	rdata_o, full_o, empty_o, rd_en_i, rd_error_o
	
);

parameter DEPTH=16, WIDTH=8, PTR_WIDTH=4;

//wr_ptr is internal to the design 
input rd_clk_i, wr_clk_i, rst_i, wr_en_i, rd_en_i;
input [WIDTH-1:0] wdata_i;
output reg wr_error_o, rd_error_o, full_o, empty_o;
output reg [WIDTH-1:0] rdata_o;

// mem declaration 
reg [WIDTH-1:0] mem [DEPTH-1:0];

// internal signals
reg [PTR_WIDTH-1:0] rd_ptr, wr_ptr;
reg wr_toggle_f, rd_toggle_f;

reg [PTR_WIDTH-1:0] rd_ptr_gray, wr_ptr_gray;
reg [PTR_WIDTH-1:0] rd_ptr_gray_wr_clk, wr_ptr_gray_rd_clk;

reg wr_toggle_f_rd_clk, rd_toggle_f_wr_clk;

integer i; // Remember to remove unwanted integers

// write always block
always @(posedge wr_clk_i) begin 
	if (rst_i == 1) begin // reset should happen w.r.t write clock domain
		wr_error_o = 0;
		rd_error_o = 0;
		full_o = 0;
		empty_o = 1;
		rdata_o = 0;
		rd_ptr = 0;
		wr_ptr = 0;
		rd_ptr_gray = 0;
		wr_ptr_gray = 0;
		rd_ptr_gray_wr_clk = 0;
		wr_ptr_gray_rd_clk = 0;	
		wr_toggle_f = 0;
		rd_toggle_f = 0;
		wr_toggle_f_rd_clk = 0;
		rd_toggle_f_wr_clk = 0;		
		// clear the memory
		for (i=0; i<DEPTH; i=i+1) begin 
			mem[i] = 0;
		end
	end	

	else begin 
		wr_error_o = 0;
		if (wr_en_i == 1) begin 
			if (full_o == 1) begin 
				wr_error_o = 1;
			end
			else begin 
				// store data into memory
				mem[wr_ptr] = wdata_i;
				// increment the wr_ptr
				if (wr_ptr == DEPTH-1) begin 
					wr_toggle_f = ~wr_toggle_f;
				end
				wr_ptr = wr_ptr + 1;
				wr_ptr_gray = {wr_ptr[PTR_WIDTH-1], (wr_ptr[PTR_WIDTH-1:1] ^ wr_ptr[PTR_WIDTH-2:0])}; // Gray code conversion 
			end
		end

	end 
end 

// read always block
always @(posedge rd_clk_i) begin 
	if (rst_i != 1) begin
		rd_error_o = 0;
		if (rd_en_i == 1) begin
			if (empty_o == 1) rd_error_o = 1;
			else begin 
				rdata_o = mem[rd_ptr];
				// increment the rd_ptr
				if (rd_ptr == DEPTH-1) rd_toggle_f = ~rd_toggle_f;
				rd_ptr = rd_ptr + 1;
				rd_ptr_gray = {rd_ptr[PTR_WIDTH-1], (rd_ptr[PTR_WIDTH-1:1] ^ rd_ptr[PTR_WIDTH-2:0])}; // Gray code conversion 
			end 		
		end
	end
end 


always @(posedge rd_clk_i) begin 
	wr_ptr_gray_rd_clk <= wr_ptr_gray;
	wr_toggle_f_rd_clk <= wr_toggle_f;
end 

always @(posedge wr_clk_i) begin 
	rd_ptr_gray_wr_clk <= rd_ptr_gray;
	rd_toggle_f_wr_clk <= rd_toggle_f;
end

// logic to create empty and full condition
/*
wr_ptr and rd_ptr are changing in different clock domains and hence cannot 
be compared directly
*/

always @(*) begin 
	empty_o = 0;
	full_o = 0;
	// full
	if (wr_ptr_gray == rd_ptr_gray_wr_clk) begin 
		if (wr_toggle_f != rd_toggle_f_wr_clk) full_o = 1;
	end
	// empty
	if (wr_ptr_gray_rd_clk == rd_ptr_gray) begin 
		if (wr_toggle_f_rd_clk == rd_toggle_f) empty_o = 1;	
	end	
end

endmodule

/*
- Aynchronous FIFO we have developed will work in RTL simulations without any issues.
- If we synthesize and make a chip out of it => it might have some glitch conditions.
- wr_ptr is 4 bit variable, when change happens from 0111 to 1000 there will be a temporary change from 0111 -> 0110 -> 0100 -> 0000 -> 1000
- when wr_ptr during this temporary change becomes 0000, it will match to rd_ptr which is also 0000 hence unwanted empty condition will be generated
- To resolve this issue we have to use grey code counter which changes only one bit while going from one value to another value => hence there
is no possibility of intermediary states => thus there is no chance of glitch
*/

Submits/RTL_Design_and_Integration_Material/Verilog_codes/31_Asynchronous_FIFO/tb_async_fifo.v
`include "async_fifo.v"
module tb();

	parameter DEPTH=16, WIDTH=8, PTR_WIDTH=4;
	parameter WR_CK_TP=10, RD_CLK_TP=14;
	parameter MAX_WR_DLY=10, MAX_RD_DLY=10;
	parameter NUM_TXS=100;

	//wr_ptr is internal to the design 
	reg rd_clk_i, wr_clk_i, rst_i, wr_en_i, rd_en_i;
	reg [WIDTH-1:0] wdata_i;
	wire wr_error_o, rd_error_o, full_o, empty_o;
	wire [WIDTH-1:0] rdata_o;

	integer num_wr, num_rd;
	integer i, j, k, l;
	integer wr_delay, rd_delay;
	integer seed;
	reg [30*8:1] testname;

	// instantiate the design
	async_fifo dut (.rd_clk_i(rd_clk_i), .wr_clk_i(wr_clk_i), .rst_i(rst_i), .wdata_i(wdata_i), .wr_en_i(wr_en_i), .wr_error_o(wr_error_o), .rdata_o(rdata_o), .full_o(full_o), .empty_o(empty_o), .rd_en_i(rd_en_i), .rd_error_o(rd_error_o));

	// generate clk
	initial begin 
		wr_clk_i = 0;
		forever #(WR_CK_TP/2.0) wr_clk_i = ~wr_clk_i;
		//don't code anything after forever in any language
	end
	
	initial begin 
		rd_clk_i = 0;
		forever #(RD_CLK_TP/2.0) rd_clk_i = ~rd_clk_i;
		//don't code anything after forever in any language
	end	

	// generate test inputs
	initial begin 
		$value$plusargs("testname=%s", testname);
		rst_i = 1; 
		seed = 415341;
		// drive design inputs to 0
		wdata_i = 0;
		wr_en_i = 0;
		rd_en_i = 0;
		// #20;
		@(posedge wr_clk_i); // holding
		rst_i = 0; // releasing
		// apply stimulus: write to the FIFO and read from the FIFO
		case (testname) 
			"test_full": begin 
				write_fifo(DEPTH);
			end
			"test_empty": begin
				write_fifo(DEPTH);
				read_fifo(DEPTH);
			end
			"test_full_error": begin 
				write_fifo(DEPTH+1);
			end
			"test_empty_error": begin 
				write_fifo(DEPTH);
				read_fifo(DEPTH+1);
			end
			"test_concurrent_wr_rd": begin 
				fork
					begin 
						for (k=0; k < NUM_TXS; k=k+1) begin //500 people going into bank in whole day
							write_fifo(1); // write one data into FIFO
							//wr_delay = $urandom_range(1, MAX_WR_DLY); //1 to 10 minutes between one person to next person
							wr_delay = 1 + $random(seed)%MAX_WR_DLY; // random number 1 to 10
							repeat (wr_delay) @(posedge wr_clk_i); // applying delay for wr_delay number of times clock edges
						end
					end 
					begin
						for (l=0; l < NUM_TXS; l=l+1) begin //500 people going out from the bank
							read_fifo(1); // read one data from FIFO
							//rd_delay = $urandom_range(1, MAX_RD_DLY); //1 to 10 minutes between one person to next person
							rd_delay = 1 + $random(seed)%MAX_RD_DLY; // random number 1 to 10
							repeat (rd_delay) @(posedge rd_clk_i); // applying delay for rd_delay number of times clock edges
							
						end
					end
				join 
			end
		endcase
		
		#50;
		$finish;
	end

	task write_fifo(input integer num_wr);
		begin
			for (i = 0; i < num_wr; i=i+1) begin 
				@(posedge wr_clk_i) 
				wr_en_i = 1;
				wdata_i = $random;
			end 	
			@(posedge wr_clk_i);
			wr_en_i = 0;
			wdata_i = 0;
		end
	endtask

	task read_fifo(input integer num_rd);
		begin
			for (j = 0; j < num_rd; j=j+1) begin 
				@(posedge rd_clk_i) rd_en_i = 1;	
			end
			@(posedge rd_clk_i);
			rd_en_i = 0;
		end
	endtask

	// dump files
	initial begin
		$dumpfile("waves.vcd");
		$dumpvars;
		
	end 

endmodule

Submits/RTL_Design_and_Integration_Material/Verilog_codes/31_Asynchronous_FIFO/waves.vcd
$date
	Sat Apr 29 17:38:07 2023
$end
$version
	QuestaSim Version 10.6c
$end
$timescale
	1ns
$end

$scope module tb $end
$var parameter 32 ! DEPTH $end
$var parameter 32 " WIDTH $end
$var parameter 32 # PTR_WIDTH $end
$var parameter 32 $ WR_CK_TP $end
$var parameter 32 % RD_CLK_TP $end
$var parameter 32 & MAX_WR_DLY $end
$var parameter 32 ' MAX_RD_DLY $end
$var parameter 32 ( NUM_TXS $end
$var reg 1 ) rd_clk_i $end
$var reg 1 * wr_clk_i $end
$var reg 1 + rst_i $end
$var reg 1 , wr_en_i $end
$var reg 1 - rd_en_i $end
$var reg 8 . wdata_i [7:0] $end
$var wire 1 / wr_error_o $end
$var wire 1 0 rd_error_o $end
$var wire 1 1 full_o $end
$var wire 1 2 empty_o $end
$var wire 1 3 rdata_o [7] $end
$var wire 1 4 rdata_o [6] $end
$var wire 1 5 rdata_o [5] $end
$var wire 1 6 rdata_o [4] $end
$var wire 1 7 rdata_o [3] $end
$var wire 1 8 rdata_o [2] $end
$var wire 1 9 rdata_o [1] $end
$var wire 1 : rdata_o [0] $end
$var integer 32 ; num_wr $end
$var integer 32 < num_rd $end
$var integer 32 = i $end
$var integer 32 > j $end
$var integer 32 ? k $end
$var integer 32 @ l $end
$var integer 32 A wr_delay $end
$var integer 32 B rd_delay $end
$var integer 32 C seed $end
$var reg 240 D testname [240:1] $end

$scope task write_fifo $end
$var integer 32 E num_wr $end
$upscope $end

$scope task read_fifo $end
$var integer 32 F num_rd $end
$upscope $end

$scope module dut $end
$var parameter 32 G DEPTH $end
$var parameter 32 H WIDTH $end
$var parameter 32 I PTR_WIDTH $end
$var wire 1 J rd_clk_i $end
$var wire 1 K wr_clk_i $end
$var wire 1 L rst_i $end
$var wire 1 M wr_en_i $end
$var wire 1 N rd_en_i $end
$var wire 1 O wdata_i [7] $end
$var wire 1 P wdata_i [6] $end
$var wire 1 Q wdata_i [5] $end
$var wire 1 R wdata_i [4] $end
$var wire 1 S wdata_i [3] $end
$var wire 1 T wdata_i [2] $end
$var wire 1 U wdata_i [1] $end
$var wire 1 V wdata_i [0] $end
$var reg 1 W wr_error_o $end
$var reg 1 X rd_error_o $end
$var reg 1 Y full_o $end
$var reg 1 Z empty_o $end
$var reg 8 [ rdata_o [7:0] $end
$var reg 4 \ rd_ptr [3:0] $end
$var reg 4 ] wr_ptr [3:0] $end
$var reg 1 ^ wr_toggle_f $end
$var reg 1 _ rd_toggle_f $end
$var reg 4 ` rd_ptr_gray [3:0] $end
$var reg 4 a wr_ptr_gray [3:0] $end
$var reg 4 b rd_ptr_gray_wr_clk [3:0] $end
$var reg 4 c wr_ptr_gray_rd_clk [3:0] $end
$var reg 1 d wr_toggle_f_rd_clk $end
$var reg 1 e rd_toggle_f_wr_clk $end
$var integer 32 f i $end
$upscope $end
$upscope $end
$enddefinitions $end
#0
$dumpvars
0)
0*
1+
0,
0-
b0 .
b11101000110010101110011011101000101111101100011011011110110111001100011011101010111001001110010011001010110111001110100010111110111011101110010010111110111001001100100 D
xW
xX
xY
xZ
bx [
bx \
bx ]
x^
x_
bx `
bx a
bx b
bx c
xd
xe
b10000 !
b1000 "
b100 #
b1010 $
b1110 %
b1010 &
b1010 '
b1100100 (
b10000 G
b1000 H
b100 I
bx ;
bx <
bx =
bx >
bx ?
bx @
bx A
bx B
b1100101011001101101 C
bx f
bx E
bx F
x/
x0
x1
x2
x:
x9
x8
x7
x6
x5
x4
x3
0N
0M
0V
0U
0T
0S
0R
0Q
0P
0O
1L
0K
0J
$end
#5
1*
1K
0W
0X
0Y
1Z
b0 [
b0 \
b0 ]
b0 `
b0 a
b0 b
b0 c
0^
0_
0d
0e
b0 f
b1 f
b10 f
b11 f
b100 f
b101 f
b110 f
b111 f
b1000 f
b1001 f
b1010 f
b1011 f
b1100 f
b1101 f
b1110 f
b1111 f
b10000 f
0+
b0 ?
b1 E
b0 =
b0 @
b1 F
b0 >
0/
00
01
12
0:
09
08
07
06
05
04
03
0L
0Z
1Z
#7
1)
1J
1-
b1 >
1N
#10
0*
0K
#14
0)
0J
#15
1*
1K
1,
b100100 .
b1 =
1M
1T
1Q
#20
0*
0K
#21
1)
1J
1X
0-
b10101101111000111011111001001010 C
b10 B
10
0N
#25
1*
1K
b1 ]
b1 a
0,
b0 .
b10001110010100110010001101000011 C
b11 A
0M
0T
0Q
0Z
1Z
#28
0)
0J
#30
0*
0K
#35
1)
1*
1J
1K
0X
00
b1 c
0Z
02
#40
0*
0K
#42
0)
0J
#45
1*
1K
#49
1)
1J
b1 @
b0 >
#50
0*
0K
#55
1*
1K
b1 ?
b0 =
#56
0)
0J
#60
0*
0K
#63
1)
1J
1-
b1 >
1N
#65
1*
1K
1,
b10101001 .
b1 =
1M
1V
1S
1Q
1O
#70
0)
0*
0J
0K
#75
1*
1K
b10 ]
b11 a
0,
b0 .
b1010100101000001010001110101000 C
b0 A
b10 ?
b0 =
0M
0V
0S
0Q
0O
#77
1)
1J
b100100 [
b1 \
b1 `
0-
b10010000100110101001010110001001 C
b1010 B
18
15
0N
1Z
12
b11 c
0Z
02
#80
0*
0K
#84
0)
0J
#85
1*
1K
1,
b1110101 .
b1 =
1M
1V
1T
1R
1Q
1P
b1 b
#90
0*
0K
#91
1)
1J
#95
1*
1K
b11 ]
b10 a
0,
b0 .
b111010111010101011001110110110 C
b11111111111111111111111111111000 A
b11 ?
b0 =
0M
0V
0T
0R
0Q
0P
#98
0)
0J
#100
0*
0K
#105
1)
1*
1J
1K
1,
b10011001 .
b1 =
1M
1V
1S
1R
1O
b10 c
#110
0*
0K
#112
0)
0J
#115
1*
1K
b100 ]
b110 a
0,
b0 .
b11001100110010000010011010111111 C
b110 A
0M
0V
0S
0R
0O
#119
1)
1J
b110 c
#120
0*
0K
#125
1*
1K
#126
0)
0J
#130
0*
0K
#133
1)
1J
#135
1*
1K
#140
0)
0*
0J
0K
#145
1*
1K
#147
1)
1J
#150
0*
0K
#154
0)
0J
#155
1*
1K
#160
0*
0K
#161
1)
1J
#165
1*
1K
#168
0)
0J
#170
0*
0K
#175
1)
1*
1J
1K
b100 ?
b0 =
#180
0*
0K
#182
0)
0J
#185
1*
1K
1,
b10011001 .
b1 =
1M
1V
1S
1R
1O
#189
1)
1J
#190
0*
0K
#195
1*
1K
b101 ]
b111 a
0,
b0 .
b1001100111111011011100111110100 C
b11111111111111111111111111111100 A
b101 ?
b0 =
0M
0V
0S
0R
0O
#196
0)
0J
#200
0*
0K
#203
1)
1J
b111 c
#205
1*
1K
1,
b10000111 .
b1 =
1M
1V
1U
1T
1O
#210
0)
0*
0J
0K
#215
1*
1K
b110 ]
b101 a
0,
b0 .
b1000011100100110100110001100101 C
b0 A
b110 ?
b0 =
0M
0V
0U
0T
0O
#217
1)
1J
b10 @
b0 >
b101 c
#220
0*
0K
#224
0)
0J
#225
1*
1K
1,
b11001000 .
b1 =
1M
1S
1P
1O
#230
0*
0K
#231
1)
1J
1-
b1 >
1N
#235
1*
1K
b111 ]
b100 a
0,
b0 .
b11100100001110100100110111100010 C
b11 A
0M
0S
0P
0O
#238
0)
0J
#240
0*
0K
#245
1)
1*
1J
1K
b10101001 [
b10 \
b11 `
0-
b110100001101101011111111011 C
b11111111111111111111111111111000 B
b11 @
b0 >
1:
08
17
13
0N
b100 c
#250
0*
0K
#252
0)
0J
#255
1*
1K
b11 b
#259
1)
1J
1-
b1 >
1N
#260
0*
0K
#265
1*
1K
b111 ?
b0 =
#266
0)
0J
#270
0*
0K
#273
1)
1J
b1110101 [
b11 \
b10 `
0-
b11101010111011011011001100000000 C
b1000 B
18
07
16
14
03
0N
#275
1*
1K
1,
b11001010 .
b1 =
1M
1U
1S
1P
1O
b10 b
#280
0)
0*
0J
0K
#285
1*
1K
b1000 ]
b1100 a
0,
b0 .
b11100101011011110101011100000001 C
b1001 A
0M
0U
0S
0P
0O
#287
1)
1J
b1100 c
#290
0*
0K
#294
0)
0J
#295
1*
1K
#300
0*
0K
#301
1)
1J
#305
1*
1K
#308
0)
0J
#310
0*
0K
#315
1)
1*
1J
1K
#320
0*
0K
#322
0)
0J
#325
1*
1K
#329
1)
1J
#330
0*
0K
#335
1*
1K
#336
0)
0J
#340
0*
0K
#343
1)
1J
#345
1*
1K
#350
0)
0*
0J
0K
#355
1*
1K
#357
1)
1J
#360
0*
0K
#364
0)
0J
#365
1*
1K
#370
0*
0K
#371
1)
1J
#375
1*
1K
b1000 ?
b0 =
#378
0)
0J
#380
0*
0K
#385
1)
1*
1J
1K
b100 @
b0 >
1,
b1110001 .
b1 =
1M
1V
1R
1Q
1P
#390
0*
0K
#392
0)
0J
#395
1*
1K
b1001 ]
b1101 a
0,
b0 .
b10111000100101001011100011001110 C
b1010 A
0M
0V
0R
0Q
0P
#399
1)
1J
1-
b1 >
1N
b1101 c
#400
0*
0K
#405
1*
1K
#406
0)
0J
#410
0*
0K
#413
1)
1J
b10011001 [
b100 \
b110 `
0-
b10101010010000111001011110111 C
b11111111111111111111111111111111 B
b101 @
b0 >
08
17
05
04
13
0N
#415
1*
1K
b110 b
#420
0)
0*
0J
0K
#425
1*
1K
#427
1)
1J
1-
b1 >
1N
#430
0*
0K
#434
0)
0J
#435
1*
1K
#440
0*
0K
#441
1)
1J
b101 \
b111 `
0-
b101011110100011001101011001100 C
b11111111111111111111111111111110 B
b110 @
b0 >
0N
#445
1*
1K
b111 b
#448
0)
0J
#450
0*
0K
#455
1)
1*
1J
1K
1-
b1 >
1N
#460
0*
0K
#462
0)
0J
#465
1*
1K
#469
1)
1J
b10000111 [
b110 \
b101 `
0-
b1010110100000010101000101011101 C
b111 @
b0 >
19
18
07
06
0N
#470
0*
0K
#475
1*
1K
b101 b
#476
0)
0J
#480
0*
0K
#483
1)
1J
1-
b1 >
1N
#485
1*
1K
#490
0)
0*
0J
0K
#495
1*
1K
b1001 ?
b0 =
#497
1)
1J
b11001000 [
b111 \
b100 `
0-
b101000000011001110000001111010 C
b1 B
0:
09
08
17
14
0N
#500
0*
0K
#504
0)
0J
#505
1*
1K
1,
b110100 .
b1 =
1M
1T
1R
1Q
b100 b
#510
0*
0K
#511
1)
1J
b1000 @
b0 >
#515
1*
1K
b1010 ]
b1111 a
0,
b0 .
b10011010001011111111001110110011 C
b1 A
0M
0T
0R
0Q
#518
0)
0J
#520
0*
0K
#525
1)
1*
1J
1K
1-
b1 >
b1010 ?
b0 =
1N
b1111 c
#530
0*
0K
#532
0)
0J
#535
1*
1K
1,
b10110110 .
b1 =
1M
1U
1T
1R
1Q
1O
#539
1)
1J
b11001010 [
b1000 \
b1100 `
0-
b11011011011110010011110101011000 C
b11 B
19
0N
#540
0*
0K
#545
1*
1K
b1011 ]
b1110 a
0,
b0 .
b100101100010111001011101111001 C
b11111111111111111111111111111100 A
b1011 ?
b0 =
0M
0U
0T
0R
0Q
0O
b1100 b
#546
0)
0J
#550
0*
0K
#553
1)
1J
b1110 c
#555
1*
1K
1,
b1111101 .
b1 =
1M
1V
1T
1S
1R
1Q
1P
#560
0)
0*
0J
0K
#565
1*
1K
b1100 ]
b1010 a
0,
b0 .
b10111110111100100111000011100110 C
b1010 A
0M
0V
0T
0S
0R
0Q
0P
#567
1)
1J
b1010 c
#570
0*
0K
#574
0)
0J
#575
1*
1K
#580
0*
0K
#581
1)
1J
b1001 @
b0 >
#585
1*
1K
#588
0)
0J
#590
0*
0K
#595
1)
1*
1J
1K
1-
b1 >
1N
#600
0*
0K
#602
0)
0J
#605
1*
1K
#609
1)
1J
b1110001 [
b1001 \
b1101 `
0-
b10101000110001100001011000101111 C
b1010 B
1:
09
07
16
15
03
0N
#610
0*
0K
#615
1*
1K
b1101 b
#616
0)
0J
#620
0*
0K
#623
1)
1J
#625
1*
1K
#630
0)
0*
0J
0K
#635
1*
1K
#637
1)
1J
#640
0*
0K
#644
0)
0J
#645
1*
1K
#650
0*
0K
#651
1)
1J
#655
1*
1K
#658
0)
0J
#660
0*
0K
#665
1)
1*
1J
1K
b1100 ?
b0 =
#670
0*
0K
#672
0)
0J
#675
1*
1K
1,
b10010111 .
b1 =
1M
1V
1U
1T
1R
1O
#679
1)
1J
#680
0*
0K
#685
1*
1K
b1101 ]
b1011 a
0,
b0 .
b1001011111011110010011010100100 C
b11111111111111111111111111111110 A
b1101 ?
b0 =
0M
0V
0U
0T
0R
0O
#686
0)
0J
#690
0*
0K
#693
1)
1J
b1011 c
#695
1*
1K
1,
b110100 .
b1 =
1M
1T
1R
1Q
#700
0)
0*
0J
0K
#705
1*
1K
b1110 ]
b1001 a
0,
b0 .
b11010000111000100010101010101 C
b11111111111111111111111111111111 A
b1110 ?
b0 =
0M
0T
0R
0Q
#707
1)
1J
b1001 c
#710
0*
0K
#714
0)
0J
#715
1*
1K
1,
b111010 .
b1 =
1M
1U
1S
1R
1Q
#720
0*
0K
#721
1)
1J
#725
1*
1K
b1111 ]
b1000 a
0,
b0 .
b10011101011111011101011000010010 C
b101 A
0M
0U
0S
0R
0Q
#728
0)
0J
#730
0*
0K
#735
1)
1*
1J
1K
b1000 c
#740
0*
0K
#742
0)
0J
#745
1*
1K
#749
1)
1J
b1010 @
b0 >
#750
0*
0K
#755
1*
1K
#756
0)
0J
#760
0*
0K
#763
1)
1J
1-
b1 >
1N
#765
1*
1K
#770
0)
0*
0J
0K
#775
1*
1K
b1111 ?
b0 =
#777
1)
1J
b110100 [
b1010 \
b1111 `
0-
b1010111101101010101011001101011 C
b11111111111111111111111111111010 B
b1011 @
b0 >
0:
18
04
0N
#780
0*
0K
#784
0)
0J
#785
1*
1K
1,
b10010000 .
b1 =
1M
1R
1O
b1111 b
#790
0*
0K
#791
1)
1J
1-
b1 >
1N
#795
1*
1K
1^
b0 ]
b0 a
0,
b0 .
b11001000000001001010001010110000 C
b1 A
0M
0R
0O
#798
0)
0J
#800
0*
0K
#805
1)
1*
1J
1K
b10110110 [
b1011 \
b1110 `
0-
b1010101010010011011011110001 C
b1100 @
b0 >
b10000 ?
b0 =
19
13
0N
b0 c
1d
#810
0*
0K
#812
0)
0J
#815
1*
1K
1,
b10110000 .
b1 =
1M
1R
1Q
1O
b1110 b
#819
1)
1J
1-
b1 >
1N
#820
0*
0K
#825
1*
1K
b1 ]
b1 a
0,
b0 .
b1011000001111000011101111111110 C
b11111111111111111111111111111101 A
b10001 ?
b0 =
0M
0R
0Q
0O
#826
0)
0J
#830
0*
0K
#833
1)
1J
b1111101 [
b1100 \
b1010 `
0-
b11110011010001011111000001100111 C
b11 B
1:
09
17
14
03
0N
b1 c
#835
1*
1K
1,
b10011001 .
b1 =
1M
1V
1S
1R
1O
b1010 b
#840
0)
0*
0J
0K
#845
1*
1K
b10 ]
b11 a
0,
b0 .
b1001100100111011011110101111100 C
b11111111111111111111111111111010 A
b10010 ?
b0 =
0M
0V
0S
0R
0O
#847
1)
1J
b11 c
#850
0*
0K
#854
0)
0J
#855
1*
1K
1,
b110100 .
b1 =
1M
1T
1R
1Q
#860
0*
0K
#861
1)
1J
#865
1*
1K
b11 ]
b10 a
0,
b0 .
b11010011011000000100001001101 C
b11111111111111111111111111111111 A
b10011 ?
b0 =
0M
0T
0R
0Q
#868
0)
0J
#870
0*
0K
#875
1)
1*
1J
1K
b1101 @
b0 >
1,
b1011010 .
b1 =
1M
1U
1S
1R
1P
b10 c
#880
0*
0K
#882
0)
0J
#885
1*
1K
b100 ]
b110 a
0,
b0 .
b10101101001110111000111010101010 C
b101 A
0M
0U
0S
0R
0P
#889
1)
1J
1-
b1 >
1N
b110 c
#890
0*
0K
#895
1*
1K
#896
0)
0J
#900
0*
0K
#903
1)
1J
b10010111 [
b1101 \
b1011 `
0-
b1001101100110011110000000100011 C
b11111111111111111111111111111010 B
b1110 @
b0 >
19
07
05
04
13
0N
#905
1*
1K
b1011 b
#910
0)
0*
0J
0K
#915
1*
1K
#917
1)
1J
1-
b1 >
1N
#920
0*
0K
#924
0)
0J
#925
1*
1K
#930
0*
0K
#931
1)
1J
b110100 [
b1110 \
b1001 `
0-
b11010100101111010100001100001000 C
b10 B
0:
09
15
03
0N
#935
1*
1K
b10100 ?
b0 =
b1001 b
#938
0)
0J
#940
0*
0K
#945
1)
1*
1J
1K
1,
b1110101 .
b1 =
1M
1V
1T
1R
1Q
1P
#950
0*
0K
#952
0)
0J
#955
1*
1K
b101 ]
b111 a
0,
b0 .
b111010111111100001010101101001 C
b11111111111111111111111111111010 A
b10101 ?
b0 =
0M
0V
0T
0R
0Q
0P
#959
1)
1J
b1111 @
b0 >
b111 c
#960
0*
0K
#965
1*
1K
1,
b1110011 .
b1 =
1M
1V
1U
1R
1Q
1P
#966
0)
0J
#970
0*
0K
#973
1)
1J
1-
b1 >
1N
#975
1*
1K
b110 ]
b101 a
0,
b0 .
b111001111101100111101000010110 C
b0 A
b10110 ?
b0 =
0M
0V
0U
0R
0Q
0P
#980
0)
0*
0J
0K
#985
1*
1K
1,
b11010001 .
b1 =
1M
1V
1R
1P
1O
#987
1)
1J
b111010 [
b1111 \
b1000 `
0-
b1101000101010001110000110011111 C
b0 B
b10000 @
b0 >
19
08
17
0N
b101 c
#990
0*
0K
#994
0)
0J
#995
1*
1K
b111 ]
b100 a
0,
b0 .
b1000100010100001011111101010100 C
b11111111111111111111111111111111 A
b10111 ?
b0 =
0M
0V
0R
0P
0O
b1000 b
#1000
0*
0K
#1001
1)
1J
1-
b1 >
1N
b100 c
#1005
1*
1K
1,
b11011 .
b1 =
1M
1V
1U
1S
1R
#1008
0)
0J
#1010
0*
0K
#1015
1)
1*
1J
1K
b1000 ]
b1100 a
b10010000 [
1_
b0 \
b0 `
0-
b10001101101101000111101001000101 C
b110 B
0,
b0 .
b11110000000000110101001000010 C
b1 A
0N
0M
0V
0U
0S
0R
09
07
05
13
b1100 c
#1020
0*
0K
#1022
0)
0J
#1025
1*
1K
b11000 ?
b0 =
b0 b
1e
#1029
1)
1J
#1030
0*
0K
#1035
1*
1K
1,
b11101011 .
b1 =
1M
1V
1U
1S
1Q
1P
1O
#1036
0)
0J
#1040
0*
0K
#1043
1)
1J
#1045
1*
1K
b1001 ]
b1101 a
0,
b0 .
b1110101111111000111000011011011 C
b11111111111111111111111111111100 A
b11001 ?
b0 =
0M
0V
0U
0S
0Q
0P
0O
#1050
0)
0*
0J
0K
#1055
1*
1K
1,
b1111011 .
b1 =
1M
1V
1U
1S
1R
1Q
1P
#1057
1)
1J
b1101 c
#1060
0*
0K
#1064
0)
0J
#1065
1*
1K
b1010 ]
b1111 a
0,
b0 .
b10111101101111000111111001100000 C
b10 A
0M
0V
0U
0S
0R
0Q
0P
#1070
0*
0K
#1071
1)
1J
b1111 c
#1075
1*
1K
#1078
0)
0J
#1080
0*
0K
#1085
1)
1*
1J
1K
b11010 ?
b0 =
#1090
0*
0K
#1092
0)
0J
#1095
1*
1K
1,
b1 .
b1 =
1M
1V
#1099
1)
1J
b10001 @
b0 >
#1100
0*
0K
#1105
1*
1K
b1011 ]
b1110 a
0,
b0 .
b101111000001001011100001 C
b11111111111111111111111111111000 A
b11011 ?
b0 =
0M
0V
#1106
0)
0J
#1110
0*
0K
#1113
1)
1J
1-
b1 >
1N
b1110 c
#1115
1*
1K
1,
b1101100 .
b1 =
1M
1T
1S
1Q
1P
#1120
0)
0*
0J
0K
#1125
1*
1K
b1100 ]
b1010 a
0,
b0 .
b110110011100011000101100101110 C
b11111111111111111111111111111001 A
b11100 ?
b0 =
0M
0T
0S
0Q
0P
#1127
1)
1J
b10110000 [
b1 \
b1 `
0-
b11101000001010111100100111010111 C
b1001 B
15
0N
b1010 c
#1130
0*
0K
#1134
0)
0J
#1135
1*
1K
1,
b11011100 .
b1 =
1M
1T
1S
1R
1P
1O
b1 b
#1140
0*
0K
#1141
1)
1J
#1145
1*
1K
b1101 ]
b1011 a
0,
b0 .
b11101110001001111000110000101100 C
b11 A
0M
0T
0S
0R
0P
0O
#1148
0)
0J
#1150
0*
0K
#1155
1)
1*
1J
1K
b1011 c
#1160
0*
0K
#1162
0)
0J
#1165
1*
1K
#1169
1)
1J
#1170
0*
0K
#1175
1*
1K
b11101 ?
b0 =
#1176
0)
0J
#1180
0*
0K
#1183
1)
1J
#1185
1*
1K
1,
b10000111 .
b1 =
1M
1V
1U
1T
1O
#1190
0)
0*
0J
0K
#1195
1*
1K
b1110 ]
b1001 a
0,
b0 .
b1000011111101010111101100111101 C
b11111111111111111111111111111010 A
b11110 ?
b0 =
0M
0V
0U
0T
0O
#1197
1)
1J
b1001 c
#1200
0*
0K
#1204
0)
0J
#1205
1*
1K
1,
b10111100 .
b1 =
1M
1T
1S
1R
1Q
1O
#1210
0*
0K
#1211
1)
1J
#1215
1*
1K
b1111 ]
b1000 a
0,
b0 .
b1011110000100101100100011011010 C
b11111111111111111111111111111011 A
b11111 ?
b0 =
0M
0T
0S
0R
0Q
0O
#1218
0)
0J
#1220
0*
0K
#1225
1)
1*
1J
1K
1,
b100100 .
b1 =
1M
1T
1Q
b1000 c
#1230
0*
0K
#1232
0)
0J
#1235
1*
1K
0^
b0 ]
b0 a
0,
b0 .
b10010000101111110100010010011 C
b11111111111111111111111111111111 A
b100000 ?
b0 =
0M
0T
0Q
#1239
1)
1J
b0 c
0d
#1240
0*
0K
#1245
1*
1K
1,
b111001 .
b1 =
1M
1V
1S
1R
1Q
#1246
0)
0J
#1250
0*
0K
#1253
1)
1J
b10010 @
b0 >
#1255
1*
1K
b1 ]
b1 a
0,
b0 .
b10011100100001111011010010111000 C
b100 A
0M
0V
0S
0R
0Q
1Y
11
#1260
0)
0*
0J
0K
#1265
1*
1K
#1267
1)
1J
1-
b1 >
1N
b1 c
0Y
1Y
#1270
0*
0K
#1274
0)
0J
#1275
1*
1K
#1280
0*
0K
#1281
1)
1J
b10011001 [
b10 \
b11 `
0-
b11110001100100010000111101011001 C
b1000 B
1:
17
05
0N
0Y
1Y
#1285
1*
1K
b11 b
0Y
01
#1288
0)
0J
#1290
0*
0K
#1295
1)
1*
1J
1K
b100001 ?
b0 =
#1300
0*
0K
#1302
0)
0J
