Submits/RTL_Design_and_Integration_Material/Verilog_codes/DFF/DFF.v
// Code your design here
module dff(input clk,   // defaults it datatype as wire
           input reset_n,
           input data,
           output reg q ); 
  
  always@(posedge clk) begin 
    if(!reset_n) 
     begin 
       q<='b0;
     end 
    else 
     begin 
       q<=data;
     end
  end 
endmodule

Submits/RTL_Design_and_Integration_Material/Verilog_codes/DFF/DFF_tb.v
`include "DFF.v"

//How to write a verilog code  Hardware description language 
//1. synthesisable code - can be made into a chip  
//2. non-synthesisable code - cannot be made into a chip
// Verilog gives us a flexibility with a set of constructs
  
// Can be synthesised 
// module
// function 
// for block 
// case  (like a mux)
// if else block (like a mux)
// and or xor nor nand  
// wire and reg 
// always block 

// Cannot be synthesised 
// task 
// integer
// real 
// time
// initial block 

// Example of wire : 
// if a is wire 
// a=b; // we will not get it in next simulation time
// if a as reg; 
// a=b; // get in the next simulation time 



// Dflipflop - in a dataflow method 



module tb;
  reg clk;
  reg reset_n;
  reg data;
  wire q;
  
  dff dut (clk,reset_n,data,q);
  
  initial begin 
    clk='b0;
    forever #10 clk=~clk;
  end 
  
  initial begin
    #15 reset_n=0;
    #15 reset_n=1; data=1;
    #15 reset_n=1; data=0;
    #15 reset_n=1; data=1;
    #15 reset_n=1; data=0;
    #15 reset_n=1; data=1;
    #15 reset_n=1; data=0;
    #15 reset_n=1; data=1;
    #15 reset_n=1; data=0;
    #15 reset_n=1; data=1;
    #15 reset_n=1; data=0;
  end 
  
  initial begin 
    $dumpvars(0,tb);
    $dumpfile("dump.vcd");
    $monitor("clk =%d, reset_n=%d, data=%d, q=%d",clk,reset_n,data,q);
    #300 $finish;
  end 
endmodule

Submits/RTL_Design_and_Integration_Material/Verilog_codes/DFF/dump.vcd
$date
	Wed Apr 19 07:17:23 2023
$end
$version
	QuestaSim Version 10.6c
$end
$timescale
	1ns
$end

$scope module tb $end
$var reg 1 ! clk $end
$var reg 1 " reset_n $end
$var reg 1 # data $end
$var wire 1 $ q $end

$scope module dut $end
$var wire 1 % clk $end
$var wire 1 & reset_n $end
$var wire 1 ' data $end
$var reg 1 ( q $end
$upscope $end
$upscope $end
$enddefinitions $end
#0
$dumpvars
0!
x"
x#
x(
x$
x'
x&
0%
$end
#10
1!
1%
#15
0"
0&
#20
0!
0%
#30
1"
1#
1!
1&
1'
1%
1(
1$
#40
0!
0%
#45
0#
0'
#50
1!
1%
0(
0$
#60
1#
0!
1'
0%
#70
1!
1%
1(
1$
#75
0#
0'
#80
0!
0%
#90
1#
1!
1'
1%
#100
0!
0%
#105
0#
0'
#110
1!
1%
0(
0$
#120
1#
0!
1'
0%
#130
1!
1%
1(
1$
#135
0#
0'
#140
0!
0%
#150
1#
1!
1'
1%
#160
0!
0%
#165
0#
0'
#170
1!
1%
0(
0$
