Submits/RTL_Design_and_Integration_Material/Ibrahim_Verilog_Codes/12_Dynamic_Pattern_Detector_Implicit/dynamic_pattern_detector.v
module dynamic_pattern_detector(clk, reset, d_in, valid_in, pattern_flag);

input clk, reset, d_in, valid_in;
output reg pattern_flag;

reg[4:0] pattern_to_detect, current_pattern;
integer count;

initial begin 
	pattern_to_detect = 5'b01101; //BCCBC
	current_pattern = 5'b00000;
end

always @(posedge clk) begin 
	if (reset == 1) begin 
		current_pattern = 'b0;
		pattern_flag = 0;
		count = 0;
	end
	else begin 
		pattern_flag = 0;
		if (valid_in == 1) begin 
			current_pattern = {current_pattern[3:0], d_in};
			if (current_pattern == pattern_to_detect) begin 
				pattern_flag = 1;
			end 
		end
	end 	

end 
	
endmodule

Submits/RTL_Design_and_Integration_Material/Ibrahim_Verilog_Codes/12_Dynamic_Pattern_Detector_Implicit/tb.v
`include "dynamic_pattern_detector.v"

module tb;
	// Add the nets
	reg clk, reset, d_in, valid_in;
	wire pattern_flag;
	integer seed;
	integer count;

	// generate clk
	always begin 
		#5 clk = 0;
		#5 clk = 1;
	end

	//instantiate
	dynamic_pattern_detector dut (clk, reset, d_in, valid_in, pattern_flag);

	//dump vars
	initial begin 
		$dumpfile("waves.vcd");
		$dumpvars;
	end
	
	//generate inputs
	initial begin
		count = 0;
		seed = 37934298;
		reset = 1;
		#20;
		reset = 0;
		repeat (540) begin 
			@(posedge clk) begin
				valid_in = 1'b1;	
				d_in = $random(seed);
			end
		end 
		@(posedge clk) begin 
			valid_in = 1'b0;
			d_in = 1'b0;
			end
		#50;
		$display("total count = %0d", count);
		$finish;
	end 
	
	always @(posedge pattern_flag) count = count + 1;
	
endmodule

Submits/RTL_Design_and_Integration_Material/Ibrahim_Verilog_Codes/12_Dynamic_Pattern_Detector_Implicit/waves.vcd
$date
	Mon Apr 24 22:23:27 2023
$end
$version
	QuestaSim Version 10.6c
$end
$timescale
	1ns
$end

$scope module tb $end
$var reg 1 ! clk $end
$var reg 1 " reset $end
$var reg 1 # d_in $end
$var reg 1 $ valid_in $end
$var wire 1 % pattern_flag $end
$var integer 32 & seed $end
$var integer 32 ' count $end

$scope module dut $end
$var wire 1 ( clk $end
$var wire 1 ) reset $end
$var wire 1 * d_in $end
$var wire 1 + valid_in $end
$var reg 1 , pattern_flag $end
$var reg 5 - pattern_to_detect [4:0] $end
$var reg 5 . current_pattern [4:0] $end
$var integer 32 / count $end
$upscope $end
$upscope $end
$enddefinitions $end
#0
$dumpvars
x!
1"
x#
x$
x,
b1101 -
b0 .
b10010000101101010011011010 &
b0 '
bx /
x%
x+
x*
1)
x(
$end
#5
0!
0(
#10
1!
1(
0,
0%
#15
0!
0(
#20
0"
1!
0)
1(
1$
b1001001011011000010010010011 &
0#
1+
0*
#25
0!
0(
#30
1!
1(
b101101110000011010000010111000 &
1#
1*
#35
0!
0(
#40
1!
1(
b1 .
b11001111011110000101101011001 &
#45
0!
0(
#50
1!
1(
b11 .
b11110011010110001001101101000110 &
0#
0*
#55
0!
0(
#60
1!
1(
b110 .
b11111001000111001110010100001111 &
#65
0!
0(
#70
1!
1(
b1100 .
b11011000110101000011000000000100 &
1#
1*
#75
0!
0(
#80
1!
1(
b11001 .
b10011000010111101010011100110101 &
0#
0*
#85
0!
0(
#90
1!
1(
b10010 .
b1111001011111101001011001110010 &
#95
0!
0(
#100
1!
1(
b100 .
b1001110011101000100001101001011 &
#105
0!
0(
#110
1!
1(
b1000 .
b11111101110011111011001000010000 &
1#
1*
#115
0!
0(
#120
1!
1(
b10001 .
b1111101011011000110011011010001 &
0#
0*
#125
0!
0(
#130
1!
1(
b10 .
b1010111110101111111001001011110 &
1#
1*
#135
0!
0(
#140
1!
1(
b101 .
b1000001100110011101101101000111 &
#145
0!
0(
#150
1!
1(
b1011 .
b110011100111100011001011011100 &
#155
0!
0(
#160
1!
1(
b10111 .
b10010001000111111110011000101101 &
0#
0*
#165
0!
0(
#170
1!
1(
b1110 .
b10111011011010001001101100001010 &
#175
0!
0(
#180
1!
1(
b11100 .
b11111101101011011010100100000011 &
1#
1*
#185
0!
0(
#190
1!
1(
b11001 .
b10011110101010000111111001101000 &
#195
0!
0(
#200
1!
1(
b10011 .
b11001110000001000000101001001 &
#205
0!
0(
#210
1!
1(
b111 .
b11100111000000010011110001110110 &
0#
0*
#215
0!
0(
#220
1!
1(
b1110 .
b1001000100001010110100001111111 &
1#
1*
#225
0!
0(
#230
1!
1(
b11101 .
b1000001101000100010000010110100 &
#235
0!
0(
#240
1!
1(
b11011 .
b11101011001100010101010000100101 &
0#
0*
#245
0!
0(
#250
1!
1(
b10110 .
b101011111010110100001010100010 &
1#
1*
#255
0!
0(
#260
1!
1(
b1101 .
1,
b1100000011010001001010110111011 &
0#
0*
1%
b1 '
#265
0!
0(
#270
1!
1(
0,
b11010 .
b11001000101010110010111000000 &
0%
#275
0!
0(
#280
1!
1(
b10100 .
b10010010000011010011101011000001 &
#285
0!
0(
#290
1!
1(
b1000 .
b11011011010101001101100110001110 &
#295
0!
0(
#300
1!
1(
b10000 .
b11001011100011000110110010110111 &
1#
1*
#305
0!
0(
#310
1!
1(
b1 .
b10001101101011110101100110001100 &
#315
0!
0(
#320
1!
1(
b11 .
b10110110100000101101000100011101 &
#325
0!
0(
#330
1!
1(
b111 .
b10011100011111001110110100111010 &
0#
0*
#335
0!
0(
#340
1!
1(
b1110 .
b10010101010011111110100101110011 &
#345
0!
0(
#350
1!
1(
b11100 .
b10001001010010111100100000011000 &
#355
0!
0(
#360
1!
1(
b11000 .
b10010010111100000111001100111001 &
1#
1*
#365
0!
0(
#370
1!
1(
b10001 .
b1010011100111110010100110100110 &
#375
0!
0(
#380
1!
1(
b11 .
b110101001101111100011111101111 &
0#
0*
#385
0!
0(
#390
1!
1(
b110 .
b111010110000010011110101100100 &
1#
1*
#395
0!
0(
#400
1!
1(
b1101 .
1,
b11010010000000011110100010101 &
0#
0*
1%
b10 '
#405
0!
0(
#410
1!
1(
0,
b11010 .
b10000101100111111111101011010010 &
1#
1*
0%
#415
0!
0(
#420
1!
1(
b10101 .
b11011101010101000010000101011 &
#425
0!
0(
#430
1!
1(
b1011 .
b1010100011011010000010101110000 &
0#
0*
#435
0!
0(
#440
1!
1(
b10110 .
b101010000001000000101010110001 &
#445
0!
0(
#450
1!
1(
b1100 .
b11100100011110001000110010111110 &
#455
0!
0(
#460
1!
1(
b11000 .
b10100000011011000101101000100111 &
#465
0!
0(
#470
1!
1(
b10000 .
b1010001011111110010110000111100 &
#475
0!
0(
#480
1!
1(
b0 .
b11100100010100010111100000001101 &
#485
0!
0(
#490
1!
1(
b1110000011000101100101101101010 &
#495
0!
0(
#500
1!
1(
b11001110110110110100010111100011 &
1#
1*
#505
0!
0(
#510
1!
1(
b1 .
b1110000001100111110111001000 &
0#
0*
#515
0!
0(
#520
1!
1(
b10 .
b1101010111011110000100101001 &
#525
0!
0(
#530
1!
1(
b100 .
b1011001110001010110001011010110 &
1#
1*
#535
0!
0(
#540
1!
1(
b1001 .
b1001011111010110000001101011111 &
#545
0!
0(
#550
1!
1(
b10011 .
b10111101101111001000011000010100 &
#555
0!
0(
#560
1!
1(
b111 .
b1000110110100110001000000101 &
#565
0!
0(
#570
1!
1(
b1111 .
b10001111110111111011111100000010 &
#575
0!
0(
#580
1!
1(
b11111 .
b1010001111000010000111010011011 &
#585
0!
0(
#590
1!
1(
b1101100100011001000100100000 &
#595
0!
0(
#600
1!
1(
b11010011000011111101011010100001 &
0#
0*
#605
0!
0(
#610
1!
1(
b11110 .
b10101000001101100000101111101110 &
#615
0!
0(
#620
1!
1(
b11100 .
b1111101110100001010001110010111 &
1#
1*
#625
0!
0(
#630
1!
1(
b11001 .
b11111011111110001010101011101100 &
#635
0!
0(
#640
1!
1(
b10011 .
b10001101110101101101011111101 &
#645
0!
0(
#650
1!
1(
b111 .
b10001010101111010011010110011010 &
#655
0!
0(
#660
1!
1(
b1111 .
b11101010110101101011111001010011 &
#665
0!
0(
#670
1!
1(
b11111 .
b10110011111100111001111101111000 &
#675
0!
0(
#680
1!
1(
b11000101001111100101100011001 &
#685
0!
0(
#690
1!
1(
b1110110001101110100000000110 &
#695
0!
0(
#700
1!
1(
b11010111000101100001101011001111 &
0#
0*
#705
0!
0(
#710
1!
1(
b11110 .
b1110110110111101111101011000100 &
1#
1*
#715
0!
0(
#720
1!
1(
b11101 .
b1111110000011101100001011110101 &
0#
0*
#725
0!
0(
#730
1!
1(
b11010 .
b1110100101011011000111100110010 &
1#
1*
#735
0!
0(
#740
1!
1(
b10101 .
b11001110011100110011010100001011 &
0#
0*
#745
0!
0(
#750
1!
1(
b1010 .
b1100000111111100000100011010000 &
1#
1*
#755
0!
0(
#760
1!
1(
b10101 .
b10011010101011111001111010010001 &
#765
0!
0(
#770
1!
1(
b1011 .
b1101000010000000101011100011110 &
0#
0*
#775
0!
0(
#780
1!
1(
b10110 .
b10111000100000100100100000111 &
#785
0!
0(
#790
1!
1(
b1100 .
b10010100110001101101010110011100 &
1#
1*
#795
0!
0(
#800
1!
1(
b11001 .
b10001101011011111100111101101 &
#805
0!
0(
#810
1!
1(
b10011 .
b11110111111011110010101111001010 &
#815
0!
0(
#820
1!
1(
b111 .
b11011011100010010101001011000011 &
#825
0!
0(
#830
1!
1(
b1111 .
b11000111011100010110100101000 &
#835
0!
0(
#840
1!
1(
b11111 .
b111100001011010011000100001001 &
0#
0*
#845
0!
0(
#850
1!
1(
b11110 .
b10101100101101101011100100110110 &
1#
1*
#855
0!
0(
#860
1!
1(
b11101 .
b1001110111100000000111000111111 &
#865
0!
0(
#870
1!
1(
b11011 .
b1110101001100111001101101110100 &
0#
0*
#875
0!
0(
#880
1!
1(
b10110 .
b10100101011000101111111100101 &
1#
1*
#885
0!
0(
#890
1!
1(
b1101 .
1,
b10101110110011000110101101100010 &
1%
b11 '
#895
0!
0(
#900
1!
1(
0,
b11011 .
b11000110100001111111011101111011 &
0%
#905
0!
0(
#910
1!
1(
b10111 .
b11011001111011010110110010000000 &
#915
0!
0(
#920
1!
1(
b1111 .
b11111110001000100110001010000001 &
0#
0*
#925
0!
0(
#930
1!
1(
b11110 .
b10100011000010100110111001001110 &
#935
0!
0(
#940
1!
1(
b11100 .
b10000101010000100100101001110111 &
#945
0!
0(
#950
1!
1(
b11000 .
b1011110010101001010110001001100 &
#955
0!
0(
#960
1!
1(
b10000 .
b10000010110110011101010011011101 &
1#
1*
#965
0!
0(
#970
1!
1(
b1 .
b10101101000110111010110111111010 &
0#
0*
#975
0!
0(
#980
1!
1(
b10 .
b10110100111110100000001100110011 &
1#
1*
#985
0!
0(
#990
1!
1(
b101 .
b10100001100100010010011011011000 &
#995
0!
0(
#1000
1!
1(
b1011 .
b11100111000011010001001011111001 &
0#
0*
#1005
0!
0(
#1010
1!
1(
b10110 .
b11000010011001111101011001100110 &
#1015
0!
0(
#1020
1!
1(
b1100 .
b11001001011011111101110110101111 &
#1025
0!
0(
#1030
1!
1(
b11000 .
b11011010100001010110100000100100 &
1#
1*
#1035
0!
0(
#1040
1!
1(
b10001 .
b101011010000100011100011010101 &
0#
0*
#1045
0!
0(
#1050
1!
1(
b10 .
b111001101111110101001110010010 &
1#
1*
#1055
0!
0(
#1060
1!
1(
b101 .
b1001001000001100101010111101011 &
0#
0*
#1065
0!
0(
#1070
1!
1(
b1010 .
b100010010110101011110000110000 &
#1075
0!
0(
#1080
1!
1(
b10100 .
b11011010011001110010001001110001 &
#1085
0!
0(
#1090
1!
1(
b1000 .
b1000011110001110101000101111110 &
1#
1*
#1095
0!
0(
#1100
1!
1(
b10001 .
b10110111001111011010011111100111 &
0#
0*
#1105
0!
0(
#1110
1!
1(
b10 .
b10000101110011010010111011111100 &
1#
1*
#1115
0!
0(
#1120
1!
1(
b101 .
b10111111101011010110101111001101 &
#1125
0!
0(
#1130
1!
1(
b1011 .
b10111000001001011011110000101010 &
0#
0*
#1135
0!
0(
#1140
1!
1(
b10110 .
b11100111011111100111110100011 &
1#
1*
#1145
0!
0(
#1150
1!
1(
b1101 .
1,
b101001001101111000110010001000 &
0#
0*
1%
b100 '
#1155
0!
0(
#1160
1!
1(
0,
b11010 .
b1100000001001100111000011101001 &
0%
#1165
0!
0(
#1170
1!
1(
b10100 .
b1100011011011010011111110010110 &
#1175
0!
0(
#1180
1!
1(
b1000 .
b1101010010011001000100100011111 &
#1185
0!
0(
#1190
1!
1(
b10000 .
b10001011010111110110000011010100 &
#1195
0!
0(
#1200
1!
1(
b0 .
b11010100000111110100110111000101 &
#1205
0!
0(
#1210
1!
1(
b11000001110010010100011111000010 &
1#
1*
#1215
0!
0(
#1220
1!
1(
b1 .
b10101110100101010101000001011011 &
#1225
0!
0(
#1230
1!
1(
b11 .
b10110011000000001111011111100000 &
0#
0*
#1235
0!
0(
#1240
1!
1(
b110 .
b1011100001111001101111001100001 &
#1245
0!
0(
#1250
1!
1(
b1100 .
b11010010011010100000000010101110 &
#1255
0!
0(
#1260
1!
1(
b11000 .
b11100001100110010110000101010111 &
1#
1*
#1265
0!
0(
#1270
1!
1(
b10001 .
b11010011000110110101110110101100 &
0#
0*
#1275
0!
0(
#1280
1!
1(
b10 .
b11001110010101111011111010111101 &
#1285
0!
0(
#1290
1!
1(
b100 .
b1101111101100000101011001011010 &
1#
1*
#1295
0!
0(
#1300
1!
1(
b1001 .
b10111010111100011011100000010011 &
#1305
0!
0(
#1310
1!
1(
b10011 .
b10110001111111000101111000111000 &
#1315
0!
0(
#1320
1!
1(
b111 .
b10110110000110000100101011011001 &
0#
0*
#1325
0!
0(
#1330
1!
1(
b1110 .
b1011000000110011111010011000110 &
#1335
0!
0(
#1340
1!
1(
b11100 .
b11010010111111010001000010001111 &
1#
1*
#1345
0!
0(
#1350
1!
1(
b11001 .
b11011111000011001000010110000100 &
0#
0*
#1355
0!
0(
#1360
1!
1(
b10010 .
b11000101010100101001111010110101 &
#1365
0!
0(
#1370
1!
1(
b100 .
b11010011111011010100011111110010 &
1#
1*
#1375
0!
0(
#1380
1!
1(
b1001 .
b1001100110111110011011001011 &
#1385
0!
0(
#1390
1!
1(
b10011 .
b10000011010110110001111110010000 &
0#
0*
#1395
0!
0(
#1400
1!
1(
b110 .
b11110000001000101001011001010001 &
#1405
0!
0(
#1410
1!
1(
b1100 .
b10100011101001010111101111011110 &
1#
1*
#1415
0!
0(
#1420
1!
1(
b11001 .
b11101110101011000111011011000111 &
#1425
0!
0(
#1430
1!
1(
b10011 .
b1011000111010100011100001011100 &
#1435
0!
0(
#1440
1!
1(
b111 .
b1010000110001111100110110101101 &
#1445
0!
0(
#1450
1!
1(
b1111 .
b10100011000111100111110010001010 &
0#
0*
#1455
0!
0(
#1460
1!
1(
b11110 .
b10101000010001101011110010000011 &
#1465
0!
0(
#1470
1!
1(
b11100 .
b10100101110101001101111101000 &
1#
1*
#1475
0!
0(
#1480
1!
1(
b11001 .
b10101111010000011010000011001001 &
0#
0*
#1485
0!
0(
#1490
1!
1(
b10010 .
b1001101100000001111010111110110 &
1#
1*
#1495
0!
0(
#1500
1!
1(
b101 .
b10010010101110000111001111111111 &
#1505
0!
0(
#1510
1!
1(
b1011 .
b1001111100101111101011000110100 &
#1515
0!
0(
#1520
1!
1(
b10111 .
b1001000101010110010101110100101 &
#1525
0!
0(
#1530
1!
1(
b1111 .
b1101111011100101010000100010 &
#1535
0!
0(
#1540
1!
1(
b11111 .
b10010110010000010001100100111011 &
0#
0*
#1545
0!
0(
#1550
1!
1(
b11110 .
b10111001101001000011001101000000 &
1#
1*
#1555
0!
0(
#1560
1!
1(
b11101 .
b110010010101110100101001000001 &
0#
0*
#1565
0!
0(
#1570
1!
1(
b11010 .
b1000111011001100001100001110 &
1#
1*
#1575
0!
0(
#1580
1!
1(
b10101 .
b11101110100011011110100000110111 &
#1585
0!
0(
#1590
1!
1(
b1011 .
b100100101001001011111100001100 &
#1595
0!
0(
#1600
1!
1(
b10111 .
b1110100101011001001100010011101 &
#1605
0!
0(
#1610
1!
1(
b1111 .
b11001010100100110010111010111010 &
#1615
0!
0(
#1620
1!
1(
b11111 .
b11011111111101011101110011110011 &
#1625
0!
0(
#1630
1!
1(
b10110001000011010100010110011000 &
0#
0*
#1635
0!
0(
#1640
1!
1(
b11110 .
b10111001110000010111001010111001 &
1#
1*
#1645
0!
0(
#1650
1!
1(
b11101 .
b101011101010100001100100110 &
0#
0*
#1655
0!
0(
#1660
1!
1(
b11010 .
b10010110011101011011001101101111 &
#1665
0!
0(
#1670
1!
1(
b10100 .
b101001110011000101001011100100 &
1#
1*
#1675
0!
0(
#1680
1!
1(
b1001 .
b101011101101111111010010010101 &
#1685
0!
0(
#1690
1!
1(
b10011 .
b1001110010011110110110001010010 &
0#
0*
#1695
0!
0(
#1700
1!
1(
b110 .
b101010011010111110011110101011 &
#1705
0!
0(
#1710
1!
1(
b1100 .
b1011010110101110011001011110000 &
1#
1*
#1715
0!
0(
#1720
1!
1(
b11001 .
b11011110110110011111101000110001 &
#1725
0!
0(
#1730
1!
1(
b10011 .
b10000000011100101101011000111110 &
0#
0*
#1735
0!
0(
#1740
1!
1(
b110 .
b10000111000101001011010110100111 &
#1745
0!
0(
#1750
1!
1(
b1100 .
b11101110011101011111000110111100 &
#1755
0!
0(
#1760
1!
1(
b11000 .
b11100011011101010001111110001101 &
#1765
0!
0(
#1770
1!
1(
b10000 .
b110110111100010110110011101010 &
1#
1*
#1775
0!
0(
#1780
1!
1(
b1 .
b10101110110001100001100101100011 &
#1785
0!
0(
#1790
1!
1(
b11 .
b11101010011110101101101001000 &
0#
0*
#1795
0!
0(
#1800
1!
1(
b110 .
b11011011011101101100000010101001 &
#1805
0!
0(
#1810
1!
1(
b1100 .
b10000110100010011101110001010110 &
1#
1*
#1815
0!
0(
#1820
1!
1(
b11001 .
b10011000111010111100111011011111 &
#1825
0!
0(
#1830
1!
1(
b10011 .
b111101001101001111101110010100 &
0#
0*
#1835
0!
0(
#1840
1!
1(
b110 .
b10101111110001111111100110000101 &
1#
1*
#1845
0!
0(
#1850
1!
1(
b1101 .
1,
b11100100010100111001000010000010 &
0#
0*
1%
b101 '
#1855
0!
0(
#1860
1!
1(
0,
b11010 .
b10100101110000110101001000011011 &
1#
1*
0%
#1865
0!
0(
#1870
1!
1(
b10101 .
b11111010101011110001111010100000 &
#1875
0!
0(
#1880
1!
1(
b1011 .
b11000001011010011010011000100001 &
0#
0*
#1885
0!
0(
#1890
1!
1(
b10110 .
b11100101001010101011010101101110 &
#1895
0!
0(
#1900
1!
1(
b1100 .
b1100011110101111101111100010111 &
1#
1*
#1905
0!
0(
#1910
1!
1(
b11001 .
b11001001010010001101000001101100 &
0#
0*
#1915
0!
0(
#1920
1!
1(
b10010 .
b10110010010100000110001001111101 &
#1925
0!
0(
#1930
1!
1(
b100 .
b1000001110111000011011100011010 &
1#
1*
#1935
0!
0(
#1940
1!
1(
b1001 .
b100011001111100111000111010011 &
0#
0*
#1945
0!
0(
#1950
1!
1(
b10010 .
b11010110100110111101110011111000 &
1#
1*
#1955
0!
0(
#1960
1!
1(
b101 .
b10100010000000001000101010011001 &
0#
0*
#1965
0!
0(
#1970
1!
1(
b1010 .
b1001100000100011100000110000110 &
#1975
0!
0(
#1980
1!
1(
b10100 .
b10010010100100011100011001001111 &
1#
1*
#1985
0!
0(
#1990
1!
1(
b1001 .
b10001100000111001101000001000100 &
0#
0*
#1995
0!
0(
#2000
1!
1(
b10010 .
b1111001111010100011101001110101 &
1#
1*
#2005
0!
0(
#2010
1!
1(
b101 .
b10111111111111011100000010110010 &
#2015
0!
0(
#2020
1!
1(
b1011 .
b1100001101011100101100010001011 &
#2025
0!
0(
#2030
1!
1(
b10111 .
b1101011101001101111011001010000 &
#2035
0!
0(
#2040
1!
1(
b1111 .
b10100101100001010100111000010001 &
#2045
0!
0(
#2050
1!
1(
b11111 .
b10011110110001110110000010011110 &
#2055
0!
0(
#2060
1!
1(
b10100110001011100110010010000111 &
0#
0*
#2065
0!
0(
#2070
1!
1(
b11110 .
b11010010110010000101101100011100 &
1#
1*
#2075
0!
0(
#2080
1!
1(
b11101 .
b1010010001011010110000101101101 &
0#
0*
#2085
0!
0(
#2090
1!
1(
b11010 .
b1111101101101101000110101001010 &
1#
1*
#2095
0!
0(
#2100
1!
1(
b10101 .
b1111101101001011110011001000011 &
#2105
0!
0(
#2110
1!
1(
b1011 .
b11110000110011011100101010101000 &
#2115
0!
0(
#2120
1!
1(
b10111 .
b10010101111011101000010001001 &
#2125
0!
0(
#2130
1!
1(
b1111 .
b1110110000111111111001010110110 &
0#
0*
#2135
0!
0(
#2140
1!
1(
b11110 .
b101001100111101001100110111111 &
1#
1*
#2145
0!
0(
#2150
1!
1(
b11101 .
b11111011100011101101000011110100 &
#2155
0!
0(
#2160
1!
1(
b11011 .
b10000010111011011011011101100101 &
#2165
0!
0(
#2170
1!
1(
b10111 .
b10100010000100001111110011100010 &
0#
0*
#2175
0!
0(
#2180
1!
1(
b1110 .
b10100001010100111111101011111011 &
#2185
0!
0(
#2190
1!
1(
b11100 .
b1101110111110011011101000000000 &
1#
1*
#2195
0!
0(
#2200
1!
1(
b11001 .
b1000110011010111111001000000001 &
0#
0*
#2205
0!
0(
#2210
1!
1(
b10010 .
b11010001101110111101011111001110 &
1#
1*
#2215
0!
0(
#2220
1!
1(
b101 .
b1010101001011110100010111110111 &
0#
0*
#2225
0!
0(
#2230
1!
1(
b1010 .
b11100011010111111001000111001100 &
#2235
0!
0(
#2240
1!
1(
b10100 .
b1111111101110110001110001011101 &
1#
1*
#2245
0!
0(
#2250
1!
1(
b1001 .
b11100101101000110110111101111010 &
#2255
0!
0(
#2260
1!
1(
b10011 .
b10100000000000110111011010110011 &
0#
0*
#2265
0!
0(
#2270
1!
1(
b110 .
b11000110100000000010010001011000 &
1#
1*
#2275
0!
0(
#2280
1!
1(
b1101 .
1,
b10011010110011011001001001111001 &
1%
b110 '
#2285
0!
0(
#2290
1!
1(
0,
b11011 .
b11111001100001110110111111100110 &
0%
#2295
0!
0(
#2300
1!
1(
b10111 .
b100010000010010100100100101111 &
0#
0*
#2305
0!
0(
#2310
1!
1(
b1110 .
b11010101011111110110100100 &
#2315
0!
0(
#2320
1!
1(
b11100 .
b111011000010111000001010101 &
#2325
0!
0(
#2330
1!
1(
b11000 .
b1001100000100000100010100010010 &
#2335
0!
0(
#2340
1!
1(
b10000 .
b1100110110011100101101011 &
1#
1*
#2345
0!
0(
#2350
1!
1(
b1 .
b1100100101000100110100110110000 &
#2355
0!
0(
#2360
1!
1(
b11 .
b111111000111001001000111110001 &
0#
0*
#2365
0!
0(
#2370
1!
1(
b110 .
b10001111001110110001101011111110 &
#2375
0!
0(
#2380
1!
1(
b1100 .
b11001101101100011000001101100111 &
1#
1*
#2385
0!
0(
#2390
1!
1(
b11001 .
b111110001110010111010001111100 &
0#
0*
#2395
0!
0(
#2400
1!
1(
b10010 .
b110011011010001001001101001101 &
#2405
0!
0(
#2410
1!
1(
b100 .
b1101100001011101110110101010 &
1#
1*
#2415
0!
0(
#2420
1!
1(
b1001 .
b1111110000111100010001100100011 &
0#
0*
#2425
0!
0(
#2430
1!
1(
b10010 .
b10101001000011011110101000001000 &
#2435
0!
0(
#2440
1!
1(
b100 .
b11111111000011101101000001101001 &
#2445
0!
0(
#2450
1!
1(
b1000 .
b11001111110110110011100100010110 &
1#
1*
#2455
0!
0(
#2460
1!
1(
b10001 .
b11001101100010001101010010011111 &
#2465
0!
0(
#2470
1!
1(
b11 .
b1011101111111010101011001010100 &
#2475
0!
0(
#2480
1!
1(
b111 .
b1110111100101000110010101000101 &
#2485
0!
0(
#2490
1!
1(
b1111 .
b10110000001111101001100101000010 &
0#
0*
#2495
0!
0(
#2500
1!
1(
b11110 .
b11101001001010110001001111011011 &
#2505
0!
0(
#2510
1!
1(
b11100 .
b11111011010111000000010101100000 &
#2515
0!
0(
#2520
1!
1(
b11000 .
b11111010010101100010110111100001 &
#2525
0!
0(
#2530
1!
1(
b10000 .
b101001110000010101000101110 &
#2535
0!
0(
#2540
1!
1(
b0 .
b110010010011000001110011010111 &
#2545
0!
0(
#2550
1!
1(
b1000001010000010000001100101100 &
#2555
0!
0(
#2560
1!
1(
b10010001011001001100011000111101 &
#2565
0!
0(
#2570
1!
1(
b1010010000000001101011111011010 &
#2575
0!
0(
#2580
1!
1(
b10001101011111001110101110010011 &
#2585
0!
0(
#2590
1!
1(
b10010000100100100001101110111000 &
1#
1*
#2595
0!
0(
#2600
1!
1(
b1 .
b1001100001000001000101001011001 &
0#
0*
#2605
0!
0(
#2610
1!
1(
b10 .
b100111011011100100111001000110 &
#2615
0!
0(
#2620
1!
1(
b100 .
b1111011100101000011110000001111 &
1#
1*
#2625
0!
0(
#2630
1!
1(
b1001 .
b10111000110011111101101100000100 &
#2635
0!
0(
#2640
1!
1(
b10011 .
b1100111100101011001011000110101 &
#2645
0!
0(
#2650
1!
1(
b111 .
b100001100111101111100101110010 &
#2655
0!
0(
#2660
1!
1(
b1111 .
b11111000011010101000101001001011 &
0#
0*
#2665
0!
0(
#2670
1!
1(
b11110 .
b11100000101000011000110100010000 &
1#
1*
#2675
0!
0(
#2680
1!
1(
b11101 .
b10100010100101111100010111010001 &
#2685
0!
0(
#2690
1!
1(
b11011 .
b10101110011001100000010101011110 &
0#
0*
#2695
0!
0(
#2700
1!
1(
b10110 .
b11011011010101100001001001000111 &
#2705
0!
0(
#2710
1!
1(
b1100 .
b10101001000010011110111011100 &
#2715
0!
0(
#2720
1!
1(
b11000 .
b11011001100111101011010100101101 &
1#
1*
#2725
0!
0(
#2730
1!
1(
b10001 .
b1000011101110101111000001010 &
0#
0*
#2735
0!
0(
#2740
1!
1(
b10 .
b110101011001101101000000000011 &
#2745
0!
0(
#2750
1!
1(
b100 .
b11001011111001111011100101101000 &
1#
1*
#2755
0!
0(
#2760
1!
1(
b1001 .
b11000110011000011100000001001001 &
0#
0*
#2765
0!
0(
#2770
1!
1(
b10010 .
b10010011010100111010111101110110 &
#2775
0!
0(
#2780
1!
1(
b100 .
b11101001011000100111111101111111 &
#2785
0!
0(
#2790
1!
1(
b1000 .
b1100011110110001000101110110100 &
1#
1*
#2795
0!
0(
#2800
1!
1(
b10001 .
b1111111001101000000001100100101 &
0#
0*
#2805
0!
0(
#2810
1!
1(
b10 .
b10000011111101000110010110100010 &
1#
1*
#2815
0!
0(
#2820
1!
1(
b101 .
b1111001100000001001110010111011 &
#2825
0!
0(
#2830
1!
1(
b1011 .
b1110000101011100000000011000000 &
#2835
0!
0(
#2840
1!
1(
b10111 .
b10010001000000101100111000001 &
0#
0*
#2845
0!
0(
#2850
1!
1(
b1110 .
b10000010001101111010110010001110 &
#2855
0!
0(
#2860
1!
1(
b11100 .
b11000110111001100110001110110111 &
1#
1*
#2865
0!
0(
#2870
1!
1(
b11001 .
b1011101010001010010010010001100 &
0#
0*
#2875
0!
0(
#2880
1!
1(
b10010 .
b1010111110001010110000000011101 &
1#
1*
#2885
0!
0(
#2890
1!
1(
b101 .
b10101111000011000111000000111010 &
0#
0*
#2895
0!
0(
#2900
1!
1(
b1010 .
b111110111000101101000001110011 &
1#
1*
#2905
0!
0(
#2910
1!
1(
b10101 .
b10110000101010011100001100011000 &
#2915
0!
0(
#2920
1!
1(
b1011 .
b11011001111100010111001000111001 &
#2925
0!
0(
#2930
1!
1(
b10111 .
b111011010111100101110010100110 &
0#
0*
#2935
0!
0(
#2940
1!
1(
b1110 .
b10110001111010101001111011101111 &
1#
1*
#2945
0!
0(
#2950
1!
1(
b11101 .
b1111000100110100001100100 &
#2955
0!
0(
#2960
1!
1(
b11011 .
b1101001111111101010110000010101 &
#2965
0!
0(
#2970
1!
1(
b10111 .
b1111011110000011101110111010010 &
#2975
0!
0(
#2980
1!
1(
b1111 .
b11010000010101000100101100101011 &
0#
0*
#2985
0!
0(
#2990
1!
1(
b11110 .
b1100110011111000110000001110000 &
#2995
0!
0(
#3000
1!
1(
b11100 .
b11000010111011101110100110110001 &
1#
1*
#3005
0!
0(
#3010
1!
1(
b11001 .
b100100111000000001111110111110 &
#3015
0!
0(
#3020
1!
1(
b10011 .
b1000110101000001000100100111 &
#3025
0!
0(
#3030
1!
1(
b111 .
b11100111110101111011011100111100 &
#3035
0!
0(
#3040
1!
1(
b1111 .
b1010011010001111100011100001101 &
0#
0*
#3045
0!
0(
#3050
1!
1(
b11110 .
b11100101000110000111001101010 &
1#
1*
#3055
0!
0(
#3060
1!
1(
b11101 .
b1000100101101111110110011100011 &
#3065
0!
0(
#3070
1!
1(
b11011 .
b1001011001100110011100011001000 &
0#
0*
#3075
0!
0(
#3080
1!
1(
b10110 .
b1010101011101010000000101001 &
1#
1*
#3085
0!
0(
#3090
1!
1(
b1101 .
1,
b1100001000010101010111010110 &
0#
0*
1%
b111 '
#3095
0!
0(
#3100
1!
1(
0,
b11010 .
b10111101111000111001101001011111 &
1#
1*
0%
#3105
0!
0(
#3110
1!
1(
b10101 .
b111000011110000111000100010100 &
0#
0*
#3115
0!
0(
#3120
1!
1(
b1010 .
b11000111010001001001000100000101 &
#3125
0!
0(
#3130
1!
1(
b10100 .
b10011110010010100110001000000010 &
#3135
0!
0(
#3140
1!
1(
b1000 .
b11101010100011001001010110011011 &
1#
1*
#3145
0!
0(
#3150
1!
1(
b10001 .
b10001011110001111010110000100000 &
#3155
0!
0(
#3160
1!
1(
b11 .
b10111110110000100111010110100001 &
#3165
0!
0(
#3170
1!
1(
b111 .
b10111010100100101111011101110 &
0#
0*
#3175
0!
0(
#3180
1!
1(
b1110 .
b111010101101100001101010010111 &
1#
1*
#3185
0!
0(
