Submits/RTL_Design_and_Integration_Material/Ibrahim_Verilog_Codes/13_Sequential_Multiplier_Constructionist/sequential_multiplier_NoFSM.v
// This Code is designed in a way that Multiplicand_length has to be always greater then Multiplier_length

module seq_mult(a, b, ab_valid, ab_ready, clk, rst, z_valid, z);

	parameter Multiplicand_length = 5;
	parameter Multiplier_length = 2;
	
	input [Multiplicand_length-1: 0] a;
	input [Multiplier_length-1: 0] b;
	input ab_valid;
	input clk;
	input rst;
	output reg ab_ready;
	output reg z_valid;
    output reg [Multiplier_length+Multiplicand_length-1: 0] z;

	reg [Multiplier_length-1: 0] multiplier_reg, multiplier_next;	
	reg [Multiplier_length+Multiplicand_length-1:0] multiplicand_reg, multiplicand_next;	
	reg ab_valid_reg;
	reg [Multiplier_length+Multiplicand_length-1:0] z_reg, z_next; 
	reg ab_ready_next, ab_ready_reg, z_valid_reg, z_valid_next;

	always @ (posedge clk or negedge rst) begin 
		if (~rst) begin
			multiplier_reg <= 'd0;
			multiplicand_reg <= 'd0;
			ab_valid_reg <= 'b0;
			ab_ready_reg <= 'b1; // if rst ab_ready_reg=1 because then we are indicating that our design is in idle state
			z_valid_reg <= 'b0;
			z_reg <= 'd0;
		end 
		else begin 
			multiplier_reg <= multiplier_next;
			multiplicand_reg <= multiplicand_next;
			ab_valid_reg <= ab_valid;
			ab_ready_reg <= ab_ready_next;
			z_valid_reg <= z_valid_next;
			z_reg <= z_next; 	
		end 
	end

	always @(*) begin 
		//multiplier_next = multiplier_reg;
		//multiplicand_next = multiplicand_reg;
		//ab_ready_next = ab_ready_reg;
		//z_valid_next = z_valid_reg;
		//z_next = z_reg;
		//state_next = state_reg;

		ab_ready = ab_ready_reg; // here as soon as we are finishing calculations we transfer the values of these to the final output
		z_valid = z_valid_reg;
		z = z_reg;    		
			
		// idle state
		if (ab_ready_reg == 1) begin 
			ab_ready_next = 'b1;
			z_valid_next = 'b0;				
          	if(ab_valid_reg) begin 
				multiplicand_next = 'd0;
				multiplicand_next = multiplicand_next + a;                  
				multiplier_next = b;			
				ab_ready_next = 'b0;
				z_next = 'd0;
			end 
		end
		
		// mult state
		else begin // ab_ready_reg == 0
			if (multiplier_reg[0] == 'b1) begin 
				z_next = z_reg + multiplicand_reg;
			end
			else begin 
				z_next = z_reg;
			end	

			multiplier_next = multiplier_reg >> 'b1;
			multiplicand_next = multiplicand_reg << 'b1;
			
			ab_ready_next = 'b0;
			if(multiplier_reg == 'd0) begin
				ab_ready_next = 'b1;
				z_valid_next = 'b1;
			end	
		end 
			
	end

endmodule

// problem is that with state machine as soon as ab_valid is high 
// once, the state is locked to mult, how can this be done without
// state machine and be ensured that the state remains mult until
// output is thrown even though ab_valid is high

Submits/RTL_Design_and_Integration_Material/Ibrahim_Verilog_Codes/13_Sequential_Multiplier_Constructionist/tb.v
`include "sequential_multiplier_NoFSM.v"

module tb;
	// Declare IO's
	parameter Multiplicand_length = 5;
	parameter Multiplier_length = 2;	
	
	reg [Multiplicand_length-1: 0] a;
	reg [Multiplier_length-1: 0] b;
	reg ab_valid;
	reg clk;
	reg rst;
	wire ab_ready;
	wire z_valid;
	wire [Multiplier_length+Multiplicand_length-1: 0] z;
	
	// Declare clk
	initial begin 
		clk = 0;
		forever #1 clk = ~clk;
	end 
	
	// Instantiate design 
  seq_mult #(.Multiplicand_length(Multiplicand_length), .Multiplier_length(Multiplier_length)) dut 	 	(
	.a(a), 
	.b(b), 
	.ab_valid(ab_valid),
	.ab_ready(ab_ready),
	.clk(clk),
	.rst(rst),
	.z_valid(z_valid),
	.z(z));
	
	// Drive Inputs
	initial begin 
		rst = 0; 
		#5;
		rst = 1;
		#5;
      repeat (50) begin 
			@(posedge clk) begin
              	ab_valid = $random;
				a = $random;
				b = $random;
			end
		end
		@(posedge clk) begin 
				ab_valid = 0;
			end		
		#100;
		$finish();
	end 
	
	initial begin 
		$monitor("time=%0t, a=%d, b=%d, ab_valid=%d, rst=%d, z=%d, z_valid=%d, ab_ready=%d", $time, a, b, ab_valid, rst, z, z_valid, ab_ready);
	end	
	
	// Dump Variables
	initial begin 
		$dumpfile("waves.vcd");
		$dumpvars;
		
	end
	
endmodule

Submits/RTL_Design_and_Integration_Material/Ibrahim_Verilog_Codes/13_Sequential_Multiplier_Constructionist/waves.vcd
$date
	Sat May 06 17:10:53 2023
$end
$version
	QuestaSim Version 10.6c
$end
$timescale
	1ns
$end

$scope module tb $end
$var parameter 32 ! Multiplicand_length $end
$var parameter 32 " Multiplier_length $end
$var reg 5 # a [4:0] $end
$var reg 2 $ b [1:0] $end
$var reg 1 % ab_valid $end
$var reg 1 & clk $end
$var reg 1 ' rst $end
$var wire 1 ( ab_ready $end
$var wire 1 ) z_valid $end
$var wire 1 * z [6] $end
$var wire 1 + z [5] $end
$var wire 1 , z [4] $end
$var wire 1 - z [3] $end
$var wire 1 . z [2] $end
$var wire 1 / z [1] $end
$var wire 1 0 z [0] $end

$scope module dut $end
$var parameter 32 1 Multiplicand_length $end
$var parameter 32 2 Multiplier_length $end
$var wire 1 3 a [4] $end
$var wire 1 4 a [3] $end
$var wire 1 5 a [2] $end
$var wire 1 6 a [1] $end
$var wire 1 7 a [0] $end
$var wire 1 8 b [1] $end
$var wire 1 9 b [0] $end
$var wire 1 : ab_valid $end
$var wire 1 ; clk $end
$var wire 1 < rst $end
$var reg 1 = ab_ready $end
$var reg 1 > z_valid $end
$var reg 7 ? z [6:0] $end
$var reg 2 @ multiplier_reg [1:0] $end
$var reg 2 A multiplier_next [1:0] $end
$var reg 7 B multiplicand_reg [6:0] $end
$var reg 7 C multiplicand_next [6:0] $end
$var reg 1 D ab_valid_reg $end
$var reg 7 E z_reg [6:0] $end
$var reg 7 F z_next [6:0] $end
$var reg 1 G ab_ready_next $end
$var reg 1 H ab_ready_reg $end
$var reg 1 I z_valid_reg $end
$var reg 1 J z_valid_next $end
$upscope $end
$upscope $end
$enddefinitions $end
#0
$dumpvars
bx #
bx $
x%
0&
0'
1=
0>
b0 ?
b0 @
bx A
b0 B
bx C
0D
b0 E
bx F
1G
1H
0I
0J
b101 !
b10 "
b101 1
b10 2
1(
0)
00
0/
0.
0-
0,
0+
0*
0<
0;
x:
x9
x8
x7
x6
x5
x4
x3
$end
#1
1&
1;
#2
0&
0;
#3
1&
1;
#4
0&
0;
#5
1'
1&
1<
1;
bx @
bx B
xD
bx E
bx ?
x0
x/
x.
x-
x,
x+
x*
#6
0&
0;
#7
1&
1;
#8
0&
0;
#9
1&
1;
#10
0&
0;
#11
1&
1;
0%
b1 #
b1 $
0:
19
08
17
06
05
04
03
#12
0&
0;
#13
1&
1;
1%
b1101 #
1:
15
14
0D
#14
0&
0;
#15
1&
1;
b10010 #
07
16
05
04
13
1D
b0 C
b10010 C
b1 A
0G
b0 F
#16
0&
0;
#17
1&
1;
b10110 #
15
1G
b0 C
b10110 C
0G
b1 @
b10010 B
0H
b0 E
0=
b0 ?
b10010 F
b0 A
b100100 C
0(
00
0/
0.
0-
0,
0+
0*
#18
0&
0;
#19
1&
1;
b1100 #
06
14
03
b0 @
b100100 B
b10010 E
b10010 ?
b1001000 C
1G
1J
1/
1,
#20
0&
0;
#21
1&
1;
0%
b101 #
b10 $
0:
09
18
17
04
0G
1G
b1001000 B
1H
1I
1=
1>
0J
b0 C
b101 C
b10 A
0G
b0 F
1(
1)
#22
0&
0;
#23
1&
1;
1%
b10111 #
1:
16
13
1G
b0 C
b10111 C
0G
b10 @
b101 B
0D
0H
0I
b0 E
0=
0>
b0 ?
b1 A
b1010 C
0(
0)
0/
0,
#24
0&
0;
#25
1&
1;
b10010 #
07
05
b1 @
b1010 B
1D
b1010 F
b0 A
b10100 C
#26
0&
0;
#27
1&
1;
0%
b101 #
b0 $
0:
08
17
06
15
03
b0 @
b10100 B
b1010 E
b1010 ?
b101000 C
1G
1J
1/
1-
#28
0&
0;
#29
1&
1;
1%
b1101 #
b1 $
1:
19
14
0G
1G
b101000 B
0D
1H
1I
1=
1>
0J
1(
1)
#30
0&
0;
#31
1&
1;
b1010 #
b0 $
09
07
16
05
1D
0I
0>
b0 C
b1010 C
0G
b0 F
0)
#32
0&
0;
#33
1&
1;
0%
b1 $
0:
19
1G
b0 C
b1010 C
b1 A
0G
b1010 B
0H
b0 E
0=
b0 ?
b0 A
b10100 C
1G
1J
0(
0/
0-
#34
0&
0;
#35
1&
1;
b10011 #
17
04
13
0G
1G
b10100 B
0D
1H
1I
1=
1>
0J
1(
1)
#36
0&
0;
#37
1&
1;
1%
b1011 #
1:
14
03
0I
0>
0)
#38
0&
0;
#39
1&
1;
0%
b1110 #
0:
07
15
1D
b0 C
b1110 C
b1 A
0G
#40
0&
0;
#41
1&
1;
1%
b11 #
b10 $
1:
09
18
17
05
04
1G
b0 C
b11 C
b10 A
0G
b1 @
b1110 B
0D
0H
0=
b1110 F
b0 A
b11100 C
0(
#42
0&
0;
#43
1&
1;
0%
b11100 #
0:
07
06
15
14
13
b0 @
b11100 B
1D
b1110 E
b1110 ?
b111000 C
1G
1J
1/
1.
1-
#44
0&
0;
#45
1&
1;
b1 #
b0 $
08
17
05
04
03
0G
1G
b111000 B
0D
1H
1I
1=
1>
0J
1(
1)
#46
0&
0;
#47
1&
1;
b1001 #
b11 $
19
18
14
0I
0>
0)
#48
0&
0;
#49
1&
1;
b110 #
b10 $
09
07
16
15
04
#50
0&
0;
#51
1&
1;
b1010 #
b11 $
19
05
14
#52
0&
0;
#53
1&
1;
1%
b101 #
1:
17
06
15
04
#54
0&
0;
#55
1&
1;
b11010 #
b10 $
09
07
16
05
14
13
1D
b0 C
b11010 C
b10 A
0G
b0 F
#56
0&
0;
#57
1&
1;
b10001 #
b1 $
19
08
17
06
04
1G
b0 C
b10001 C
b1 A
0G
b10 @
b11010 B
0H
b0 E
0=
b0 ?
b110100 C
0(
0/
0.
0-
#58
0&
0;
#59
1&
1;
0%
b1100 #
b11 $
0:
18
07
15
14
03
b1 @
b110100 B
b110100 F
b0 A
b1101000 C
#60
0&
0;
#61
1&
1;
1%
b11000 #
1:
05
13
b0 @
b1101000 B
0D
b110100 E
b110100 ?
b1010000 C
1G
1J
1.
1,
1+
#62
0&
0;
#63
1&
1;
b11100 #
15
0G
1G
b1010000 B
1D
1H
1I
1=
1>
0J
b0 C
b11100 C
b11 A
0G
b0 F
1(
1)
#64
0&
0;
#65
1&
1;
b1001 #
b0 $
09
08
17
05
03
1G
b0 C
b1001 C
b