Submits/RTL_Design_and_Integration_Material/Ibrahim_Verilog_Codes/7_Clock Generation/practice/tb_clock_5.v
`timescale 1ns/1ps // time period for 30MHz freq is 33.33ns

//100Mhz => 10ns
// hence clock period is 10ns hence both positive and negative clocks will be 5ns each
// by default time step in verilog and precision is 1ns/1ns

module tb;
reg clk;
real tp, freq, duty;
real jitter_factor, tp_jitter, jitter;
real prev_edge_time, cur_edge_time, tp_calc, freq_calc;

always begin
	jitter_factor = $urandom_range(100-jitter, 100+jitter)/100.0;
	tp_jitter = tp*jitter_factor;
	clk = 0; #(tp_jitter * (duty/100));
	clk = 1; #(tp_jitter * ((100-duty)/100));
end

// Use a seprarate initial block for command line argument passing
initial begin 
	$value$plusargs("freq=%f", freq); //in MHz
	$value$plusargs("duty=%f", duty); //in MHz
	$value$plusargs("jitter=%f", jitter); //in MHz
	// convert frequency to time period
	// equation to convert MHz into ns = 1000/freq ns
	tp = 1000 / freq; // in ns
	#200;
	$finish;	
end

always @(posedge clk) begin
	prev_edge_time = cur_edge_time;
	cur_edge_time = $realtime;
	tp_calc = cur_edge_time - prev_edge_time;
	freq_calc = 1000/tp_calc; // ns to MHz conversion equation
	$display("freq_cal = %f", freq_calc);


end



// dump waves
initial begin 
	$dumpfile("waves.vcd");
	$dumpvars;
end

endmodule

Submits/RTL_Design_and_Integration_Material/Ibrahim_Verilog_Codes/7_Clock Generation/practice/waves.vcd
$date
	Sat Apr 22 13:29:22 2023
$end
$version
	QuestaSim Version 10.6c
$end
$timescale
	1ps
$end

$scope module tb $end
$var reg 1 ! clk $end
$var real 0 " tp $end
$var real 0 # freq $end
$var real 0 $ duty $end
$var real 0 % jitter_factor $end
$var real 0 & tp_jitter $end
$var real 0 ' jitter $end
$var real 0 ( prev_edge_time $end
$var real 0 ) cur_edge_time $end
$var real 0 * tp_calc $end
$var real 0 + freq_calc $end
$upscope $end
$enddefinitions $end
#0
$dumpvars
0!
r5 "
r200 #
r50 $
r1.05 %
r5.25 &
r5 '
r0 (
r0 )
r0 *
r1.#INF +
$end
#2625
1!
r2.625 )
r2.625 *
r380.952380952381 +
#5250
r1.03 %
r5.15 &
0!
#7825
1!
r2.625 (
r7.825 )
r5.2 *
r192.3076923076923 +
#10400
r0.98 %
r4.9 &
0!
#12850
1!
r7.825 (
r12.85 )
r5.025 *
r199.0049751243781 +
#15300
r1 %
r5 &
0!
#17800
1!
r12.85 (
r17.8 )
r4.950000000000001 *
r202.020202020202 +
#20300
r1.04 %
r5.2 &
0!
#22900
1!
r17.8 (
r22.9 )
r5.099999999999998 *
r196.0784313725491 +
#25500
r0.98 %
r4.9 &
0!
#27950
1!
r22.9 (
r27.95 )
r5.050000000000001 *
r198.019801980198 +
#30400
r1.05 %
r5.25 &
0!
#33025
1!
r27.95 (
r33.025 )
r5.074999999999999 *
r197.0443349753695 +
#35650
r1.01 %
r5.05 &
0!
#38175
1!
r33.025 (
r38.175 )
r5.149999999999999 *
r194.1747572815534 +
#40700
r0.98 %
r4.9 &
0!
#43150
1!
r38.175 (
r43.15 )
r4.975000000000001 *
r201.0050251256281 +
#45600
r1.04 %
r5.2 &
0!
#48200
1!
r43.15 (
r48.2 )
r5.050000000000004 *
r198.0198019801979 +
#50800
r0.98 %
r4.9 &
0!
#53250
1!
r48.2 (
r53.25 )
r5.049999999999997 *
r198.0198019801981 +
#55700
r0.99 %
r4.95 &
0!
#58175
1!
r53.25 (
r58.175 )
r4.924999999999997 *
r203.0456852791879 +
#60650
r0.97 %
r4.85 &
0!
#63075
1!
r58.175 (
r63.075 )
r4.900000000000006 *
r204.081632653061 +
#65500
r1.05 %
r5.25 &
0!
#68125
1!
r63.075 (
r68.125 )
r5.049999999999997 *
r198.0198019801981 +
#70750
0!
#73375
1!
r68.125 (
r73.375 )
r5.25 *
r190.4761904761905 +
#76000
r1 %
r5 &
0!
#78500
1!
r73.375 (
r78.5 )
r5.125 *
r195.1219512195122 +
#81000
r0.97 %
r4.85 &
0!
#83425
1!
r78.5 (
r83.425 )
r4.924999999999997 *
r203.0456852791879 +
#85850
r1 %
r5 &
0!
#88350
1!
r83.425 (
r88.34999999999999 )
#90850
r0.98 %
r4.9 &
0!
#93300
1!
r88.34999999999999 (
r93.3 )
r4.950000000000003 *
r202.0202020202019 +
#95750
r0.96 %
r4.8 &
0!
#98150
1!
r93.3 (
r98.15000000000001 )
r4.850000000000009 *
r206.1855670103089 +
#100550
r1.05 %
r5.25 &
0!
#103175
1!
r98.15000000000001 (
r103.175 )
r5.024999999999992 *
r199.0049751243785 +
#105800
r0.98 %
r4.9 &
0!
#108250
1!
r103.175 (
r108.25 )
r5.075000000000003 *
r197.0443349753693 +
#110700
0!
#113150
1!
r108.25 (
r113.15 )
r4.900000000000006 *
r204.081632653061 +
#115600
r1.04 %
r5.2 &
0!
#118200
1!
r113.15 (
r118.2 )
r5.049999999999997 *
r198.0198019801981 +
#120800
r0.98 %
r4.9 &
0!
#123250
1!
r118.2 (
r123.25 )
#125700
r1.04 %
r5.2 &
0!
#128300
1!
r123.25 (
r128.3 )
r5.050000000000011 *
r198.0198019801976 +
#130900
r0.99 %
r4.95 &
0!
#133375
1!
r128.3 (
r133.375 )
r5.074999999999989 *
r197.0443349753699 +
#135850
r0.95 %
r4.75 &
0!
#138225
1!
r133.375 (
r138.225 )
r4.849999999999994 *
r206.1855670103095 +
#140600
r0.96 %
r4.8 &
0!
#143000
1!
r138.225 (
r143 )
r4.775000000000006 *
r209.4240837696333 +
#145400
r1.05 %
r5.25 &
0!
#148025
1!
r143 (
r148.025 )
r5.025000000000006 *
r199.0049751243779 +
#150650
r1 %
r5 &
0!
#153150
1!
r148.025 (
r153.15 )
r5.125 *
r195.1219512195122 +
#155650
r1.05 %
r5.25 &
0!
#158275
1!
r153.15 (
r158.275 )
#160900
r1.04 %
r5.2 &
0!
#163500
1!
r158.275 (
r163.5 )
r5.224999999999994 *
r191.3875598086127 +
#166100
r0.95 %
r4.75 &
0!
#168475
1!
r163.5 (
r168.475 )
r4.974999999999994 *
r201.0050251256284 +
#170850
r0.99 %
r4.95 &
0!
#173325
1!
r168.475 (
r173.325 )
r4.849999999999994 *
r206.1855670103095 +
#175800
r0.97 %
r4.85 &
0!
#178225
1!
r173.325 (
r178.225 )
r4.900000000000006 *
r204.081632653061 +
#180650
r1.01 %
r5.05 &
0!
#183175
1!
r178.225 (
r183.175 )
r4.950000000000017 *
r202.0202020202013 +
#185700
r0.96 %
r4.8 &
0!
#188100
1!
r183.175 (
r188.1 )
r4.924999999999983 *
r203.0456852791885 +
#190500
r0.99 %
r4.95 &
0!
#192975
1!
r188.1 (
r192.975 )
r4.875 *
r205.1282051282051 +
#195450
r1 %
r5 &
0!
#197950
1!
r192.975 (
r197.95 )
r4.974999999999994 *
r201.0050251256284 +
