Submits/RTL_Design_and_Integration_Material/Verilog_codes/2_full_adder_single_bit/full_adder.v
module half_adder(a, b, carry_in, sum, carry_out);
	input a;
	input b; 
	input carry_in;
	
	output sum;
	output carry_out;
	
	wire s1; // sum wires 
	wire c1, c2; // carry
	
	xor x1 (s1, a, b);
	// xor (s1, a, b); This is allowed as well. You can skip giving gate name
	xor x2 (sum, s1, carry_in);
	and a1 (c2, a, b);
	and a2 (c1, s1, carry_in);
	or o1(carry_out, c1, c2);
	
endmodule

Submits/RTL_Design_and_Integration_Material/Verilog_codes/2_full_adder_single_bit/tb_full_adder.v
module tb_half_adder();
	reg tb_a; 
	reg tb_b;
	reg tb_carry_in;
	wire tb_sum; 
	wire tb_carry_out;
	
	//instantiate the design
	half_adder dut (.a(tb_a),
					.b(tb_b),
					.carry_in(tb_carry_in),
					.sum(tb_sum),
					.carry_out(tb_carry_out)
					);

	// drive inputs
	initial begin 
		repeat (20) begin 
			tb_a = $random;
			tb_b = $random;
			tb_carry_in = $random;
			#1;
		end
	end 
	
	// dump variables
	initial begin
		$dumpfile("full_adder.vcd");
		$dumpvars;
	end
	
	// monitor outputs
	initial begin
		$monitor("time - %0t, a=%d, b=%d, carry_in=%d, sum=%d, carry_out=%d", $time, tb_a, tb_b, tb_carry_in, tb_sum, tb_carry_out);
	end	
	

endmodule

Submits/RTL_Design_and_Integration_Material/Verilog_codes/2_full_adder_single_bit/full_adder.vcd
$date
	Fri Apr 07 11:17:37 2023
$end
$version
	Icarus Verilog
$end
$timescale
	1s
$end
$scope module tb_half_adder $end
$var wire 1 ! tb_sum $end
$var wire 1 " tb_carry_out $end
$var reg 1 # tb_a $end
$var reg 1 $ tb_b $end
$var reg 1 % tb_carry_in $end
$scope module dut $end
$var wire 1 # a $end
$var wire 1 $ b $end
$var wire 1 & c1 $end
$var wire 1 ' c2 $end
$var wire 1 % carry_in $end
$var wire 1 " carry_out $end
$var wire 1 ( s1 $end
$var wire 1 ! sum $end
$upscope $end
$upscope $end
$enddefinitions $end
#0
$dumpvars
1(
0'
1&
1%
1$
0#
1"
0!
$end
#1
1!
0&
0(
1'
1#
#2
0!
1&
1"
1(
0'
0$
#5
0"
1!
0&
0%
1$
0#
#6
0!
1"
0(
1'
1#
#7
1!
0"
1(
0'
0$
#8
1$
0#
#9
1"
0(
1'
1%
1#
#10
0"
1(
0'
0%
0$
#11
0(
1%
0#
#12
1"
0!
1&
1(
1$
#13
1!
0&
0(
1'
1#
#14
0"
0'
0$
0#
#15
1"
0!
1'
0%
1$
1#
#16
0"
0'
0$
0#
#17
1!
1(
1$
#18
1"
0!
1&
1%
#19
0"
0&
0(
0%
0$
