Submits/RTL_Design_and_Integration_Material/Ibrahim_Verilog_Codes/1_Mux_2_to_1/mux_2_to_1.v
module mux_2_to_1 (a, b, out, outbar, sel);
	input [7:0] a, b;
    	input sel;
	output [7:0] out, outbar;
	reg [7:0] out;

	assign outbar = ~out;
	
	always @(a or b or sel) begin 
		out = (sel == 1'b1) ? a : b;
	end

endmodule

Submits/RTL_Design_and_Integration_Material/Ibrahim_Verilog_Codes/1_Mux_2_to_1/tb_mux2to1.v
module tb;
	// 1. Declare variables
	reg [7:0] a, b;
	reg sel;
	wire [7:0] out, outbar;
	
	// 2. Instantiate the design
	mux_2_to_1 dut (.a(a), .b(b), .sel(sel), .out(out), .outbar(outbar));

	// 3. Drive Inputs
	initial begin // started at time 0
		repeat (20) begin 
		a = $urandom_range(1, 900);
		b = $urandom_range(1, 900);
		sel = $random;
		#1;
		end
		// simulation will exit here, since intial functionality has completed
	end // 0 time
	// 4. Monitor Inputs
	initial begin
		$monitor("time = %0t, a = %d, b = %d, sel = %d, out = %d, outbar = %d", $time, a, b, sel, out, outbar);
	end
	
	//5. Log waves
	initial begin 
		$dumpfile("mux.vcd");
		$dumpvars; // This should always come after dumpfile
	end
endmodule

Submits/RTL_Design_and_Integration_Material/Ibrahim_Verilog_Codes/1_Mux_2_to_1/mux.vcd
$date
	Tue Apr 18 23:37:33 2023
$end
$version
	QuestaSim Version 10.6c
$end
$timescale
	1ns
$end

$scope module tb $end
$var reg 8 ! a [7:0] $end
$var reg 8 " b [7:0] $end
$var reg 1 # sel $end
$var wire 1 $ out [7] $end
$var wire 1 % out [6] $end
$var wire 1 & out [5] $end
$var wire 1 ' out [4] $end
$var wire 1 ( out [3] $end
$var wire 1 ) out [2] $end
$var wire 1 * out [1] $end
$var wire 1 + out [0] $end
$var wire 1 , outbar [7] $end
$var wire 1 - outbar [6] $end
$var wire 1 . outbar [5] $end
$var wire 1 / outbar [4] $end
$var wire 1 0 outbar [3] $end
$var wire 1 1 outbar [2] $end
$var wire 1 2 outbar [1] $end
$var wire 1 3 outbar [0] $end

$scope module dut $end
$var wire 1 4 a [7] $end
$var wire 1 5 a [6] $end
$var wire 1 6 a [5] $end
$var wire 1 7 a [4] $end
$var wire 1 8 a [3] $end
$var wire 1 9 a [2] $end
$var wire 1 : a [1] $end
$var wire 1 ; a [0] $end
$var wire 1 < b [7] $end
$var wire 1 = b [6] $end
$var wire 1 > b [5] $end
$var wire 1 ? b [4] $end
$var wire 1 @ b [3] $end
$var wire 1 A b [2] $end
$var wire 1 B b [1] $end
$var wire 1 C b [0] $end
$var wire 1 D sel $end
$var reg 8 E out [7:0] $end
$var wire 1 , outbar [7] $end
$var wire 1 - outbar [6] $end
$var wire 1 . outbar [5] $end
$var wire 1 / outbar [4] $end
$var wire 1 0 outbar [3] $end
$var wire 1 1 outbar [2] $end
$var wire 1 2 outbar [1] $end
$var wire 1 3 outbar [0] $end
$upscope $end
$upscope $end
$enddefinitions $end
#0
$dumpvars
b1100101 !
b10111111 "
0#
b10111111 E
1+
1*
1)
1(
1'
1&
0%
1$
03
02
01
00
0/
0.
1-
0,
0D
1C
1B
1A
1@
1?
1>
0=
1<
1;
0:
19
08
07
16
15
04
$end
#1
b10111011 !
b111111 "
1#
0<
1:
09
18
17
05
14
1D
b10111011 E
0)
11
#2
b1011011 !
b10111111 "
1<
06
15
04
b1011011 E
0&
1%
0$
1.
0-
1,
#3
b10111 !
b1000011 "
0A
0@
0?
0>
1=
0<
19
08
05
b10111 E
1)
0(
0%
01
10
1-
#4
b11000000 !
b10010011 "
1?
0=
1<
0;
0:
09
07
15
14
b11000000 E
0+
0*
0)
0'
1%
1$
13
12
11
1/
0-
0,
#5
b11 !
b10101101 "
0B
1A
1@
0?
1>
1;
1:
05
04
b11 E
1+
1*
0%
0$
03
02
1-
1,
#6
b0 !
b1110011 "
1B
0A
0@
1?
1=
0<
0;
0:
b0 E
0+
0*
13
12
#7
b111110 !
b11010001 "
0#
0B
0>
1<
1:
19
18
17
16
0D
b11010001 E
1+
1'
1%
1$
03
0/
0-
0,
#8
b10010011 !
b1010 "
1#
0C
1B
1@
0?
0=
0<
1;
09
08
06
14
1D
b10010011 E
1*
0%
02
1-
#9
b1100100 !
b10001010 "
1<
0;
0:
19
07
16
15
04
b1100100 E
0+
0*
1)
0'
1&
1%
0$
13
12
01
1/
0.
0-
1,
#10
b11001000 !
b1000001 "
0#
1C
0B
0@
1=
0<
09
18
06
14
0D
b1000001 E
1+
0)
0&
03
11
1.
#11
b10110110 !
b10101010 "
1#
0C
1B
1@
1>
0=
1<
1:
19
08
17
16
05
1D
b10110110 E
0+
1*
1)
1'
1&
0%
1$
13
02
01
0/
0.
1-
0,
#12
b10001010 !
b10010 "
0@
1?
0>
0<
09
18
07
06
b10001010 E
0)
1(
0'
0&
11
00
1/
1.
#13
b110 !
b11011011 "
0#
1C
1@
1=
1<
19
08
04
0D
b11011011 E
1+
1'
1%
03
0/
0-
#14
b10110101 !
b101000 "
1#
0C
0B
0?
1>
0=
0<
1;
0:
17
16
14
1D
b10110101 E
0*
1)
0(
1&
0%
12
01
10
0.
1-
#15
b10010011 !
b101010 "
0#
1B
1:
09
06
0D
b101010 E
0+
1*
0)
1(
0'
0$
13
02
11
00
1/
1,
#16
b110010 !
b10111101 "
1#
1C
0B
1A
1?
1<
0;
16
04
1D
b110010 E
0(
1'
10
0/
#17
b1100101 !
b11111 "
0#
1B
0>
0<
1;
0:
19
07
15
0D
b11111 E
1+
1)
1(
0&
03
01
00
1.
#18
b1101101 !
b11100011 "
1#
0A
0@
0?
1>
1=
1<
18
1D
b1101101 E
0*
0'
1&
1%
12
1/
0.
0-
#19
b10001101 !
b1101100 "
0C
0B
1A
1@
0<
06
05
14
b10001101 E
0&
0%
1$
1.
1-
0,
