Submits/RTL_Design_and_Integration_Material/Verilog_codes/6_3bit_updown_counter/up_down_counter.v
module up_down_counter_behav (clk, rst, count, up_down);
	input clk, rst, up_down;
	output reg [2:0] count; // reg is required because in between positive edges count should hold the value
	
	always @ (posedge clk) begin
		if (rst == 1) count = 0;
		else begin 
			if (up_down == 1) count = count + 1;
			if (up_down == 0) count = count - 1;
		end
	end

endmodule

Submits/RTL_Design_and_Integration_Material/Verilog_codes/6_3bit_updown_counter/tb_up_down_counter.v
module tb_up_down_counter();
	reg tb_clk, tb_rst, tb_up_down; // default value of reg is x
	wire [2:0] tb_count;
	integer delay;
	
	// instantiate the design 
	up_down_counter_behav DUT (.clk(tb_clk), .rst(tb_rst), .count(tb_count), .up_down(tb_up_down));
					
	// Monitor output
	initial begin
		$monitor("time - %0t, clk = %d, rst = %d, , up_down = %d, count = %d", $time, tb_clk, tb_rst, tb_up_down, tb_count);
	end
	
	/*
	// clock generation 
	initial begin 
		tb_clk = 0;
		//repeat (200) begin 
		forever begin
		#50 tb_clk = ~tb_clk;	
		end
	end
	*/
	
	/*
	// clock generation
	initial begin 
		tb_clk = 0;
	end
	always begin
		#50 tb_clk = ~tb_clk;	
	end
	*/
	
	// clock generation
	always begin 
		tb_clk = 0; #50;
		tb_clk = 1; #50;
	end
	
	/*
	// Drive Inputs
	initial begin 
		tb_rst = 1;
		#100;
		tb_rst = 0;
		tb_up_down = 0; // down_counter
		// count will start automatically
		// let the count happen for sometime, then end the simulations ($finish)
		#500;
		tb_up_down = 1;
		#500;
		tb_up_down = 0;
		#500;
		tb_up_down = 1;
		#500;
		tb_up_down = 0;		
		#500;
		$finish;
	end
	*/
	
	// Drive Inputs
	initial begin 
		tb_rst = 1;
		#100;
		tb_rst = 0;
		tb_up_down = 0; // down_counter
		repeat (50) begin 
			tb_up_down = $random;
			delay = $urandom_range(50, 200); //u: unsigned(+number), random_range: number in the range
			#delay;
		end 
		#1000;
		$finish;
	end	
	
	initial begin 
		//$dumpvars(0, tb_2x1Mux);
		$dumpfile("tb_up_down_counter.vcd");
		$dumpvars; // This should always come after dumpfile
	end
endmodule

Submits/RTL_Design_and_Integration_Material/Verilog_codes/6_3bit_updown_counter/tb_up_down_counter.vcd
$date
	Sat Apr 08 15:45:47 2023
$end
$version
	Icarus Verilog
$end
$timescale
	1s
$end
$scope module tb_up_down_counter $end
$var wire 3 ! tb_count [2:0] $end
$var reg 1 " tb_clk $end
$var reg 1 # tb_rst $end
$var reg 1 $ tb_up_down $end
$var integer 32 % delay [31:0] $end
$scope module DUT $end
$var wire 1 " clk $end
$var wire 1 # rst $end
$var wire 1 $ up_down $end
$var reg 3 & count [2:0] $end
$upscope $end
$upscope $end
$enddefinitions $end
#0
$dumpvars
bx &
bx %
x$
1#
0"
bx !
$end
#50
b0 !
b0 &
1"
#100
0"
b10001000 %
0$
0#
#150
b111 !
b111 &
1"
#200
0"
#236
b1011000 %
1$
#250
b0 !
b0 &
1"
#300
0"
#324
b110100 %
#350
b1 !
b1 &
1"
#376
b1001111 %
#400
0"
#450
b10 !
b10 &
1"
#455
b10000001 %
#500
0"
#550
b11 !
b11 &
1"
#584
b10100111 %
#600
0"
#650
b100 !
b100 &
1"
#700
0"
#750
b101 !
b101 &
1"
#751
b1001111 %
#800
0"
#830
b110111 %
0$
#850
b100 !
b100 &
1"
#885
b1111110 %
1$
#900
0"
#950
b101 !
b101 &
1"
#1000
0"
#1011
b10000001 %
#1050
b110 !
b110 &
1"
#1100
0"
#1140
b10100000 %
0$
#1150
b101 !
b101 &
1"
#1200
0"
#1250
b100 !
b100 &
1"
#1300
0"
b10001111 %
1$
#1350
b101 !
b101 &
1"
#1400
0"
#1443
b11000011 %
#1450
b110 !
b110 &
1"
#1500
0"
#1550
b111 !
b111 &
1"
#1600
0"
#1638
b10100110 %
0$
#1650
b110 !
b110 &
1"
#1700
0"
#1750
b101 !
b101 &
1"
#1800
0"
#1804
b11000111 %
1$
#1850
b110 !
b110 &
1"
#1900
0"
#1950
b111 !
b111 &
1"
#2000
0"
#2003
b1101100 %
0$
#2050
b110 !
b110 &
1"
#2100
0"
#2111
1$
#2150
b111 !
b111 &
1"
#2200
0"
#2219
b1100100 %
0$
#2250
b110 !
b110 &
1"
#2300
0"
#2319
b11000001 %
1$
#2350
b111 !
b111 &
1"
#2400
0"
#2450
b0 !
b0 &
1"
#2500
0"
#2512
b1010101 %
#2550
b1 !
b1 &
1"
#2597
b110111 %
0$
#2600
0"
#2650
b0 !
b0 &
1"
#2652
b10100111 %
1$
#2700
0"
#2750
b1 !
b1 &
1"
#2800
0"
#2819
b11000100 %
0$
#2850
b0 !
b0 &
1"
#2900
0"
#2950
b111 !
b111 &
1"
#3000
0"
#3015
b1101111 %
#3050
b110 !
b110 &
1"
#3100
0"
#3126
b1110110 %
#3150
b101 !
b101 &
1"
#3200
0"
#3244
b1101100 %
1$
#3250
b110 !
b110 &
1"
#3300
0"
#3350
b111 !
b111 &
1"
#3352
b10011000 %
0$
#3400
0"
#3450
b110 !
b110 &
1"
#3500
0"
#3504
b1101001 %
1$
#3550
b111 !
b111 &
1"
#3600
0"
#3609
b111111 %
#3650
b0 !
b0 &
1"
#3672
b1001111 %
#3700
0"
#3750
b1 !
b1 &
1"
#3800
0"
#3830
b10000000 %
0$
#3850
b0 !
b0 &
1"
#3900
0"
#3950
b111 !
b111 &
1"
#3958
b1010111 %
#4000
0"
#4045
b10000111 %
#4050
b110 !
b110 &
1"
#4100
0"
#4150
b101 !
b101 &
1"
#4180
b10101111 %
#4200
0"
#4250
b100 !
b100 &
1"
#4300
0"
#4350
b11 !
b11 &
1"
#4355
b1100000 %
1$
#4400
0"
#4450
b100 !
b100 &
1"
#4451
b1011110 %
0$
#4500
0"
#4545
b110111 %
1$
#4550
b101 !
b101 &
1"
#4600
0"
b110101 %
#4650
b110 !
b110 &
1"
#4653
b1001010 %
#4700
0"
#4727
b10011101 %
#4750
b111 !
b111 &
1"
#4800
0"
#4850
b0 !
b0 &
1"
#4884
b1110000 %
#4900
0"
#4950
b1 !
b1 &
1"
#4996
b110010 %
0$
#5000
0"
#5046
b1100101 %
#5050
b0 !
b0 &
1"
#5100
0"
#5147
b10000110 %
1$
#5150
b1 !
b1 &
1"
#5200
0"
#5250
b10 !
b10 &
1"
#5281
b1101111 %
#5300
0"
#5350
b11 !
b11 &
1"
#5392
b10000111 %
#5400
0"
#5450
b100 !
b100 &
1"
#5500
0"
#5527
b10000000 %
0$
#5550
b11 !
b11 &
1"
#5600
0"
#5650
b10 !
b10 &
1"
#5655
b1101101 %
#5700
0"
#5750
b1 !
b1 &
1"
#5764
b1000011 %
#5800
0"
#5850
b0 !
b0 &
1"
#5900
0"
#5950
b111 !
b111 &
1"
#6000
0"
#6050
b110 !
b110 &
1"
#6100
0"
#6150
b101 !
b101 &
1"
#6200
0"
#6250
b100 !
b100 &
1"
#6300
0"
#6350
b11 !
b11 &
1"
#6400
0"
#6450
b10 !
b10 &
1"
#6500
0"
#6550
b1 !
b1 &
1"
#6600
0"
#6650
b0 !
b0 &
1"
#6700
0"
#6750
b111 !
b111 &
1"
