Submits/RTL_Design_and_Integration_Material/Ibrahim_Verilog_Codes/5_UpDowncounter/upDownCounter.v
module up_down_counter(clk, reset, up_down, counter);
	input clk, reset, up_down;
	parameter WIDTH = 4;
	output reg [WIDTH-1:0] counter;

	always @ (posedge clk) begin
		if (reset) counter <= 'b0;
		else if (up_down == 'b1) counter <= counter + 1;
		else counter <= counter - 1;
	end 
endmodule

Submits/RTL_Design_and_Integration_Material/Ibrahim_Verilog_Codes/5_UpDowncounter/tb_upDownCounter.v
`include "upDownCounter.v"
module tb;
	//
	reg clk, reset, up_down;
	parameter WIDTH = 4;
	wire [WIDTH-1:0] counter;
	
	//
	up_down_counter dut (.clk(clk), .reset(reset), .up_down(up_down), .counter(counter));
	
	//
	initial begin	
		clk = 1'b0;
		forever #2 clk = ~clk;
	end 

	//
	initial begin
		reset = 1'b1;
		up_down = 1'b0;
		#5;
		repeat (100) begin 
		{reset, up_down} = $random;
		#2;	
	end
	end 

	
	//
	initial begin 
		$monitor("time=%0t, clk=%d, reset=%d, up_down=%d, counter=%d", $time, clk, reset, up_down, counter);
	end

	//
	initial begin 
		$dumpfile("wave.vcd");
		$dumpvars;
		#100;
		$finish;
	end	
endmodule

Submits/RTL_Design_and_Integration_Material/Ibrahim_Verilog_Codes/5_UpDowncounter/wave.vcd
$date
	Wed Apr 19 08:03:04 2023
$end
$version
	QuestaSim Version 10.6c
$end
$timescale
	1ns
$end

$scope module tb $end
$var parameter 32 ! WIDTH $end
$var reg 1 " clk $end
$var reg 1 # reset $end
$var reg 1 $ up_down $end
$var wire 1 % counter [3] $end
$var wire 1 & counter [2] $end
$var wire 1 ' counter [1] $end
$var wire 1 ( counter [0] $end

$scope module dut $end
$var parameter 32 ) WIDTH $end
$var wire 1 * clk $end
$var wire 1 + reset $end
$var wire 1 , up_down $end
$var reg 4 - counter [3:0] $end
$upscope $end
$upscope $end
$enddefinitions $end
#0
$dumpvars
0"
1#
0$
bx -
b100 !
b100 )
x(
x'
x&
x%
0,
1+
0*
$end
#2
1"
1*
b0 -
0(
0'
0&
0%
#4
0"
0*
#5
0#
0+
#6
1"
1*
b1111 -
1(
1'
1&
1%
#7
1$
1,
#8
0"
0*
#10
1"
1*
b0 -
0(
0'
0&
0%
#11
1#
1+
#12
0"
0*
#13
0#
0+
#14
1"
1*
b1 -
1(
#16
0"
0*
#18
1"
1*
b10 -
0(
1'
#19
0$
1#
0,
1+
#20
0"
0*
#21
1$
0#
1,
0+
#22
1"
1*
b11 -
1(
#24
0"
0*
#25
0$
1#
0,
1+
#26
1"
1*
b0 -
0(
0'
#27
1$
0#
1,
0+
#28
0"
0*
#30
1"
1*
b1 -
1(
#31
0$
0,
#32
0"
0*
#33
1$
1,
#34
1"
1*
b10 -
0(
1'
#35
0$
1#
0,
1+
#36
0"
0*
#37
1$
0#
1,
0+
#38
1"
1*
b11 -
1(
#39
0$
1#
0,
1+
#40
0"
0*
#41
1$
0#
1,
0+
#42
1"
1*
b100 -
0(
0'
1&
#43
1#
1+
#44
0"
0*
#45
0$
0,
#46
1"
1*
b0 -
0&
#47
1$
1,
#48
0"
0*
#49
0$
0,
#50
1"
1*
#52
0"
0*
#53
0#
0+
#54
1"
1*
b1111 -
1(
1'
1&
1%
#55
1$
1,
#56
0"
0*
#57
0$
0,
#58
1"
1*
b1110 -
0(
#59
1$
1,
#60
0"
0*
#62
1"
1*
b1111 -
1(
#64
0"
0*
#65
1#
1+
#66
1"
1*
b0 -
0(
0'
0&
0%
#67
0$
0,
#68
0"
0*
#69
0#
0+
#70
1"
1*
b1111 -
1(
1'
1&
1%
#72
0"
0*
#73
1#
1+
#74
1"
1*
b0 -
0(
0'
0&
0%
#75
1$
0#
1,
0+
#76
0"
0*
#77
0$
1#
0,
1+
#78
1"
1*
#79
1$
1,
#80
0"
0*
#81
0#
0+
#82
1"
1*
b1 -
1(
#83
1#
1+
#84
0"
0*
#86
1"
1*
b0 -
0(
#87
0#
0+
#88
0"
0*
#89
0$
1#
0,
1+
#90
1"
1*
#92
0"
0*
#93
1$
0#
1,
0+
#94
1"
1*
b1 -
1(
#95
1#
1+
#96
0"
0*
#98
1"
1*
b0 -
0(
#99
0$
0,
