Submits/RTL_Design_and_Integration_Material/Verilog_codes/12_Heirarchical_Memory/memory_handshake.v
module memory_handshake(clk_i, rst_i, addr_i, wdata_i, rdata_o, wr_rd_i, valid_i, ready_o);
// 1K memory with 16 bit width
// width=16, depth=1024/16 = 64, addr_width=6

// DO NOT CONFUSE MEMORY WITH FLIPFLOP
// This Verilog code is analogous to simple SRAM memory 

parameter WIDTH = 16;
parameter DEPTH = 16;
parameter ADDR_WIDTH = 4;

input clk_i, rst_i;
input [ADDR_WIDTH-1:0] addr_i;
input [WIDTH-1:0] wdata_i;
output reg [WIDTH-1:0] rdata_o; // Output shall be declared as reg as it has to store data
input wr_rd_i;
input valid_i;
output reg ready_o;

integer i;


reg [WIDTH-1:0] mem [DEPTH-1:0];

always @ (posedge clk_i) begin 
if (rst_i == 1) begin
	rdata_o = 0;
	ready_o = 0;
	for (i=0; i<DEPTH; i=i+1) mem[i] = 0;
end
	
else begin
if (valid_i == 1) begin 
		ready_o = 1;
		if (wr_rd_i == 1) mem[addr_i] = wdata_i;
		else rdata_o = mem[addr_i];
	end 
	else begin
		ready_o = 0;
	end
end

end
endmodule

Submits/RTL_Design_and_Integration_Material/Verilog_codes/12_Heirarchical_Memory/tb_memory.v
`include "memory_handshake.v"

module tb;

// 1K memory with 16 bit width
// width=16, depth=1024/16 = 64, addr_width=6

// DO NOT CONFUSE MEMORY WITH FLIPFLOP
// This Verilog code is analogous to simple SRAM memory 

parameter WIDTH = 16;
parameter DEPTH = 16;
parameter ADDR_WIDTH = 4;

reg clk_i, rst_i;
reg [ADDR_WIDTH-1:0] addr_i;
reg [WIDTH-1:0] wdata_i;
wire [WIDTH-1:0] rdata_o; // Output shall be declared as reg as it has to store data
reg wr_rd_i;
reg valid_i;
wire ready_o;

integer i;



memory_handshake #(.DEPTH(DEPTH), .ADDR_WIDTH(ADDR_WIDTH), .WIDTH(WIDTH)) dut (clk_i, rst_i, addr_i, wdata_i, rdata_o, wr_rd_i, valid_i, ready_o);
//memory_handshake dut (clk_i, rst_i, addr_i, wdata_i, rdata_o, wr_rd_i, valid_i, ready_o);

  

always #5 clk_i = ~clk_i;

initial begin 
	clk_i = 0;
	rst_i = 1;
	#20;
	rst_i = 0;
	// now apply the stimulus
	// write to all locations 
	write_memory(0, DEPTH);
	read_memory(0, DEPTH);
	#100;
	$finish;			
	 
end

task write_memory(input [ADDR_WIDTH-1:0] start_loc, input [ADDR_WIDTH:0] num_loc);
begin
	for (i = start_loc; i < start_loc + num_loc; i=i+1) begin 
		@(posedge clk_i); // at the positive edge of the clock
		// memory is a synchronous design hence all operations should happen at the positive edge of the clock
		addr_i = i;
		wdata_i = $random;
		wr_rd_i = 1;
		valid_i = 1;
	end
		// wait for getting hand	
		wait (ready_o == 1); // wait for ready_o after all 256 locations are written
		// once handshake is completed drop the hand, meaning making the values 0
		// If we don't do this it will continue to hold the values, it will be assumed that throughout the eval you're keeping this value
		@(posedge clk_i);
		valid_i = 0;
		addr_i = 0;
		wdata_i = 0;
		wr_rd_i = 0;
		
end
endtask

task read_memory(input [ADDR_WIDTH-1:0] start_loc, input [ADDR_WIDTH:0] num_loc);
begin
	
	for (i = start_loc; i < start_loc + num_loc; i=i+1) begin 
		@(posedge clk_i); // at the positive edge of the clock
		// memory is a synchronous design hence all operations should happen at the positive edge of the clock
		addr_i = i;
		wr_rd_i = 0;
		valid_i = 1;
		// wait for getting hand	
		//wait (ready_o == 1); // wait for ready_o after all 256 locations are written
	end
		// once handshake is completed drop the hand, meaning making the values 0
		// If we don't do this it will continue to hold the values, it will be assumed that throughout the eval you're keeping this value
		@(posedge clk_i);
		valid_i = 0;
		addr_i = 0;
		wdata_i = 0;
		wr_rd_i = 0;
		

end
endtask

initial begin 
	$dumpfile("1.vcd");  
  	$dumpvars;
	
end 
endmodule

Submits/RTL_Design_and_Integration_Material/Verilog_codes/12_Heirarchical_Memory/1.vcd
$date
	Tue Apr 11 14:19:29 2023
$end
$version
	QuestaSim Version 10.6c
$end
$timescale
	1ns
$end

$scope module tb $end
$var parameter 32 ! WIDTH $end
$var parameter 32 " DEPTH $end
$var parameter 32 # ADDR_WIDTH $end
$var reg 1 $ clk_i $end
$var reg 1 % rst_i $end
$var reg 4 & addr_i [3:0] $end
$var reg 16 ' wdata_i [15:0] $end
$var wire 1 ( rdata_o [15] $end
$var wire 1 ) rdata_o [14] $end
$var wire 1 * rdata_o [13] $end
$var wire 1 + rdata_o [12] $end
$var wire 1 , rdata_o [11] $end
$var wire 1 - rdata_o [10] $end
$var wire 1 . rdata_o [9] $end
$var wire 1 / rdata_o [8] $end
$var wire 1 0 rdata_o [7] $end
$var wire 1 1 rdata_o [6] $end
$var wire 1 2 rdata_o [5] $end
$var wire 1 3 rdata_o [4] $end
$var wire 1 4 rdata_o [3] $end
$var wire 1 5 rdata_o [2] $end
$var wire 1 6 rdata_o [1] $end
$var wire 1 7 rdata_o [0] $end
$var reg 1 8 wr_rd_i $end
$var reg 1 9 valid_i $end
$var wire 1 : ready_o $end
$var integer 32 ; i $end

$scope task write_memory $end
$var reg 4 < start_loc [3:0] $end
$var reg 5 = num_loc [4:0] $end
$upscope $end

$scope task read_memory $end
$var reg 4 > start_loc [3:0] $end
$var reg 5 ? num_loc [4:0] $end
$upscope $end

$scope module dut $end
$var parameter 32 @ WIDTH $end
$var parameter 32 A DEPTH $end
$var parameter 32 B ADDR_WIDTH $end
$var wire 1 C clk_i $end
$var wire 1 D rst_i $end
$var wire 1 E addr_i [3] $end
$var wire 1 F addr_i [2] $end
$var wire 1 G addr_i [1] $end
$var wire 1 H addr_i [0] $end
$var wire 1 I wdata_i [15] $end
$var wire 1 J wdata_i [14] $end
$var wire 1 K wdata_i [13] $end
$var wire 1 L wdata_i [12] $end
$var wire 1 M wdata_i [11] $end
$var wire 1 N wdata_i [10] $end
$var wire 1 O wdata_i [9] $end
$var wire 1 P wdata_i [8] $end
$var wire 1 Q wdata_i [7] $end
$var wire 1 R wdata_i [6] $end
$var wire 1 S wdata_i [5] $end
$var wire 1 T wdata_i [4] $end
$var wire 1 U wdata_i [3] $end
$var wire 1 V wdata_i [2] $end
$var wire 1 W wdata_i [1] $end
$var wire 1 X wdata_i [0] $end
$var reg 16 Y rdata_o [15:0] $end
$var wire 1 Z wr_rd_i $end
$var wire 1 [ valid_i $end
$var reg 1 \ ready_o $end
$var integer 32 ] i $end
$upscope $end
$upscope $end
$enddefinitions $end
#0
$dumpvars
0$
1%
bx &
bx '
x8
x9
bx Y
x\
bx <
bx =
bx >
bx ?
b10000 !
b10000 "
b100 #
b10000 @
b10000 A
b100 B
bx ;
bx ]
x7
x6
x5
x4
x3
x2
x1
x0
x/
x.
x-
x,
x+
x*
x)
x(
x:
x[
xZ
xX
xW
xV
xU
xT
xS
xR
xQ
xP
xO
xN
xM
xL
xK
xJ
xI
xH
xG
xF
xE
1D
0C
$end
#5
1$
1C
b0 Y
0\
b0 ]
b1 ]
b10 ]
b11 ]
b100 ]
b101 ]
b110 ]
b111 ]
b1000 ]
b1001 ]
b1010 ]
b1011 ]
b1100 ]
b1101 ]
b1110 ]
b1111 ]
b10000 ]
07
06
05
04
03
02
01
00
0/
0.
0-
0,
0+
0*
0)
0(
0:
#10
0$
0C
#15
1$
1C
b0 ]
b1 ]
b10 ]
b11 ]
b100 ]
b101 ]
b110 ]
b111 ]
b1000 ]
b1001 ]
b1010 ]
b1011 ]
b1100 ]
b1101 ]
b1110 ]
b1111 ]
b10000 ]
#20
0%
b0 <
b10000 =
b0 ;
0$
0D
0C
#25
1$
1C
b0 &
b11010100100100 '
18
19
b1 ;
0X
0W
1V
0U
0T
1S
0R
0Q
1P
0O
1N
0M
1L
1K
0J
0I
0H
0G
0F
0E
1Z
1[
#30
0$
0C
#35
1$
1C
1\
b1 &
b101111010000001 '
b10 ;
1:
1X
0V
0S
1Q
0P
1O
1M
0K
1J
1H
#40
0$
0C
#45
1$
1C
b10 &
b1101011000001001 '
b11 ;
1U
0Q
0M
1I
0H
1G
#50
0$
0C
#55
1$
1C
b11 &
b101011001100011 '
b100 ;
1W
0U
1S
1R
0I
1H
#60
0$
0C
#65
1$
1C
b100 &
b111101100001101 '
b101 ;
0W
1V
1U
0S
0R
1P
0N
1M
1K
0H
0G
1F
#70
0$
0C
#75
1$
1C
b101 &
b1001100110001101 '
b110 ;
1Q
0O
0K
0J
1I
1H
#80
0$
0C
#85
1$
1C
b110 &
b1000010001100101 '
b111 ;
0U
1S
1R
0Q
0P
1N
0M
0L
0H
1G
#90
0$
0C
#95
1$
1C
b111 &
b101001000010010 '
b1000 ;
0X
1W
0V
1T
0S
0R
1O
0N
1L
1J
0I
1H
#100
0$
0C
#105
1$
1C
b1000 &
b1110001100000001 '
b1001 ;
1X
0W
0T
1P
0L
1K
1I
0H
0G
0F
1E
#110
0$
0C
#115
1$
1C
b1001 &
b1100110100001101 '
b1010 ;
1V
1U
0O
1N
1M
0K
1H
#120
0$
0C
#125
1$
1C
b1010 &
b1111000101110110 '
b1011 ;
0X
1W
0U
1T
1S
1R
0N
0M
1L
1K
0H
1G
#130
0$
0C
#135
1$
1C
b1011 &
b1100110100111101 '
b1100 ;
1X
0W
1U
0R
1N
1M
0L
0K
1H
#140
0$
0C
#145
1$
1C
b1100 &
b101011111101101 '
b1101 ;
0T
1R
1Q
1O
0M
1L
0I
0H
0G
1F
#150
0$
0C
#155
1$
1C
b1101 &
b1111011110001100 '
b1110 ;
0X
0S
0R
1K
1I
1H
#160
0$
0C
#165
1$
1C
b1110 &
b1110100111111001 '
b1111 ;
1X
0V
1T
1S
1R
0O
0N
1M
0L
0H
1G
#170
0$
0C
#175
1$
1C
b1111 &
b10010011000110 '
b10000 ;
0X
1W
1V
0U
0T
0S
0P
1N
0M
0J
0I
1H
#180
0$
0C
#185
1$
1C
09
b0 &
b0 '
08
b0 >
b10000 ?
b0 ;
0[
0W
0V
0R
0Q
0N
0K
0H
0G
0F
0E
0Z
#190
0$
0C
#195
1$
1C
0\
19
b1 ;
0:
1[
#200
0$
0C
#205
1$
1C
1\
b11010100100100 Y
b1 &
b10 ;
1:
1H
15
12
1/
1-
1+
1*
#210
0$
0C
#215
1$
1C
b101111010000001 Y
b10 &
b11 ;
0H
1G
17
05
02
10
0/
1.
1,
0*
1)
#220
0$
0C
#225
1$
1C
b1101011000001001 Y
b11 &
b100 ;
1H
14
00
0,
1(
#230
0$
0C
#235
1$
1C
b101011001100011 Y
b100 &
b101 ;
0H
0G
1F
16
04
12
11
0(
#240
0$
0C
#245
1$
1C
b111101100001101 Y
b101 &
b110 ;
1H
06
15
14
02
01
1/
0-
1,
1*
#250
0$
0C
#255
1$
1C
b1001100110001101 Y
b110 &
b111 ;
0H
1G
10
0.
0*
0)
1(
#260
0$
0C
#265
1$
1C
b1000010001100101 Y
b111 &
b1000 ;
1H
04
12
11
00
0/
1-
0,
0+
#270
0$
0C
#275
1$
1C
b101001000010010 Y
b1000 &
b1001 ;
0H
0G
0F
1E
07
16
05
13
02
01
1.
0-
1+
1)
0(
#280
0$
0C
#285
1$
1C
b1110001100000001 Y
b1001 &
b1010 ;
1H
17
06
03
1/
0+
1*
1(
#290
0$
0C
#295
1$
1C
b1100110100001101 Y
b1010 &
b1011 ;
0H
1G
15
14
0.
1-
1,
0*
#300
0$
0C
#305
1$
1C
b1111000101110110 Y
b1011 &
b1100 ;
1H
07
16
04
13
12
11
0-
0,
1+
1*
#310
0$
0C
#315
1$
1C
b1100110100111101 Y
b1100 &
b1101 ;
0H
0G
1F
17
06
14
01
1-
1,
0+
0*
#320
0$
0C
#325
1$
1C
b101011111101101 Y
b1101 &
b1110 ;
1H
03
11
10
1.
0,
1+
0(
#330
0$
0C
#335
1$
1C
b1111011110001100 Y
b1110 &
b1111 ;
0H
1G
07
02
01
1*
1(
#340
0$
0C
#345
1$
1C
b1110100111111001 Y
b1111 &
b10000 ;
1H
17
05
13
12
11
0.
0-
1,
0+
#350
0$
0C
#355
1$
1C
b10010011000110 Y
09
b0 &
0[
0H
0G
0F
0E
07
16
15
04
03
02
0/
1-
0,
0)
0(
#360
0$
0C
#365
1$
1C
0\
0:
