Submits/RTL_Design_and_Integration_Material/Ibrahim_Verilog_Codes/14_Sequential_Divider_Constructionist/sequential_divider.v
/*

Watch the Video - https://www.youtube.com/watch?v=VKemv9u40gc
				  https://www.youtube.com/watch?v=MVpOKwTKVSc&t=297s
- Design is similar to Multiplier 

*/

module sequential_divider (num, den, nd_valid, nd_ready, clk, rst, qr_valid, quo, rem);
	parameter NUM_LENGTH = 1;
	parameter DEN_LENGTH = 1;
	input [NUM_LENGTH-1:0] num;
	input [DEN_LENGTH-1:0] den;
	input nd_valid;
	input clk;
	input rst;
	
	output reg nd_ready;	
	output reg qr_valid;
	output reg [NUM_LENGTH-1:0] quo;
	output reg [DEN_LENGTH-1:0] rem;
	
	parameter idle = 2'b00;
	parameter div = 2'b01;
	parameter undefined_div_by_0 = 2'b10;
	
	reg [1:0] state_reg, state_next;
	reg [NUM_LENGTH-1:0] quo_reg, quo_next;
	reg [NUM_LENGTH+DEN_LENGTH:0] rem_reg, rem_next;
	reg [NUM_LENGTH+DEN_LENGTH-1:0] divisor_reg, divisor_next;
	reg nd_ready_reg, nd_ready_next;
	reg qr_valid_reg, qr_valid_next;
	reg [DEN_LENGTH-1:0] counter_reg, counter_next;
	//reg nd_valid_reg; // This will make the design grab inputs on next clock edge
	
	always @(posedge clk or negedge rst) begin 
		if (~rst) begin 
			quo_reg <= 0;
			rem_reg <= 0;
			divisor_reg <= 0;
			nd_ready_reg <= 1;
			qr_valid_reg <= 0;
			counter_reg <= 0;
			state_reg <= idle;
			//nd_valid_reg <= 0;
		end
		else begin 
			quo_reg <= quo_next;
			rem_reg <= rem_next;
			divisor_reg <= divisor_next;
			nd_ready_reg <= nd_ready_next;
			qr_valid_reg <= qr_valid_next;
			counter_reg <= counter_next;	
			state_reg <= state_next;
			//nd_valid_reg <= nd_valid;			
		end
	end 
	
	always @(*) begin 
		////////// These lines are needed in Div but not in Mult because in Mult design all the variables on LHS is *_reg
		quo_next = quo_reg;
		rem_next = rem_reg;
		divisor_next = divisor_reg;
		nd_ready_next = nd_ready_reg;
		qr_valid_next = qr_valid_reg;
		counter_next = counter_reg;
		state_next = state_reg;      
	
		quo = quo_reg;
		rem = rem_reg[DEN_LENGTH-1:0];
		nd_ready = nd_ready_reg;
		qr_valid = qr_valid_reg;
		
		case (state_next) 
			idle:
			begin 
              	nd_ready_next = 1;
				state_next = idle;	
				qr_valid_next = 0;
				counter_next = 0;	
				if (nd_valid) begin 
					if (den == 0) begin 
						nd_ready_next = 0;
						state_next = undefined_div_by_0;
						quo_next = 0;
						divisor_next = 0;
						rem_next = 0;
					end
					else begin 
						nd_ready_next = 0;
						state_next = div;					
						quo_next = 0;
						
						divisor_next = 0;
						divisor_next = divisor_next + den;
						divisor_next = divisor_next << NUM_LENGTH; 

						rem_next = 0;
						rem_next = rem_next + num;
					end 
				end
			end
			div:
			begin 
				//$display("pre_rem_sub quo_next %b divisor_next %b rem_next %b",quo_next, divisor_next,rem_next);
				rem_next = rem_next - divisor_next;
				//$display("post_rem_sub quo_next %b divisor_next %b rem_next %b",quo_next, divisor_next,rem_next);
				if (rem_next[NUM_LENGTH+DEN_LENGTH] == 0) begin 
					quo_next = quo_reg << 1;
					quo_next = quo_next + 1;
				end 
				else begin 
					rem_next = rem_next + divisor_next;
					quo_next = quo_reg << 1;
				end
				//$display("post_rem_add quo_next %b divisor_next %b rem_next %b",quo_next, divisor_next,rem_next);
				divisor_next = divisor_next >> 1;
				counter_next = counter_next + 1;
				//$display("post_div_shf quo_next %b divisor_next %b rem_next %b",quo_next, divisor_next,rem_next);
				//$display("post_cnt_add counter_next %d",counter_next);
				if (counter_next == (NUM_LENGTH+1)) begin 
					nd_ready_next = 1;
					qr_valid_next = 1;
					state_next = idle;
				end 
			end 
			
			undefined_div_by_0: // division by 0
			begin 
				quo_next = 0;
				rem_next = 0;
				divisor_next = 0;
				nd_ready_next = 1;
				qr_valid_next = 1;
				state_next = idle;				
			end
		endcase
	end
	
endmodule

Submits/RTL_Design_and_Integration_Material/Ibrahim_Verilog_Codes/14_Sequential_Divider_Constructionist/tb.v
`include "sequential_divider.v"

module tb;
	// Declare IO's
	parameter NUM_LENGTH = 5;
	parameter DEN_LENGTH = 3;	
	integer seed = 123135;
	
	reg [NUM_LENGTH-1:0] num;
	reg [DEN_LENGTH-1:0] den;
	reg nd_valid;
	reg clk;
	reg rst;
	
	wire nd_ready;	
	wire qr_valid;
	wire [NUM_LENGTH-1:0] quo;
	wire [DEN_LENGTH-1:0] rem;
  	reg [7:0] clk_cnt;
    
  sequential_divider #(.NUM_LENGTH(NUM_LENGTH), .DEN_LENGTH(DEN_LENGTH)) DUT (.num(num),
                .den(den),
                .nd_valid(nd_valid),
                .nd_ready(nd_ready),
                .clk(clk),
                .rst(rst),
                .qr_valid(qr_valid),
                .quo(quo),
                .rem(rem));

	// Declare clk
	initial begin 
		clk = 0;
		forever #1 clk = ~clk;
	end 
  
	// Drive Inputs
	initial begin 
		rst = 0; 
		#5;
		rst = 1;
		#5;
		/*
        nd_valid = 1;
		num = 26;
		den = 5;
        */
      
      repeat (100) begin 
			@(posedge clk) begin
              	nd_valid = $random(seed);
				num = $random(seed);
				den = $random(seed);
			end
		end
		@(posedge clk) begin 
				nd_valid = 0;
			end		
      
		#50;
		$finish();
      
	end 
	
	initial begin 
      $monitor("time=%0d num=%d den=%d nd_valid=%d rst=%d quo=%d rem=%d qr_valid=%d nd_ready=%d", $time, num, den, nd_valid, rst, quo, rem, qr_valid, nd_ready);
	end	
	
	// Dump Variables
	initial begin 
		$dumpfile("waves.vcd");
		$dumpvars;
		
	end
	
endmodule

Submits/RTL_Design_and_Integration_Material/Ibrahim_Verilog_Codes/14_Sequential_Divider_Constructionist/waves.vcd
$date
	Sun May 07 23:21:55 2023
$end
$version
	QuestaSim Version 10.6c
$end
$timescale
	1ns
$end

$scope module tb $end
$var parameter 32 ! NUM_LENGTH $end
$var parameter 32 " DEN_LENGTH $end
$var integer 32 # seed $end
$var reg 5 $ num [4:0] $end
$var reg 3 % den [2:0] $end
$var reg 1 & nd_valid $end
$var reg 1 ' clk $end
$var reg 1 ( rst $end
$var wire 1 ) nd_ready $end
$var wire 1 * qr_valid $end
$var wire 1 + quo [4] $end
$var wire 1 , quo [3] $end
$var wire 1 - quo [2] $end
$var wire 1 . quo [1] $end
$var wire 1 / quo [0] $end
$var wire 1 0 rem [2] $end
$var wire 1 1 rem [1] $end
$var wire 1 2 rem [0] $end
$var reg 8 3 clk_cnt [7:0] $end

$scope module DUT $end
$var parameter 32 4 NUM_LENGTH $end
$var parameter 32 5 DEN_LENGTH $end
$var parameter 2 6 idle $end
$var parameter 2 7 div $end
$var parameter 2 8 undefined_div_by_0 $end
$var wire 1 9 num [4] $end
$var wire 1 : num [3] $end
$var wire 1 ; num [2] $end
$var wire 1 < num [1] $end
$var wire 1 = num [0] $end
$var wire 1 > den [2] $end
$var wire 1 ? den [1] $end
$var wire 1 @ den [0] $end
$var wire 1 A nd_valid $end
$var wire 1 B clk $end
$var wire 1 C rst $end
$var reg 1 D nd_ready $end
$var reg 1 E qr_valid $end
$var reg 5 F quo [4:0] $end
$var reg 3 G rem [2:0] $end
$var reg 2 H state_reg [1:0] $end
$var reg 2 I state_next [1:0] $end
$var reg 5 J quo_reg [4:0] $end
$var reg 5 K quo_next [4:0] $end
$var reg 9 L rem_reg [8:0] $end
$var reg 9 M rem_next [8:0] $end
$var reg 8 N divisor_reg [7:0] $end
$var reg 8 O divisor_next [7:0] $end
$var reg 1 P nd_ready_reg $end
$var reg 1 Q nd_ready_next $end
$var reg 1 R qr_valid_reg $end
$var reg 1 S qr_valid_next $end
$var reg 3 T counter_reg [2:0] $end
$var reg 3 U counter_next [2:0] $end
$upscope $end
$upscope $end
$enddefinitions $end
#0
$dumpvars
bx $
bx %
x&
0'
0(
bx 3
1D
0E
b0 F
b0 G
b0 H
b0 I
b0 J
b0 K
b0 L
b0 M
b0 N
b0 O
1P
1Q
0R
0S
b0 T
b0 U
b101 !
b11 "
b101 4
b11 5
b0 6
b1 7
b10 8
b11110000011111111 #
1)
0*
0/
0.
0-
0,
0+
02
01
00
0C
0B
xA
x@
x?
x>
x=
x<
x;
x:
x9
$end
#1
1'
1B
#2
0'
0B
#3
1'
1B
#4
0'
0B
#5
1(
1'
1C
1B
#6
0'
0B
#7
1'
1B
#8
0'
0B
#9
1'
1B
#10
0'
0B
#11
1'
1B
b11111010111011010001111100110100 #
1&
b11001101010111010000010100101 #
b10011 $
b11100110001111010000010100100010 #
b100 %
1A
0@
0?
1>
1=
1<
0;
0:
19
0Q
b1 I
b100 O
b10000000 O
b10011 M
#12
0'
0B
#13
1'
1B
b1111101010000011101011000111011 #
0&
b1111011110101001000110001000000 #
b10111 $
b10000000100100111000111101000001 #
b1 %
0A
1@
0>
1;
b0 M
b0 O
1Q
b0 I
b10011 L
b10000000 N
0P
b1 H
b10011 M
b10000000 O
0Q
b1 I
b11 G
0D
b110010011 M
b10011 M
b1000000 O
b1 U
12
11
0)
#14
0'
0B
#15
1'
1B
b11101100010000010000001110 #
1&
b11110110000000101111010100110111 #
b1100 $
b11100000010010010100000001100 #
b0 %
1A
0@
0=
0<
1:
09
b10000000 O
b0 U
b110010011 M
b10011 M
b1000000 O
b1 U
b1000000 N
b1 T
b111010011 M
b10011 M
b100000 O
b10 U
#16
0'
0B
#17
1'
1B
b10010011010011010110110011101 #
0&
b11001010000011011111111110111010 #
b10100 $
b10000010111011000011100111110011 #
b101 %
0A
1@
1>
0:
19
b1000000 O
b1 U
b111010011 M
b10011 M
b100000 O
b10 U
b100000 N
b10 T
b111110011 M
b10011 M
b10000 O
b11 U
#18
0'
0B
#19
1'
1B
b10000000011101011111010011000 #
b1011010000101000101011110111001 #
b10000010011101111010010000100110 #
b100 %
0@
b100000 O
b10 U
b111110011 M
b10011 M
b10000 O
b11 U
b10000 N
b11 T
b11 M
b1 K
b1000 O
b100 U
#20
0'
0B
#21
1'
1B
b110001010010100110000001101111 #
b10011111111000111101101111100100 #
b11111 $
b1110111100001011010100110010101 #
b111 %
1@
1?
1=
1<
1:
b0 K
b10011 M
b10000 O
b11 U
b11 M
b1 K
b1000 O
b100 U
b1 J
b11 L
b1000 N
b100 T
b1 F
b111111011 M
b11 M
b10 K
b100 O
b101 U
1/
#22
0'
0B
#23
1'
1B
b101001001110100101110101010010 #
b1010111110010111110010010101011 #
b1111 $
b10001101100011011100101111110000 #
b11 %
0>
09
b1 K
b1000 O
b100 U
b111111011 M
b11 M
b10 K
b100 O
b101 U
b10 J
b100 N
b101 T
b10 F
b111111111 M
b11 M
b100 K
b10 O
b110 U
1Q
1S
b0 I
0/
1.
#24
0'
0B
#25
1'
1B
b1011001110101110111111100110001 #
1&
b1100010001101110101011100111110 #
b100 $
b11001100111111010000001010100111 #
b1 %
1A
0?
0=
0<
0:
b10 K
b100 O
0Q
0S
b101 U
b1 I
b111111111 M
b11 M
b100 K
b10 O
b110 U
1Q
1S
b0 I
b100 J
b10 N
1P
1R
b110 T
b0 H
b100 F
1D
1E
0S
b0 U
0Q
b1 I
b0 K
b0 O
b1 O
b100000 O
b0 M
b100 M
0.
1-
1)
1*
#26
0'
0B
#27
1'
1B
b10011001001001101010111100 #
0&
b10100001001001110111010010001101 #
b10 $
b10000010000100000111110111101010 #
b100 %
0A
0@
1>
1<
0;
b100 K
b11 M
b10 O
1Q
1S
b110 U
b0 I
0S
b0 U
b0 J
b100 L
b100000 N
0P
0R
b0 T
b1 H
b0 K
b100 M
b100000 O
0Q
b1 I
b0 F
b100 G
0D
0E
b111100100 M
b100 M
b10000 O
b1 U
02
01
10
0-
0)
0*
#28
0'
0B
#29
1'
1B
b1111011100000111011011001100011 #
1&
b1001111000111110001010001001000 #
b11110 $
b100001100101110010110101001 #
b0 %
1A
0>
1;
1:
19
b100000 O
b0 U
b111100100 M
b100 M
b10000 O
b1 U
b10000 N
b1 T
b111110100 M
b100 M
b1000 O
b10 U
#30
0'
0B
#31
1'
1B
b11011000000101000111110101010110 #
0&
b10010000000110111011101111011111 #
b0 $
b10001010100111101100010010010100 #
b101 %
0A
1@
1>
0<
0;
0:
09
b10000 O
b1 U
b111110100 M
b100 M
b1000 O
b10 U
b1000 N
b10 T
b111111100 M
b100 M
b100 O
b11 U
#32
0'
0B
#33
1'
1B
b11010101101100101110111010000101 #
1&
b100100111010101100000110000010 #
b1001 $
b111101010100101000111100011011 #
b10 %
1A
0@
1?
0>
1=
1:
b1000 O
b10 U
b111111100 M
b100 M
b100 O
b11 U
b100 N
b11 T
b0 M
b1 K
b10 O
b100 U
#34
0'
0B
#35
1'
1B
b11011011011110111111011110100000 #
0&
b101011110000110101100100001 #
b1010 $
b11101001111111110111011001101110 #
b11 %
0A
1@
0=
1<
b0 K
b100 M
b100 O
b11 U
b0 M
b1 K
b10 O
b100 U
b1 J
b0 L
b10 N
b100 T
b1 F
b0 G
b111111110 M
b0 M
b10 K
b1 O
b101 U
00
1/
#36
0'
0B
#37
1'
1B
b11010001000000110110110000010111 #
b11111000010100011011100101101100 #
b10000 $
b10111001010001111111011101111101 #
b10 %
0@
0<
0:
19
b1 K
b10 O
b100 U
b111111110 M
b0 M
b10 K
b1 O
b101 U
b10 J
b1 N
b101 T
b10 F
b111111111 M
b0 M
b100 K
b0 O
b110 U
1Q
1S
b0 I
0/
1.
#38
0'
0B
#39
1'
1B
b11111101101011111000100000011010 #
1&
b10010111100100110100111011010011 #
b1111 $
b101010110010011101010111111000 #
b101 %
1A
1@
0?
1>
1=
1<
1;
1:
09
b10 K
b1 O
0Q
0S
b101 U
b1 I
b111111111 M
b0 M
b100 K
b0 O
b110 U
1Q
1S
b0 I
b100 J
b0 N
1P
1R
b110 T
b0 H
b100 F
1D
1E
0S
b0 U
0Q
b1 I
b0 K
b101 O
b10100000 O
b1111 M
0.
1-
1)
1*
#40
0'
0B
#41
1'
1B
b1011001011101011110111110011001 #
0&
b10010000001101001010001010000110 #
b0 $
b11001000111011001111001101001111 #
b1 %
0A
0>
0=
0<
0;
0:
b100 K
b0 M
b0 O
1Q
1S
b110 U
b0 I
0S
b0 U
b0 J
b1111 L
b10100000 N
0P
0R
b0 T
b1 H
b0 K
b1111 M
b10100000 O
0Q
b1 I
b0 F
b111 G
0D
0E
b101101111 M
b1111 M
b1010000 O
b1 U
12
11
10
0-
0)
0*
#42
0'
0B
#43
1'
1B
b11100001011010001101100101000100 #
b10101101010000100110111101110101 #
b11010 $
b10001101010100010011000110110010 #
b10 %
0@
1?
1<
1:
19
b10100000 O
b0 U
b101101111 M
b1111 M
b1010000 O
b1 U
b1010000 N
b1 T
b110111111 M
b1111 M
b101000 O
b10 U
#44
0'
0B
#45
1'
1B
b1111011001111001101010110001011 #
b10011100000110100000111101010000 #
b11000 $
b1100010111101010101001100010001 #
b101 %
1@
0?
1>
0<
b1010000 O
b1 U
b110111111 M
b1111 M
b101000 O
b10 U
b101000 N
b10 T
b111100111 M
b1111 M
b10100 O
b11 U
#46
0'
0B
#47
1'
1B
b110101111000110000110011110 #
1&
b1010111011011010011000110000111 #
b1110 $
b10111111011110111000010000011100 #
b110 %
1A
0@
1?
1<
1;
09
b101000 O
b10 U
b111100111 M
b1111 M
b10100 O
b11 U
b10100 N
b11 T
b111111011 M
b1111 M
b1010 O
b100 U
#48
0'
0B
#49
1'
1B
b11111101110100011011001101101 #
b10011010011100001111001001010 #
b110 $
b10001011011000100000001101000011 #
0:
b10100 O
b11 U
b111111011 M
b1111 M
b1010 O
b100 U
b1010 N
b100 T
b101 M
b1 K
b101 O
b101 U
#50
0'
0B
#51
1'
1B
b10011010111010100000001110101000 #
b11110011001111000111010110001001 #
b1001110111010110001001110110110 #
b101 %
1@
0?
b0 K
b1111 M
b1010 O
b100 U
b101 M
b1 K
b101 O
b101 U
b1 J
b101 L
b101 N
b101 T
b1 F
b101 G
b0 M
b10 K
b11 K
b10 O
b110 U
1Q
1S
b0 I
01
1/
#52
0'
0B
#53
1'
1B
b110101111101010000011010111111 #
b10101101010011010001100111110100 #
b11010 $
b11001011000000110010110001100101 #
b110 %
0@
1?
0;
1:
19
b1 K
b101 M
b101 O
0Q
0S
b101 U
b1 I
b0 M
b10 K
b11 K
b10 O
b110 U
1Q
1S
b0 I
b11 J
b0 L
b10 N
1P
1R
b110 T
b0 H
b11 F
b0 G
1D
1E
0S
b0 U
0Q
b1 I
b0 K
b0 O
b110 O
b11000000 O
b11010 M
02
00
1.
1)
1*
#54
0'
0B
#55
1'
1B
b11100111001100001010110111100010 #
0&
b1001000101100011011011111111011 #
b10001 $
b11110100101000110001001100000000 #
b1 %
0A
1@
0?
0>
1=
0<
0:
b11 K
b0 M
b10 O
1Q
1S
b110 U
b0 I
0S
b0 U
b0 J
b11010 L
b11000000 N
0P
0R
b0 T
b1 H
b0 K
b11010 M
b11000000 O
0Q
b1 I
b0 F
b10 G
0D
0E
b101011010 M
b11010 M
b1100000 O
b1 U
11
0/
0.
0)
0*
#56
0'
0B
#57
1'
1B
b1000001100011010011011100000001 #
1&
b11100000111000010001100011001110 #
b1 $
b10011011010100010101001011110111 #
b110 %
1A
0@
1?
1>
09
b11000000 O
b0 U
b101011010 M
b11010 M
b1100000 O
b1 U
b1100000 N
b1 T
b110111010 M
b11010 M
b110000 O
b10 U
#58
0'
0B
#59
1'
1B
b11010100010011001111101011001100 #
0&
b11100101001011010011000101011101 #
b1010 $
b10000011110100000001111010 #
b100 %
0A
0?
0=
1<
1:
b1100000 O
b1 U
b110111010 M
b11010 M
b110000 O
b10 U
b110000 N
b10 T
b111101010 M
b11010 M
b11000 O
b11 U
#60
0'
0B
#61
1'
1B
b10101100111101101101001110110011 #
1&
b11011110000110101001110101011000 #
b11100 $
b11010010101001010111011101111001 #
b101 %
1A
1@
0<
1;
19
b110000 O
b10 U
b111101010 M
b11010 M
b11000 O
b11 U
b11000 N
b11 T
b10 M
b1 K
b1100 O
b100 U
#62
0'
0B
#63
1'
1B
b10001101000010101101000011100110 #
0&
b1001111001010101111011000101111 #
b11110 $
b10001010000101101000011010100100 #
b100 %
0A
0@
1<
b0 K
b11010 M
b11000 O
b11 U
b10 M
b1 K
b1100 O
b100 U
b1 J
b10 L
b1100 N
b100 T
b1 F
b111110110 M
b10 M
b10 K
b110 O
b101 U
1/
#64
0'
0B
#65
1'
1B
b111111100001000010010101010101 #
1&
b10111000000011000011011000010010 #
b10000 $
b110110100110000011011001101011 #
b101 %
1A
1@
0<
0;
0:
b1 K
b1100 O
b100 U
b111110110 M
b10 M
b10 K
b110 O
b101 U
b10 J
b110 N
b101 T
b10 F
b111111100 M
b10 M
b100 K
b11 O
b110 U
1Q
1S
b0 I
0/
1.
#66
0'
0B
#67
1'
1B
b10101001000100100000001010110000 #
0&
b1010000001111110001011011110001 #
b0 $
b10001101101000001001101111111110 #
b11 %
0A
1?
0>
09
b10 K
b110 O
0Q
0S
b101 U
b1 I
b111111100 M
b10 M
b100 K
b11 O
b110 U
1Q
1S
b0 I
b100 J
b11 N
1P
1R
b110 T
b0 H
b100 F
1D
1E
0S
b0 U
0.
1-
1)
1*
#68
0'
0B
#69
1'
1B
b101101100001101101000001100111 #
1&
b11101111100010001110101111100 #
b11011 $
b1010110000011111110100001001101 #
b100 %
1A
0@
0?
1>
1=
1<
1:
19
1S
b110 U
0S
b0 U
0Q
b1 I
b0 K
b0 O
b100 O
b10000000 O
b0 M
b11011 M
0R
b0 T
b100 K
b10 M
b11 O
1Q
b0 I
0E
0Q
b1 I
b0 K
b0 O
b100 O
b10000000 O
b0 M
b11011 M
0*
#70
0'
0B
#71
1'
1B
b10100001110101011110111010101010 #
b1100100000110001100000000100011 #
b1000 $
b101001101101101010001100001000 #
b11 %
1@
1?
0>
0=
0<
09
b100 K
b10 M
b11 O
1Q
b0 I
0Q
b1 I
b0 K
b0 O
b11 O
b1100000 O
b0 M
b1000 M
b0 J
b11011 L
b10000000 N
0P
b1 H
b11011 M
b10000000 O
b0 F
b11 G
0D
b110011011 M
b11011 M
b1000000 O
b1 U
12
0-
0)
#72
0'
0B
#73
1'
1B
b1010000100011111111010101101001 #
b11001000001001101101101000010110 #
b10000 $
b11010010001011100000110011111 #
b100 %
0@
0?
1>
0:
19
b10000000 O
b0 U
b110011011 M
b11011 M
b1000000 O
b1 U
b1000000 N
b1 T
b111011011 M
b11011 M
b100000 O
b10 U
#74
0'
0B
#75
1'
1B
b1010110010100000001111101010100 #
0&
b1001111000101000101101001000101 #
b11110 $
b10110110001001101100101001000010 #
0A
1<
1;
1:
b1000000 O
b1 U
b111011011 M
b11011 M
b100000 O
b10 U
b100000 N
b10 T
b111111011 M
b11011 M
b10000 O
b11 U
#76
0'
0B
#77
1'
1B
b10011111100101110101000011011011 #
1&
b11001100001000011101111001100000 #
b11000 $
b1101110010011111001011100001 #
b11 %
1A
1@
1?
0>
0<
0;
b100000 O
b10 U
b111111011 M
b11011 M
b10000 O
b11 U
b10000 N
b11 T
b1011 M
b1 K
b1000 O
b100 U
#78
0'
0B
#79
1'
1B
b111110111011011110101100101110 #
b1100100101001001010100111010111 #
b1001 $
b10011110010100101110110000101100 #
b100 %
0@
0?
1>
1=
09
b0 K
b11011 M
b10000 O
b11 U
b1011 M
b1 K
b1000 O
b100 U
b1 J
b1011 L
b1000 N
b100 T
b1 F
b11 M
b10 K
b11 K
b100 O
b101 U
1/
#80
0'
0B
#81
1'
1B
b11101010100100010101101100111101 #
b10010011010001010010100011011010 #
b110 $
b10011010010011101100100010010011 #
0=
1<
1;
0:
b1 K
b1011 M
b1000 O
b100 U
b11 M
b10 K
b11 K
b100 O
b101 U
b11 J
b11 L
b100 N
b101 T
b11 F
b111111111 M
b11 M
b110 K
b10 O
b110 U
1Q
1S
b0 I
1.
#82
0'
0B
#83
1'
1B
b1011001110110010001010010111000 #
b1101100110101110111101011001 #
b11011 $
b10110010100100100010111101000110 #
b101 %
1@
1=
0;
1:
19
b11 K
b100 O
0Q
0S
b101 U
b1 I
b111111111 M
b11 M
b110 K
b10 O
b110 U
1Q
1S
b0 I
b110 J
b10 N
1P
1R
b110 T
b0 H
b110 F
1D
1E
0S
b0 U
0Q
b1 I
b0 K
b0 O
b101 O
b10100000 O
b0 M
b11011 M
0/
1-
1)
1*
#84
0'
0B
#85
1'
1B
b10011010101111000110100100001111 #
b11100011010001001110010000000100 #
b110 $
b1100001110000101100101100110101 #
b11 %
1?
0>
0=
1;
0:
09
b110 K
b11 M
b10 O
1Q
1S
b110 U
b0 I
0S
b0 U
0Q
b1 I
b0 K
b0 O
b11 O
b1100000 O
b0 M
b110 M
b0 J
b11011 L
b10100000 N
0P
0R
b0 T
b1 H
b11011 M
b10100000 O
b0 F
0D
0E
b101111011 M
b11011 M
b1010000 O
b1 U
0.
0-
0)
0*
#86
0'
0B
#87
1'
1B
b11111000100000110110101001110010 #
b11000000101100000011101001011 #
b10000 $
b1101111010011011010011000010000 #
b110 %
0@
1>
0<
0;
19
b10100000 O
b0 U
b101111011 M
b11011 M
b1010000 O
b1 U
b1010000 N
b1 T
b111001011 M
b11011 M
b101000 O
b10 U
#88
0'
0B
#89
1'
1B
b10111000101011001100101011010001 #
b1110011011111000000011001011110 #
b110 $
b11001101000000011101111101000111 #
b10 %
0>
1<
1;
09
b1010000 O
b1 U
b111001011 M
b11011 M
b101000 O
b10 U
b101000 N
b10 T
b111110011 M
b11011 M
b10100 O
b11 U
#90
0'
0B
#91
1'
1B
b100010000111010110011011011100 #
0&
b110110101000001000101000101101 #
b1101 $
b1101111101111111110111100001010 #
b111 %
0A
1@
1>
1=
0<
1:
b101000 O
b10 U
b111110011 M
b11011 M
b10100 O
b11 U
b10100 N
b11 T
b111 M
b1 K
b1010 O
b100 U
#92
0'
0B
#93
1'
1B
b101010110111111110110100000011 #
1&
b10100001010111001111001001101000 #
b10 $
b11100010001001010110010101001001 #
b100 %
1A
0@
0?
0=
1<
0;
0:
b0 K
b11011 M
b10100 O
b11 U
b111 M
b1 K
b1010 O
b100 U
b1 J
b111 L
b1010 N
b100 T
b1 F
b111 G
b111111101 M
b111 M
b10 K
b101 O
b101 U
10
1/
#94
0'
0B
#95
1'
1B
b1100011010111111101000001110110 #
0&
b1000001110001011110110001111111 #
b11 $
b10100100111111111101010010110100 #
b1 %
0A
1@
0>
1=
b1 K
b1010 O
b100 U
b111111101 M
b111 M
b10 K
b101 O
b101 U
b10 J
b101 N
b101 T
b10 F
b10 M
b100 K
b101 K
b10 O
b110 U
1Q
1S
b0 I
0/
1.
#96
0'
0B
#97
1'
1B
b11110011010111100111100000100101 #
b100110111001010001011010100010 #
b1101 $
b11011110001110110101100110111011 #
b100 %
0@
1>
0<
1;
1:
b10 K
b111 M
b101 O
0Q
0S
b101 U
b1 I
b10 M
b100 K
b101 K
b10 O
b110 U
1Q
1S
b0 I
b101 J
b10 L
b10 N
1P
1R
b110 T
b0 H
b101 F
b10 G
1D
1E
0S
b0 U
02
00
1/
0.
1-
1)
1*
#98
0'
0B
#99
1'
1B
b1010010110100000101100111000000 #
1&
b111111001001101001111011000001 #
b11110 $
b100110101111011110110110001110 #
b101 %
1A
1@
0=
1<
19
1S
b110 U
0S
b0 U
0Q
b1 I
b0 K
b0 O
b101 O
b10100000 O
b0 M
b11110 M
0R
b0 T
b101 K
b10 M
b10 O
1Q
b0 I
0E
0Q
b1 I
b0 K
b0 O
b101 O
b10100000 O
b0 M
b11110 M
0*
#100
0'
0B
#101
1'
1B
b10011000101101010111000010110111 #
b11110000101110111000110110001100 #
b1 $
b11011001111011000111010100011101 #
b11 %
1?
0>
1=
0<
0;
0:
09
b101 K
b10 M
b10 O
1Q
b0 I
0Q
b1 I
b0 K
b0 O
b11 O
b1100000 O
b0 M
b1 M
b0 J
b11110 L
b10100000 N
0P
b1 H
b11110 M
b10100000 O
b0 F
b110 G
0D
b101111110 M
b11110 M
b1010000 O
b1 U
10
0/
0-
0)
#102
0'
0B
#103
1'
1B
b11111001011010010100000100111010 #
0&
b1010010110100110010110101110011 #
b101 $
b111001110111010011110000011000 #
0A
1;
b10100000 O
b0 U
b101111110 M
b11110 M
b1010000 O
b1 U
b1010000 N
b1 T
b111001110 M
b11110 M
b101000 O
b10 U
#104
0'
0B
#105
1'
1B
b11001110010011100101011100111001 #
b10000110011000101011110110100110 #
b1100 $
b1011110010110010100101111101111 #
b100 %
0@
0?
1>
0=
1:
b1010000 O
b1 U
b111001110 M
b11110 M
b101000 O
b10 U
b101000 N
b10 T
b111110110 M
b11110 M
b10100 O
b11 U
#106
0'
0B
#107
1'
1B
b1100010010010111111000101100100 #
b10000011011101100110000100010101 #
b110 $
b10101001110011101100111011010010 #
b11 %
1@
1?
0>
1<
0:
b101000 O
b10 U
b111110110 M
b11110 M
b10100 O
b11 U
b10100 N
b11 T
b1010 M
b1 K
b1010 O
b100 U
#108
0'
0B
#109
1'
1B
b1001001111011100100100000101011 #
1&
b10010101101001001111100101110000 #
b1011 $
b101111001101100110111010110001 #
b110 %
1A
0@
1>
1=
0;
1:
b0 K
b11110 M
b10100 O
b11 U
b1010 M
b1 K
b1010 O
b100 U
b1 J
b1010 L
b1010 N
b100 T
b1 F
b10 G
b0 M
b10 K
b11 K
b101 O
b101 U
00
1/
#110
0'
0B
#111
1'
1B
b111001101010000010111110 #
b1111100101100101111000100111 #
b11111 $
b1111100010110000110000000111100 #
b0 %
0?
0>
1;
19
b1 K
b1010 M
b1010 O
b100 U
b0 M
b10 K
b11 K
b101 O
b101 U
b11 J
b0 L
b101 N
b101 T
b11 F
b0 G
b111111011 M
b0 M
b110 K
b10 O
b110 U
1Q
1S
b0 I
01
1.
#112
0'
0B
#113
1'
1B
b1101111111001000001110000001101 #
b1001011001001000001111101101010 #
b10110 $
b100000111011111000100111100011 #
b1 %
1@
0=
0:
b11 K
b101 O
0Q
0S
b101 U
b1 I
b111111011 M
b0 M
b110 K
b10 O
b110 U
1Q
1S
b0 I
b110 J
b10 N
1P
1R
b110 T
b0 H
b110 F
1D
1E
0S
b0 U
0Q
b1 I
b0 K
b0 O
b1 O
b100000 O
b10110 M
0/
1-
1)
1*
#114
0'
0B
#115
1'
1B
b10011101101001111000111001000 #
b11101001111101001100010100101001 #
b10011 $
b10001100001011011111011011010110 #
b0 %
0@
1=
0;
b110 K
b0 M
b10 O
1Q
1S
b110 U
b0 I
0S
b0 U
0Q
b10 I
b0 K
b0 O
b0 J
b10110 L
b100000 N
0P
0R
b0 T
b1 H
b10110 M
b100000 O
b1 I
b0 F
b110 G
0D
0E
b111110110 M
b10110 M
b10000 O
b1 U
11
10
0.
0-
0)
0*
#116
0'
0B
#117
1'
1B
b10001101001011011000011101011111 #
0&
b11100100101101000011101000010100 #
b1001 $
b10000101010110011000011000000101 #
b10 %
0A
1?
0<
1:
09
b100000 O
b0 U
b111110110 M
b10110 M
b10000 O
b1 U
b10000 N
b1 T
b110 M
b1 K
b1000 O
b10 U
#118
0'
0B
#119
1'
1B
b11011010100000111001001100000010 #
1&
b111100110101011101001010011011 #
b11001 $
b1100101100001101000010100100000 #
b11 %
1A
1@
19
b0 K
b10110 M
b10000 O
b1 U
b110 M
b1 K
b1000 O
b10 U
b1 J
b110 L
b1000 N
b10 T
b1 F
b111111110 M
b110 M
b10 K
b100 O
b11 U
1/
#120
0'
0B
#121
1'
1B
b10100110100110110011101010100001 #
b10000110111010010001111111101110 #
b1101 $
b11111111001110111010011110010111 #
b110 %
0@
1>
1;
09
b1 K
b1000 O
b10 U
b111111110 M
b110 M
b10 K
b100 O
b11 U
b10 J
b100 N
b11 T
b10 F
b10 M
b100 K
b101 K
b10 O
b100 U
0/
1.
#122
0'
0B
