Submits/RTL_Design_and_Integration_Material/Verilog_codes/29_FSM_Patter_Detector/fsm_pattern_detector_moore.v
/*
Mistakes
1. Forgot reset logic 
2. Forgot default case statement
*/

/*
Comments
- Moore State Machine => Last State included in the design as Moore output depends only on state
*/

module fsm_pattern_detector(clk, reset, d_in, valid_in, pattern_flag);

input clk, reset, d_in, valid_in;
output reg pattern_flag;

parameter S_RESET = 3'b000;
parameter S_B = 3'b001;
parameter S_BB = 3'b010;
parameter S_BBC = 3'b011;
parameter S_BBCB = 3'b100;
parameter S_BBCBC = 3'b101;

parameter C = 1'b0; // Car
parameter B = 1'b1; // Bike

// 3FF requied for storing states
reg [2:0] state, next_state;

always @ (posedge clk) begin 
	if (reset == 1) begin 
		// all reg variables make to 0 or reset value
		pattern_flag = 0;
		state = S_RESET;
		next_state = S_RESET;
	end 
	else begin  
		pattern_flag = 1'b0;
		if (valid_in == 1) begin
			case (state) 
				S_RESET: begin 
					if (d_in == B) next_state = S_B;
					else next_state = S_RESET;
				end
				S_B: begin 
					if (d_in == B) next_state = S_BB;
					else next_state = S_RESET;
				end
				S_BB: begin 
					if (d_in == B) next_state = S_BB;
					else next_state = S_BBC;
				end
				S_BBC: begin 
					if (d_in == B) next_state = S_BBCB;
					else next_state = S_RESET;
				end
				S_BBCB: begin 
					if (d_in == B) next_state = S_BB;
					else next_state = S_BBCBC;
				end
				S_BBCBC: begin 
					pattern_flag = 1'b1;
					if (d_in == B) next_state = S_B;
					else next_state = S_RESET;
				end
				default: begin
					$display("Error Condition");
					next_state = S_RESET;
				end 
			endcase
		end 
	end
end 

always @(next_state) state = next_state;

endmodule

Submits/RTL_Design_and_Integration_Material/Verilog_codes/29_FSM_Patter_Detector/tb.v
`include "fsm_pattern_detector_moore.v"

module tb;
	// Add the nets
	reg clk, reset, d_in, valid_in;
	wire pattern_flag;
	integer seed;
	integer count;

	// generate clk
	always begin 
		#5 clk = 0;
		#5 clk = 1;
	end

	//instantiate
	fsm_pattern_detector dut (clk, reset, d_in, valid_in, pattern_flag);

	//dump vars
	initial begin 
		$dumpfile("waves.vcd");
		$dumpvars;
	end
	
	//generate inputs
	initial begin
		count = 0;
		seed = 37934298;
		reset = 1;
		#20;
		reset = 0;
		repeat (540) begin 
			@(posedge clk) begin
				valid_in = 1'b1;	
				d_in = $random(seed);
			end
		end 
		@(posedge clk) begin 
			valid_in = 1'b0;
			d_in = 1'b0;
			end
		#50;
		$display("total count = %0d", count);
		$finish;
	end 
	
	always @(posedge pattern_flag) count = count + 1;
	
endmodule

Submits/RTL_Design_and_Integration_Material/Verilog_codes/29_FSM_Patter_Detector/waves.vcd
$date
	Sun Apr 23 21:29:32 2023
$end
$version
	QuestaSim Version 10.6c
$end
$timescale
	1ns
$end

$scope module tb $end
$var reg 1 ! clk $end
$var reg 1 " reset $end
$var reg 1 # d_in $end
$var reg 1 $ valid_in $end
$var wire 1 % pattern_flag $end
$var integer 32 & seed $end
$var integer 32 ' count $end

$scope module dut $end
$var parameter 3 ( S_RESET $end
$var parameter 3 ) S_B $end
$var parameter 3 * S_BB $end
$var parameter 3 + S_BBC $end
$var parameter 3 , S_BBCB $end
$var parameter 3 - S_BBCBC $end
$var parameter 1 . C $end
$var parameter 1 / B $end
$var wire 1 0 clk $end
$var wire 1 1 reset $end
$var wire 1 2 d_in $end
$var wire 1 3 valid_in $end
$var reg 1 4 pattern_flag $end
$var reg 3 5 state [2:0] $end
$var reg 3 6 next_state [2:0] $end
$upscope $end
$upscope $end
$enddefinitions $end
#0
$dumpvars
x!
1"
x#
x$
x4
bx 5
bx 6
b0 (
b1 )
b10 *
b11 +
b100 ,
b101 -
b0 .
b1 /
b10010000101101010011011010 &
b0 '
x%
x3
x2
11
x0
$end
#5
0!
00
#10
1!
10
04
b0 5
b0 6
0%
#15
0!
00
#20
0"
1!
01
10
1$
b1001001011011000010010010011 &
0#
13
02
#25
0!
00
#30
1!
10
b101101110000011010000010111000 &
1#
12
#35
0!
00
#40
1!
10
b1 6
b11001111011110000101101011001 &
b1 5
#45
0!
00
#50
1!
10
b10 6
b11110011010110001001101101000110 &
0#
02
b10 5
#55
0!
00
#60
1!
10
b11 6
b11111001000111001110010100001111 &
b11 5
#65
0!
00
#70
1!
10
b0 6
b11011000110101000011000000000100 &
1#
12
b0 5
#75
0!
00
#80
1!
10
b1 6
b10011000010111101010011100110101 &
0#
02
b1 5
#85
0!
00
#90
1!
10
b0 6
b1111001011111101001011001110010 &
b0 5
#95
0!
00
#100
1!
10
b1001110011101000100001101001011 &
#105
0!
00
#110
1!
10
b11111101110011111011001000010000 &
1#
12
#115
0!
00
#120
1!
10
b1 6
b1111101011011000110011011010001 &
0#
02
b1 5
#125
0!
00
#130
1!
10
b0 6
b1010111110101111111001001011110 &
1#
12
b0 5
#135
0!
00
#140
1!
10
b1 6
b1000001100110011101101101000111 &
b1 5
#145
0!
00
#150
1!
10
b10 6
b110011100111100011001011011100 &
b10 5
#155
0!
00
#160
1!
10
b10010001000111111110011000101101 &
0#
02
#165
0!
00
#170
1!
10
b11 6
b10111011011010001001101100001010 &
b11 5
#175
0!
00
#180
1!
10
b0 6
b11111101101011011010100100000011 &
1#
12
b0 5
#185
0!
00
#190
1!
10
b1 6
b10011110101010000111111001101000 &
b1 5
#195
0!
00
#200
1!
10
b10 6
b11001110000001000000101001001 &
b10 5
#205
0!
00
#210
1!
10
b11100111000000010011110001110110 &
0#
02
#215
0!
00
#220
1!
10
b11 6
b1001000100001010110100001111111 &
1#
12
b11 5
#225
0!
00
#230
1!
10
b100 6
b1000001101000100010000010110100 &
b100 5
#235
0!
00
#240
1!
10
b10 6
b11101011001100010101010000100101 &
0#
02
b10 5
#245
0!
00
#250
1!
10
b11 6
b101011111010110100001010100010 &
1#
12
b11 5
#255
0!
00
#260
1!
10
b100 6
b1100000011010001001010110111011 &
0#
02
b100 5
#265
0!
00
#270
1!
10
b101 6
b11001000101010110010111000000 &
b101 5
#275
0!
00
#280
1!
10
14
b0 6
b10010010000011010011101011000001 &
1%
b1 '
b0 5
#285
0!
00
#290
1!
10
04
b11011011010101001101100110001110 &
0%
#295
0!
00
#300
1!
10
b11001011100011000110110010110111 &
1#
12
#305
0!
00
#310
1!
10
b1 6
b10001101101011110101100110001100 &
b1 5
#315
0!
00
#320
1!
10
b10 6
b10110110100000101101000100011101 &
b10 5
#325
0!
00
#330
1!
10
b10011100011111001110110100111010 &
0#
02
#335
0!
00
#340
1!
10
b11 6
b10010101010011111110100101110011 &
b11 5
#345
0!
00
#350
1!
10
b0 6
b10001001010010111100100000011000 &
b0 5
#355
0!
00
#360
1!
10
b10010010111100000111001100111001 &
1#
12
#365
0!
00
#370
1!
10
b1 6
b1010011100111110010100110100110 &
b1 5
#375
0!
00
#380
1!
10
b10 6
b110101001101111100011111101111 &
0#
02
b10 5
#385
0!
00
#390
1!
10
b11 6
b111010110000010011110101100100 &
1#
12
b11 5
#395
0!
00
#400
1!
10
b100 6
b11010010000000011110100010101 &
0#
02
b100 5
#405
0!
00
#410
1!
10
b101 6
b10000101100111111111101011010010 &
1#
12
b101 5
#415
0!
00
#420
1!
10
14
b1 6
b11011101010101000010000101011 &
1%
b10 '
b1 5
#425
0!
00
#430
1!
10
04
b10 6
b1010100011011010000010101110000 &
0#
02
0%
b10 5
#435
0!
00
#440
1!
10
b11 6
b101010000001000000101010110001 &
b11 5
#445
0!
00
#450
1!
10
b0 6
b11100100011110001000110010111110 &
b0 5
#455
0!
00
#460
1!
10
b10100000011011000101101000100111 &
#465
0!
00
#470
1!
10
b1010001011111110010110000111100 &
#475
0!
00
#480
1!
10
b11100100010100010111100000001101 &
#485
0!
00
#490
1!
10
b1110000011000101100101101101010 &
#495
0!
00
#500
1!
10
b11001110110110110100010111100011 &
1#
12
#505
0!
00
#510
1!
10
b1 6
b1110000001100111110111001000 &
0#
02
b1 5
#515
0!
00
#520
1!
10
b0 6
b1101010111011110000100101001 &
b0 5
#525
0!
00
#530
1!
10
b1011001110001010110001011010110 &
1#
12
#535
0!
00
#540
1!
10
b1 6
b1001011111010110000001101011111 &
b1 5
#545
0!
00
#550
1!
10
b10 6
b10111101101111001000011000010100 &
b10 5
#555
0!
00
#560
1!
10
b1000110110100110001000000101 &
#565
0!
00
#570
1!
10
b10001111110111111011111100000010 &
#575
0!
00
#580
1!
10
b1010001111000010000111010011011 &
#585
0!
00
#590
1!
10
b1101100100011001000100100000 &
#595
0!
00
#600
1!
10
b11010011000011111101011010100001 &
0#
02
#605
0!
00
#610
1!
10
b11 6
b10101000001101100000101111101110 &
b11 5
#615
0!
00
#620
1!
10
b0 6
b1111101110100001010001110010111 &
1#
12
b0 5
#625
0!
00
#630
1!
10
b1 6
b11111011111110001010101011101100 &
b1 5
#635
0!
00
#640
1!
10
b10 6
b10001101110101101101011111101 &
b10 5
#645
0!
00
#650
1!
10
b10001010101111010011010110011010 &
#655
0!
00
#660
1!
10
b11101010110101101011111001010011 &
#665
0!
00
#670
1!
10
b10110011111100111001111101111000 &
#675
0!
00
#680
1!
10
b11000101001111100101100011001 &
#685
0!
00
#690
1!
10
b1110110001101110100000000110 &
#695
0!
00
#700
1!
10
b11010111000101100001101011001111 &
0#
02
#705
0!
00
#710
1!
10
b11 6
b1110110110111101111101011000100 &
1#
12
b11 5
#715
0!
00
#720
1!
10
b100 6
b1111110000011101100001011110101 &
0#
02
b100 5
#725
0!
00
#730
1!
10
b101 6
b1110100101011011000111100110010 &
1#
12
b101 5
#735
0!
00
#740
1!
10
14
b1 6
b11001110011100110011010100001011 &
0#
02
1%
b11 '
b1 5
#745
0!
00
#750
1!
10
04
b0 6
b1100000111111100000100011010000 &
1#
12
0%
b0 5
#755
0!
00
#760
1!
10
b1 6
b10011010101011111001111010010001 &
b1 5
#765
0!
00
#770
1!
10
b10 6
b1101000010000000101011100011110 &
0#
02
b10 5
#775
0!
00
#780
1!
10
b11 6
b10111000100000100100100000111 &
b11 5
#785
0!
00
#790
1!
10
b0 6
b10010100110001101101010110011100 &
1#
12
b0 5
#795
0!
00
#800
1!
10
b1 6
b10001101011011111100111101101 &
b1 5
#805
0!
00
#810
1!
10
b10 6
b11110111111011110010101111001010 &
b10 5
#815
0!
00
#820
1!
10
b11011011100010010101001011000011 &
#825
0!
00
#830
1!
10
b11000111011100010110100101000 &
#835
0!
00
#840
1!
10
b111100001011010011000100001001 &
0#
02
#845
0!
00
#850
1!
10
b11 6
b10101100101101101011100100110110 &
1#
12
b11 5
#855
0!
00
#860
1!
10
b100 6
b1001110111100000000111000111111 &
b100 5
#865
0!
00
#870
1!
10
b10 6
b1110101001100111001101101110100 &
0#
02
b10 5
#875
0!
00
#880
1!
10
b11 6
b10100101011000101111111100101 &
1#
12
b11 5
#885
0!
00
#890
1!
10
b100 6
b10101110110011000110101101100010 &
b100 5
#895
0!
00
#900
1!
10
b10 6
b11000110100001111111011101111011 &
b10 5
#905
0!
00
#910
1!
10
b11011001111011010110110010000000 &
#915
0!
00
#920
1!
10
b11111110001000100110001010000001 &
0#
02
#925
0!
00
#930
1!
10
b11 6
b10100011000010100110111001001110 &
b11 5
#935
0!
00
#940
1!
10
b0 6
b10000101010000100100101001110111 &
b0 5
#945
0!
00
#950
1!
10
b1011110010101001010110001001100 &
#955
0!
00
#960
1!
10
b10000010110110011101010011011101 &
1#
12
#965
0!
00
#970
1!
10
b1 6
b10101101000110111010110111111010 &
0#
02
b1 5
#975
0!
00
#980
1!
10
b0 6
b10110100111110100000001100110011 &
1#
12
b0 5
#985
0!
00
#990
1!
10
b1 6
b10100001100100010010011011011000 &
b1 5
#995
0!
00
#1000
1!
10
b10 6
b11100111000011010001001011111001 &
0#
02
b10 5
#1005
0!
00
#1010
1!
10
b11 6
b11000010011001111101011001100110 &
b11 5
#1015
0!
00
#1020
1!
10
b0 6
b11001001011011111101110110101111 &
b0 5
#1025
0!
00
#1030
1!
10
b11011010100001010110100000100100 &
1#
12
#1035
0!
00
#1040
1!
10
b1 6
b101011010000100011100011010101 &
0#
02
b1 5
#1045
0!
00
#1050
1!
10
b0 6
b111001101111110101001110010010 &
1#
12
b0 5
#1055
0!
00
#1060
1!
10
b1 6
b1001001000001100101010111101011 &
0#
02
b1 5
#1065
0!
00
#1070
1!
10
b0 6
b100010010110101011110000110000 &
b0 5
#1075
0!
00
#1080
1!
10
b11011010011001110010001001110001 &
#1085
0!
00
#1090
1!
10
b1000011110001110101000101111110 &
1#
12
#1095
0!
00
#1100
1!
10
b1 6
b10110111001111011010011111100111 &
0#
02
b1 5
#1105
0!
00
#1110
1!
10
b0 6
b10000101110011010010111011111100 &
1#
12
b0 5
#1115
0!
00
#1120
1!
10
b1 6
b10111111101011010110101111001101 &
b1 5
#1125
0!
00
#1130
1!
10
b10 6
b10111000001001011011110000101010 &
0#
02
b10 5
#1135
0!
00
#1140
1!
10
b11 6
b11100111011111100111110100011 &
1#
12
b11 5
#1145
0!
00
#1150
1!
10
b100 6
b101001001101111000110010001000 &
0#
02
b100 5
#1155
0!
00
#1160
1!
10
b101 6
b1100000001001100111000011101001 &
b101 5
#1165
0!
00
#1170
1!
10
14
b0 6
b1100011011011010011111110010110 &
1%
b100 '
b0 5
#1175
0!
00
#1180
1!
10
04
b1101010010011001000100100011111 &
0%
#1185
0!
00
#1190
1!
10
b10001011010111110110000011010100 &
#1195
0!
00
#1200
1!
10
b11010100000111110100110111000101 &
#1205
0!
00
#1210
1!
10
b11000001110010010100011111000010 &
1#
12
#1215
0!
00
#1220
1!
10
b1 6
b10101110100101010101000001011011 &
b1 5
#1225
0!
00
#1230
1!
10
b10 6
b10110011000000001111011111100000 &
0#
02
b10 5
#1235
0!
00
#1240
1!
10
b11 6
b1011100001111001101111001100001 &
b11 5
#1245
0!
00
#1250
1!
10
b0 6
b11010010011010100000000010101110 &
b0 5
#1255
0!
00
#1260
1!
10
b11100001100110010110000101010111 &
1#
12
#1265
0!
00
#1270
1!
10
b1 6
b11010011000110110101110110101100 &
0#
02
b1 5
#1275
0!
00
#1280
1!
10
b0 6
b11001110010101111011111010111101 &
b0 5
#1285
0!
00
#1290
1!
10
b1101111101100000101011001011010 &
1#
12
#1295
0!
00
#1300
1!
10
b1 6
b10111010111100011011100000010011 &
b1 5
#1305
0!
00
#1310
1!
10
b10 6
b10110001111111000101111000111000 &
b10 5
#1315
0!
00
#1320
1!
10
b10110110000110000100101011011001 &
0#
02
#1325
0!
00
#1330
1!
10
b11 6
b1011000000110011111010011000110 &
b11 5
#1335
0!
00
#1340
1!
10
b0 6
b11010010111111010001000010001111 &
1#
12
b0 5
#1345
0!
00
#1350
1!
10
b1 6
b11011111000011001000010110000100 &
0#
02
b1 5
#1355
0!
00
#1360
1!
10
b0 6
b11000101010100101001111010110101 &
b0 5
#1365
0!
00
#1370
1!
10
b11010011111011010100011111110010 &
1#
12
#1375
0!
00
#1380
1!
10
b1 6
b1001100110111110011011001011 &
b1 5
#1385
0!
00
#1390
1!
10
b10 6
b10000011010110110001111110010000 &
0#
02
b10 5
#1395
0!
00
#1400
1!
10
b11 6
b11110000001000101001011001010001 &
b11 5
#1405
0!
00
#1410
1!
10
b0 6
b10100011101001010111101111011110 &
1#
12
b0 5
#1415
0!
00
#1420
1!
10
b1 6
b11101110101011000111011011000111 &
b1 5
#1425
0!
00
#1430
1!
10
b10 6
b1011000111010100011100001011100 &
b10 5
#1435
0!
00
#1440
1!
10
b1010000110001111100110110101101 &
#1445
0!
00
#1450
1!
10
b10100011000111100111110010001010 &
0#
02
#1455
0!
00
#1460
1!
10
b11 6
b10101000010001101011110010000011 &
b11 5
#1465
0!
00
#1470
1!
10
b0 6
b10100101110101001101111101000 &
1#
12
b0 5
#1475
0!
00
#1480
1!
10
b1 6
b10101111010000011010000011001001 &
0#
02
b1 5
#1485
0!
00
#1490
1!
10
b0 6
b1001101100000001111010111110110 &
1#
12
b0 5
#1495
0!
00
#1500
1!
10
b1 6
b10010010101110000111001111111111 &
b1 5
#1505
0!
00
#1510
1!
10
b10 6
b1001111100101111101011000110100 &
b10 5
#1515
0!
00
#1520
1!
10
b1001000101010110010101110100101 &
#1525
0!
00
#1530
1!
10
b1101111011100101010000100010 &
#1535
0!
00
#1540
1!
10
b10010110010000010001100100111011 &
0#
02
#1545
0!
00
#1550
1!
10
b11 6
b10111001101001000011001101000000 &
1#
12
b11 5
#1555
0!
00
#1560
1!
10
b100 6
b110010010101110100101001000001 &
0#
02
b100 5
#1565
0!
00
#1570
1!
10
b101 6
b1000111011001100001100001110 &
1#
12
b101 5
#1575
0!
00
#1580
1!
10
14
b1 6
b11101110100011011110100000110111 &
1%
b101 '
b1 5
#1585
0!
00
#1590
1!
10
04
b10 6
b100100101001001011111100001100 &
0%
b10 5
#1595
0!
00
#1600
1!
10
b1110100101011001001100010011101 &
#1605
0!
00
#1610
1!
10
b11001010100100110010111010111010 &
#1615
0!
00
#1620
1!
10
b11011111111101011101110011110011 &
#1625
0!
00
#1630
1!
10
b10110001000011010100010110011000 &
0#
02
#1635
0!
00
#1640
1!
10
b11 6
b10111001110000010111001010111001 &
1#
12
b11 5
#1645
0!
00
#1650
1!
10
b100 6
b101011101010100001100100110 &
0#
02
b100 5
#1655
0!
00
#1660
1!
10
b101 6
b10010110011101011011001101101111 &
b101 5
#1665
0!
00
#1670
1!
10
14
b0 6
b101001110011000101001011100100 &
1#
12
1%
b110 '
b0 5
#1675
0!
00
#1680
1!
10
04
b1 6
b101011101101111111010010010101 &
0%
b1 5
#1685
0!
00
#1690
1!
10
b10 6
b1001110010011110110110001010010 &
0#
02
b10 5
#1695
0!
00
#1700
1!
10
b11 6
b101010011010111110011110101011 &
b11 5
#1705
0!
00
#1710
1!
10
b0 6
b1011010110101110011001011110000 &
1#
12
b0 5
#1715
0!
00
#1720
1!
10
b1 6
b11011110110110011111101000110001 &
b1 5
#1725
0!
00
#1730
1!
10
b10 6
b10000000011100101101011000111110 &
0#
02
b10 5
#1735
0!
00
#1740
1!
10
b11 6
b10000111000101001011010110100111 &
b11 5
#1745
0!
00
#1750
1!
10
b0 6
b11101110011101011111000110111100 &
b0 5
#1755
0!
00
#1760
1!
10
b11100011011101010001111110001101 &
#1765
0!
00
#1770
1!
10
b110110111100010110110011101010 &
1#
12
#1775
0!
00
#1780
1!
10
b1 6
b10101110110001100001100101100011 &
b1 5
#1785
0!
00
#1790
1!
10
b10 6
b11101010011110101101101001000 &
0#
02
b10 5
#1795
0!
00
#1800
1!
10
b11 6
b11011011011101101100000010101001 &
b11 5
#1805
0!
00
#1810
1!
10
b0 6
b10000110100010011101110001010110 &
1#
12
b0 5
#1815
0!
00
#1820
1!
10
b1 6
b10011000111010111100111011011111 &
b1 5
#1825
0!
00
#1830
1!
10
b10 6
b111101001101001111101110010100 &
0#
02
b10 5
#1835
0!
00
#1840
1!
10
b11 6
b10101111110001111111100110000101 &
1#
12
b11 5
#1845
0!
00
#1850
1!
10
b100 6
b11100100010100111001000010000010 &
0#
02
b100 5
#1855
0!
00
#1860
1!
10
b101 6
b10100101110000110101001000011011 &
1#
12
b101 5
#1865
0!
00
#1870
1!
10
14
b1 6
b11111010101011110001111010100000 &
1%
b111 '
b1 5
#1875
0!
00
#1880
1!
10
04
b10 6
b11000001011010011010011000100001 &
0#
02
0%
b10 5
#1885
0!
00
#1890
1!
10
b11 6
b11100101001010101011010101101110 &
b11 5
#1895
0!
00
#1900
1!
10
b0 6
b1100011110101111101111100010111 &
1#
12
b0 5
#1905
0!
00
#1910
1!
10
b1 6
b11001001010010001101000001101100 &
0#
02
b1 5
#1915
0!
00
#1920
1!
10
b0 6
b10110010010100000110001001111101 &
b0 5
#1925
0!
00
#1930
1!
10
b1000001110111000011011100011010 &
1#
12
#1935
0!
00
#1940
1!
10
b1 6
b100011001111100111000111010011 &
0#
02
b1 5
#1945
0!
00
#1950
1!
10
b0 6
b11010110100110111101110011111000 &
1#
12
b0 5
#1955
0!
00
#1960
1!
10
b1 6
b10100010000000001000101010011001 &
0#
02
b1 5
#1965
0!
00
#1970
1!
10
b0 6
b1001100000100011100000110000110 &
b0 5
#1975
0!
00
#1980
1!
10
b10010010100100011100011001001111 &
1#
12
#1985
0!
00
#1990
1!
10
b1 6
b10001100000111001101000001000100 &
0#
02
b1 5
#1995
0!
00
#2000
1!
10
b0 6
b1111001111010100011101001110101 &
1#
12
b0 5
#2005
0!
00
#2010
1!
10
b1 6
b10111111111111011100000010110010 &
b1 5
#2015
0!
00
#2020
1!
10
b10 6
b1100001101011100101100010001011 &
b10 5
#2025
0!
00
#2030
1!
10
b1101011101001101111011001010000 &
#2035
0!
00
#2040
1!
10
b10100101100001010100111000010001 &
#2045
0!
00
#2050
1!
10
b10011110110001110110000010011110 &
#2055
0!
00
#2060
1!
10
b10100110001011100110010010000111 &
0#
02
#2065
0!
00
#2070
1!
10
b11 6
b11010010110010000101101100011100 &
1#
12
b11 5
#2075
0!
00
#2080
1!
10
b100 6
b1010010001011010110000101101101 &
0#
02
b100 5
#2085
0!
00
#2090
1!
10
b101 6
b1111101101101101000110101001010 &
1#
12
b101 5
#2095
0!
00
#2100
1!
10
14
b1 6
b1111101101001011110011001000011 &
1%
b1000 '
b1 5
#2105
0!
00
#2110
1!
10
04
b10 6
b11110000110011011100101010101000 &
0%
b10 5
#2115
0!
00
#2120
1!
10
b10010101111011101000010001001 &
#2125
0!
00
#2130
1!
10
b1110110000111111111001010110110 &
0#
02
#2135
0!
00
#2140
1!
10
b11 6
b101001100111101001100110111111 &
1#
12
b11 5
#2145
0!
00
#2150
1!
10
b100 6
b11111011100011101101000011110100 &
b100 5
#2155
0!
00
#2160
1!
10
b10 6
b10000010111011011011011101100101 &
b10 5
#2165
0!
00
#2170
1!
10
b10100010000100001111110011100010 &
0#
02
#2175
0!
00
#2180
1!
10
b11 6
b10100001010100111111101011111011 &
b11 5
#2185
0!
00
#2190
1!
10
b0 6
b1101110111110011011101000000000 &
1#
12
b0 5
#2195
0!
00
#2200
1!
10
b1 6
b1000110011010111111001000000001 &
0#
02
b1 5
#2205
0!
00
#2210
1!
10
b0 6
b11010001101110111101011111001110 &
1#
12
b0 5
#2215
0!
00
#2220
1!
10
b1 6
b1010101001011110100010111110111 &
0#
02
b1 5
#2225
0!
00
#2230
1!
10
b0 6
b11100011010111111001000111001100 &
b0 5
#2235
0!
00
#2240
1!
10
b1111111101110110001110001011101 &
1#
12
#2245
0!
00
#2250
1!
10
b1 6
b11100101101000110110111101111010 &
b1 5
#2255
0!
00
#2260
1!
10
b10 6
b10100000000000110111011010110011 &
0#
02
b10 5
#2265
0!
00
#2270
1!
10
b11 6
b11000110100000000010010001011000 &
1#
12
b11 5
#2275
0!
00
#2280
1!
10
b100 6
b10011010110011011001001001111001 &
b100 5
#2285
0!
00
#2290
1!
10
b10 6
b11111001100001110110111111100110 &
b10 5
#2295
0!
00
#2300
1!
10
b100010000010010100100100101111 &
0#
02
#2305
0!
00
#2310
1!
10
b11 6
b11010101011111110110100100 &
b11 5
#2315
0!
00
#2320
1!
10
b0 6
b111011000010111000001010101 &
b0 5
#2325
0!
00
#2330
1!
10
b1001100000100000100010100010010 &
#2335
0!
00
#2340
1!
10
b1100110110011100101101011 &
1#
12
#2345
0!
00
#2350
1!
10
b1 6
b1100100101000100110100110110000 &
b1 5
#2355
0!
00
#2360
1!
10
b10 6
b111111000111001001000111110001 &
0#
02
b10 5
#2365
0!
00
#2370
1!
10
b11 6
b10001111001110110001101011111110 &
b11 5
#2375
0!
00
#2380
1!
10
b0 6
b11001101101100011000001101100111 &
1#
12
b0 5
#2385
0!
00
#2390
1!
10
b1 6
b111110001110010111010001111100 &
0#
02
b1 5
#2395
0!
00
#2400
1!
10
b0 6
b110011011010001001001101001101 &
b0 5
#2405
0!
00
#2410
1!
10
b1101100001011101110110101010 &
1#
12
#2415
0!
00
#2420
1!
10
b1 6
b1111110000111100010001100100011 &
0#
02
b1 5
#2425
0!
00
#2430
1!
10
b0 6
b10101001000011011110101000001000 &
b0 5
#2435
0!
00
#2440
1!
10
b11111111000011101101000001101001 &
#2445
0!
00
#2450
1!
10
b11001111110110110011100100010110 &
1#
12
#2455
0!
00
#2460
1!
10
b1 6
b11001101100010001101010010011111 &
b1 5
#2465
0!
00
#2470
1!
10
b10 6
b1011101111111010101011001010100 &
b10 5
#2475
0!
00
#2480
1!
10
b1110111100101000110010101000101 &
#2485
0!
00
#2490
1!
10
b10110000001111101001100101000010 &
0#
02
#2495
0!
00
#2500
1!
10
b11 6
b11101001001010110001001111011011 &
b11 5
#2505
0!
00
#2510
1!
10
b0 6
b11111011010111000000010101100000 &
b0 5
#2515
0!
00
#2520
1!
10
b11111010010101100010110111100001 &
#2525
0!
00
#2530
1!
10
b101001110000010101000101110 &
#2535
0!
00
#2540
1!
10
b110010010011000001110011010111 &
#2545
0!
00
#2550
1!
10
b1000001010000010000001100101100 &
#2555
0!
00
#2560
1!
10
b10010001011001001100011000111101 &
#2565
0!
00
#2570
1!
10
b1010010000000001101011111011010 &
#2575
0!
00
#2580
1!
10
b10001101011111001110101110010011 &
#2585
0!
00
#2590
1!
10
b10010000100100100001101110111000 &
1#
12
#2595
0!
00
#2600
1!
10
b1 6
b1001100001000001000101001011001 &
0#
02
b1 5
#2605
0!
00
#2610
1!
10
b0 6
b100111011011100100111001000110 &
b0 5
#2615
0!
00
#2620
1!
10
b1111011100101000011110000001111 &
1#
12
#2625
0!
00
#2630
1!
10
b1 6
b10111000110011111101101100000100 &
b1 5
#2635
0!
00
#2640
1!
10
b10 6
b1100111100101011001011000110101 &
b10 5
#2645
0!
00
#2650
1!
10
b100001100111101111100101110010 &
#2655
0!
00
#2660
1!
10
b11111000011010101000101001001011 &
0#
02
#2665
0!
00
#2670
1!
10
b11 6
b11100000101000011000110100010000 &
1#
12
b11 5
#2675
0!
00
#2680
1!
10
b100 6
b10100010100101111100010111010001 &
b100 5
#2685
0!
00
#2690
1!
10
b10 6
b10101110011001100000010101011110 &
0#
02
b10 5
#2695
0!
00
#2700
1!
10
b11 6
b11011011010101100001001001000111 &
b11 5
#2705
0!
00
#2710
1!
10
b0 6
b10101001000010011110111011100 &
b0 5
#2715
0!
00
#2720
1!
10
b11011001100111101011010100101101 &
1#
12
#2725
0!
00
#2730
1!
10
b1 6
b1000011101110101111000001010 &
0#
02
b1 5
#2735
0!
00
#2740
1!
10
b0 6
b110101011001101101000000000011 &
b0 5
#2745
0!
00
#2750
1!
10
b11001011111001111011100101101000 &
1#
12
#2755
0!
00
#2760
1!
10
b1 6
b11000110011000011100000001001001 &
0#
02
b1 5
#2765
0!
00
#2770
1!
10
b0 6
b10010011010100111010111101110110 &
b0 5
#2775
0!
00
#2780
1!
10
b11101001011000100111111101111111 &
#2785
0!
00
#2790
1!
10
b1100011110110001000101110110100 &
1#
12
#2795
0!
00
#2800
1!
10
b1 6
b1111111001101000000001100100101 &
0#
02
b1 5
#2805
0!
00
#2810
1!
10
b0 6
b10000011111101000110010110100010 &
1#
12
b0 5
#2815
0!
00
#2820
1!
10
b1 6
b1111001100000001001110010111011 &
b1 5
#2825
0!
00
#2830
1!
10
b10 6
b1110000101011100000000011000000 &
b10 5
#2835
0!
00
#2840
1!
10
b10010001000000101100111000001 &
0#
02
#2845
0!
00
#2850
1!
10
b11 6
b10000010001101111010110010001110 &
b11 5
#2855
0!
00
#2860
1!
10
b0 6
b11000110111001100110001110110111 &
1#
12
b0 5
#2865
0!
00
#2870
1!
10
b1 6
b1011101010001010010010010001100 &
0#
02
b1 5
#2875
0!
00
#2880
1!
10
b0 6
b1010111110001010110000000011101 &
1#
12
b0 5
#2885
0!
00
#2890
1!
10
b1 6
b10101111000011000111000000111010 &
0#
02
b1 5
#2895
0!
00
#2900
1!
10
b0 6
b111110111000101101000001110011 &
1#
12
b0 5
#2905
0!
00
#2910
1!
10
b1 6
b10110000101010011100001100011000 &
b1 5
#2915
0!
00
#2920
1!
10
b10 6
b11011001111100010111001000111001 &
b10 5
#2925
0!
00
#2930
1!
10
b111011010111100101110010100110 &
0#
02
#2935
0!
00
#2940
1!
10
b11 6
b10110001111010101001111011101111 &
1#
12
b11 5
#2945
0!
00
#2950
1!
10
b100 6
b1111000100110100001100100 &
b100 5
#2955
0!
00
#2960
1!
10
b10 6
b1101001111111101010110000010101 &
b10 5
#2965
0!
00
#2970
1!
10
b1111011110000011101110111010010 &
#2975
0!
00
#2980
1!
10
b11010000010101000100101100101011 &
0#
02
#2985
0!
00
#2990
1!
10
b11 6
b1100110011111000110000001110000 &
b11 5
#2995
0!
00
#3000
1!
10
b0 6
b11000010111011101110100110110001 &
1#
12
b0 5
#3005
0!
00
#3010
1!
10
b1 6
b100100111000000001111110111110 &
b1 5
#3015
0!
00
#3020
1!
10
b10 6
b1000110101000001000100100111 &
b10 5
#3025
0!
00
#3030
1!
10
b11100111110101111011011100111100 &
#3035
0!
00
#3040
1!
10
b1010011010001111100011100001101 &
0#
02
#3045
0!
00
#3050
1!
10
b11 6
b11100101000110000111001101010 &
1#
12
b11 5
#3055
0!
00
#3060
1!
10
b100 6
b1000100101101111110110011100011 &
b100 5
#3065
0!
00
#3070
1!
10
b10 6
b1001011001100110011100011001000 &
0#
02
b10 5
#3075
0!
00
#3080
1!
10
b11 6
b1010101011101010000000101001 &
1#
12
b11 5
#3085
0!
00
#3090
1!
10
b100 6
b1100001000010101010111010110 &
0#
02
b100 5
#3095
0!
00
#3100
1!
10
b101 6
b10111101111000111001101001011111 &
1#
12
b101 5
#3105
0!
00
#3110
1!
10
14
b1 6
b111000011110000111000100010100 &
0#
02
1%
b1001 '
b1 5
#3115
0!
00
#3120
1!
10
04
b0 6
b11000111010001001001000100000101 &
0%
b0 5
#3125
0!
00
