Submits/RTL_Design_and_Integration_Material/Ibrahim_Verilog_Codes/2_SingleBitAdder/parametarizable_full_adder.v
module param_adder(a, b, cin, sum, cout);
	parameter WIDTH = 4;
	input [WIDTH-1:0] a, b;
	input cin;
	output reg [WIDTH-1:0] sum;
	output reg cout;

	always@(*) begin 
		{cout, sum} = a + b + cin;
	end

endmodule

Submits/RTL_Design_and_Integration_Material/Ibrahim_Verilog_Codes/2_SingleBitAdder/tb_adder.v
`include "parametarizable_full_adder.v"

module tb;
	// 1. Declare the variables
	parameter WIDTH = 4;
	reg [WIDTH-1:0] a, b;
	reg cin;
	wire [WIDTH-1:0] sum;
	wire cout;

	//2. Instantiate the design 
	param_adder DUT (.a(a), .b(b), .cin(cin), .sum(sum), .cout(cout));

	//3. Drive the inputs
	initial begin 
	repeat (20) begin 
		a = $urandom_range(0, 50);
		b = $urandom_range(0, 50);
		cin = $random;
		#2;
	end 
	end
	
	// Display outputs
	initial begin 
		$monitor("time = %0t, a = %d, b = %d, cin = %d, cout = %d, sum = %d", $time, a, b, cin, cout, sum);
	end			

	//4. Dump Signals
	initial begin
		$dumpfile("adder.vcd");
		$dumpvars;
	end	

endmodule

Submits/RTL_Design_and_Integration_Material/Ibrahim_Verilog_Codes/2_SingleBitAdder/adder.vcd
$date
	Wed Apr 19 00:22:06 2023
$end
$version
	QuestaSim Version 10.6c
$end
$timescale
	1ns
$end

$scope module tb $end
$var parameter 32 ! WIDTH $end
$var reg 4 " a [3:0] $end
$var reg 4 # b [3:0] $end
$var reg 1 $ cin $end
$var wire 1 % sum [3] $end
$var wire 1 & sum [2] $end
$var wire 1 ' sum [1] $end
$var wire 1 ( sum [0] $end
$var wire 1 ) cout $end

$scope module DUT $end
$var parameter 32 * WIDTH $end
$var wire 1 + a [3] $end
$var wire 1 , a [2] $end
$var wire 1 - a [1] $end
$var wire 1 . a [0] $end
$var wire 1 / b [3] $end
$var wire 1 0 b [2] $end
$var wire 1 1 b [1] $end
$var wire 1 2 b [0] $end
$var wire 1 3 cin $end
$var reg 4 4 sum [3:0] $end
$var reg 1 5 cout $end
$upscope $end
$upscope $end
$enddefinitions $end
#0
$dumpvars
b1001 "
b101 #
0$
b1110 4
05
b100 !
b100 *
0(
1'
1&
1%
0)
03
12
01
10
0/
1.
0-
0,
1+
$end
#2
b1 "
b1 #
1$
00
0+
13
b11 4
1(
0&
0%
#4
b1110 "
0.
1-
1,
1+
b0 4
15
0(
0'
1)
#6
b1000 "
0-
0,
b1010 4
05
1'
1%
0)
#8
b1 "
b110 #
02
11
10
1.
0+
b1000 4
0'
#10
b1101 "
b111 #
12
1,
1+
b101 4
15
1(
1&
0%
1)
#12
b101 "
b10 #
02
00
0+
b1000 4
05
0(
0&
1%
0)
#14
b1 "
b111 #
0$
12
10
0,
03
#16
b1001 "
b1001 #
1$
01
00
1/
1+
13
b11 4
15
1(
1'
0%
1)
#18
b1100 "
b0 #
02
0/
0.
1,
b1101 4
05
0'
1&
1%
0)
#20
b110 "
0$
1-
0+
03
b110 4
0(
1'
0%
#22
b0 "
b1000 #
1$
1/
0-
0,
13
b1001 4
1(
0'
0&
1%
#24
b1 "
b1 #
12
0/
1.
b11 4
1'
0%
#26
b0 "
b10 #
0$
02
11
0.
03
b10 4
0(
#28
b1100 "
b1101 #
1$
12
01
10
1/
1,
1+
13
b1010 4
15
1%
1)
#30
b0 #
0$
02
00
0/
03
b1100 4
05
0'
1&
0)
#32
b10 "
b1100 #
1$
10
1/
1-
0,
0+
13
b1111 4
1(
1'
#34
b1111 "
b1111 #
0$
12
11
1.
1,
1+
03
b1110 4
15
0(
1)
#36
b11 "
b1100 #
1$
02
01
0,
0+
13
b0 4
0'
0&
0%
#38
b1110 "
b10 #
11
00
0/
0.
1,
1+
b1 4
1(
